Workbook

Sheet All Products
I1: Material Cost | L1: Material Cost itself more than Sales Price | O1: Labour Cost itself more than Sales Price
L2: Material Cost itself more than 60% of Sales Price | O2: Labour Cost itself more than 60% of Sales Price
A3: Product_Code | B3: Customer | C3: Product_Name | D3: UoM | E3: Pack Size (UoM) | F3: Sales Price Winter 24 | G3: Sales Price Summer 26 | H3: Status | I3: RM-FOOD | J3: RM-PACKING | K3: % | L3: Labour cost Food Processing | M3: Labour cost Packing | N3: % | O3: Chemical Cost | P3: Total Cost | Q3: Winter Cash Margin | R3: Margin | S3: Avg Monthly sales qty | T3: Avg Monthly sales Value (Summer) | U3: Margin Summer price | V3: Margin Winter price | W3: Change | X3: Comment
A4: 1145CS | B4: Reynolds | C4: PREP CARROTS JULIENNE 1KG | D4: KG | E4: =VLOOKUP(A4,BOM!A:E,5,0) -> 1 | F4: 1.67 | G4: 1.72 | H4: Active | I4: =SUMIFS(BOM!Q:Q,BOM!A:A,'All Products'!A4,BOM!I:I,'All Products'!I$3) -> 0.5044471 | J4: =SUMIFS(BOM!Q:Q,BOM!A:A,'All Products'!A4,BOM!I:I,'All Products'!J$3)+0.03 -> 0.39 | K4: =(I4+J4)/G4 -> 0.52002738 | L4: =SUMIF(BOM!A:A,'All Products'!A4,BOM!S:S) -> 0.30645053 | M4: =SUMIF(BOM!A:A,'All Products'!A4,BOM!V:V) -> 0.186175 | N4: =(L4+M4)/G4 -> 0.28641019 | O4: 0 | P4: =I4+J4+M4+L4+O4 -> 1.3870726 | Q4: =G4-P4 -> 0.33292737 | R4: =IFERROR((G4-P4)/G4,0) -> 0.19356242 | S4: 5639.2 | T4: =S4*F4 -> 9417.464 | U4: =IFERROR(S4*Q4,0) -> 1877.444 | V4: =(G4-P4)*S4 -> 1877.444 | W4: =V4-U4 -> 0 | Y4: =(G4-I4)/G4 -> 0.7067168 | AF4: 2180CS
A5: 1726CS | B5: Reynolds | C5: GINGER DICED 1 X 200G | D5: KG | E5: =VLOOKUP(A5,BOM!A:E,5,0) -> 0.2 | F5: 1.37 | G5: 1.5 | H5: Active | I5: =SUMIFS(BOM!Q:Q,BOM!A:A,'All Products'!A5,BOM!I:I,'All Products'!I$3) -> 0.47625962 | J5: =SUMIFS(BOM!Q:Q,BOM!A:A,'All Products'!A5,BOM!I:I,'All Products'!J$3)+0.03 -> 0.145 | K5: =(I5+J5)/G5 -> 0.41417308 | L5: =SUMIF(BOM!A:A,'All Products'!A5,BOM!S:S) -> 0.050775 | M5: =SUMIF(BOM!A:A,'All Products'!A5,BOM!V:V) -> 0.23695 | N5: =(L5+M5)/G5 -> 0.19181667 | O5: 0 | P5: =I5+J5+M5+L5+O5 -> 0.90898462 | Q5: =G5-P5 -> 0.59101538 | R5: =IFERROR((G5-P5)/G5,0) -> 0.39401025 | S5: 0 | T5: =S5*F5 -> 0 | U5: =IFERROR(S5*Q5,0) -> 0 | V5: =(G5-P5)*S5 -> 0 | W5: =V5-U5 -> 0 | Y5: =(G5-I5)/G5 -> 0.68249359 | AC5: Above 70% Margin | AF5: Z141CS
A6: 1851CS | B6: Reynolds | C6: PREP FRUIT SALAD MIX 2KG | D6: KG | E6: =VLOOKUP(A6,BOM!A:E,5,0) -> 2.7 | F6: 9.58 | G6: 9.75 | H6: Active | I6: =SUMIFS(BOM!Q:Q,BOM!A:A,'All Products'!A6,BOM!I:I,'All Products'!I$3) -> 3.8284912 | J6: =SUMIFS(BOM!Q:Q,BOM!A:A,'All Products'!A6,BOM!I:I,'All Products'!J$3)+0.03 -> 0.75 | K6: =(I6+J6)/G6 -> 0.46958884 | L6: =SUMIF(BOM!A:A,'All Products'!A6,BOM!S:S) -> 2.5716748 | M6: =SUMIF(BOM!A:A,'All Products'!A6,BOM!V:V) -> 0.8039375 | N6: =(L6+M6)/G6 -> 0.34621665 | O6: 0 | P6: =I6+J6+M6+L6+O6 -> 7.9541035 | Q6: =G6-P6 -> 1.7958965 | R6: =IFERROR((G6-P6)/G6,0) -> 0.18419451 | S6: 2114.8 | T6: =S6*F6 -> 20259.784 | U6: =IFERROR(S6*Q6,0) -> 3797.9619 | V6: =(G6-P6)*S6 -> 3797.9619 | W6: =V6-U6 -> 0 | Y6: =(G6-I6)/G6 -> 0.60733423 | AC6: Margin Less than 25% | AF6: Z140CS
A7: 1254CS | B7: Reynolds | C7: COLESLAW DRY MIX 1KG | D7: KG | E7: =VLOOKUP(A7,BOM!A:E,5,0) -> 1 | F7: 1.91 | G7: 1.95 | H7: Active | I7: =SUMIFS(BOM!Q:Q,BOM!A:A,'All Products'!A7,BOM!I:I,'All Products'!I$3) -> 0.45953517 | J7: =SUMIFS(BOM!Q:Q,BOM!A:A,'All Products'!A7,BOM!I:I,'All Products'!J$3)+0.03 -> 0.39 | K7: =(I7+J7)/G7 -> 0.43565906 | L7: =SUMIF(BOM!A:A,'All Products'!A7,BOM!S:S) -> 0.28806692 | M7: =SUMIF(BOM!A:A,'All Products'!A7,BOM!V:V) -> 0.186175 | N7: =(L7+M7)/G7 -> 0.24320099 | O7: 0 | P7: =I7+J7+M7+L7+O7 -> 1.3237771 | Q7: =G7-P7 -> 0.62622291 | R7: =IFERROR((G7-P7)/G7,0) -> 0.32113995 | S7: 2204.8 | T7: =S7*F7 -> 4211.168 | U7: =IFERROR(S7*Q7,0) -> 1380.6963 | V7: =(G7-P7)*S7 -> 1380.6963 | W7: =V7-U7 -> 0 | Y7: =(G7-I7)/G7 -> 0.76434094 | AC7: In loss | AF7: Z139CS
A8: 1310CS | B8: Reynolds | C8: PREP ONION DICED 5mm 2.5KG | D8: KG | E8: =VLOOKUP(A8,BOM!A:E,5,0) -> 2.5 | F8: 6.33 | G8: 6.36 | H8: Active | I8: =SUMIFS(BOM!Q:Q,BOM!A:A,'All Products'!A8,BOM!I:I,'All Products'!I$3) -> 2.6479274 | J8: =SUMIFS(BOM!Q:Q,BOM!A:A,'All Products'!A8,BOM!I:I,'All Products'!J$3)+0.03 -> 0.4 | K8: =(I8+J8)/G8 -> 0.47923388 | L8: =SUMIF(BOM!A:A,'All Products'!A8,BOM!S:S) -> 0.5500625 | M8: =SUMIF(BOM!A:A,'All Products'!A8,BOM!V:V) -> 0.2961875 | N8: =(L8+M8)/G8 -> 0.13305818 | O8: 0 | P8: =I8+J8+M8+L8+O8 -> 3.8941774 | Q8: =G8-P8 -> 2.4658226 | R8: =IFERROR((G8-P8)/G8,0) -> 0.38770795 | S8: 2053.2 | T8: =S8*F8 -> 12996.756 | U8: =IFERROR(S8*Q8,0) -> 5062.8269 | V8: =(G8-P8)*S8 -> 5062.8269 | W8: =V8-U8 -> 0 | Y8: =(G8-I8)/G8 -> 0.58365921 | AF8: Z138CS
A9: 1255CS | B9: Reynolds | C9: PREP COLESLAW DRY MIX 2.5KG | D9: KG | E9: =VLOOKUP(A9,BOM!A:E,5,0) -> 2.5 | F9: 3.29 | G9: 3.37 | H9: Active | I9: =SUMIFS(BOM!Q:Q,BOM!A:A,'All Products'!A9,BOM!I:I,'All Products'!I$3) -> 1.1488379 | J9: =SUMIFS(BOM!Q:Q,BOM!A:A,'All Products'!A9,BOM!I:I,'All Products'!J$3)+0.03 -> 0.39 | K9: =(I9+J9)/G9 -> 0.45662846 | L9: =SUMIF(BOM!A:A,'All Products'!A9,BOM!S:S) -> 0.72016731 | M9: =SUMIF(BOM!A:A,'All Products'!A9,BOM!V:V) -> 0.2961875 | N9: =(L9+M9)/G9 -> 0.30158896 | O9: 0 | P9: =I9+J9+M9+L9+O9 -> 2.5551927 | Q9: =G9-P9 -> 0.81480727 | R9: =IFERROR((G9-P9)/G9,0) -> 0.24178257 | S9: 1401 | T9: =S9*F9 -> 4609.29 | U9: =IFERROR(S9*Q9,0) -> 1141.545 | V9: =(G9-P9)*S9 -> 1141.545 | W9: =V9-U9 -> 0 | Y9: =(G9-I9)/G9 -> 0.65909854 | AF9: Z353CS
A10: 103ACS | B10: Reynolds | C10: DICED RED PEPPER 4 X 750G | D10: KG | E10: =VLOOKUP(A10,BOM!A:E,5,0) -> 3 | F10: 19.57 | G10: 20.01 | H10: Active | I10: =SUMIFS(BOM!Q:Q,BOM!A:A,'All Products'!A10,BOM!I:I,'All Products'!I$3) -> 7.406725 | J10: =SUMIFS(BOM!Q:Q,BOM!A:A,'All Products'!A10,BOM!I:I,'All Products'!J$3)+0.03 -> 0.63 | K10: =(I10+J10)/G10 -> 0.40163543 | L10: =SUMIF(BOM!A:A,'All Products'!A10,BOM!S:S) -> 1.0470222 | M10: =SUMIF(BOM!A:A,'All Products'!A10,BOM!V:V) -> 0.592375 | N10: =(L10+M10)/G10 -> 0.081928897 | O10: 0 | P10: =I10+J10+M10+L10+O10 -> 9.6761222 | Q10: =G10-P10 -> 10.333878 | R10: =IFERROR((G10-P10)/G10,0) -> 0.51643567 | S10: 1733.6 | T10: =S10*F10 -> 33926.552 | U10: =IFERROR(S10*Q10,0) -> 17914.811 | V10: =(G10-P10)*S10 -> 17914.811 | W10: =V10-U10 -> 0 | Y10: =(G10-I10)/G10 -> 0.62984883 | AF10: Z352CS
A11: 785ACS | B11: Reynolds | C11: PICKLED RED CABBAGE DL 1x1.3KG | D11: KG | E11: =VLOOKUP(A11,BOM!A:E,5,0) -> 1.3 | F11: 2.52 | G11: 2.66 | H11: Active | I11: =SUMIFS(BOM!Q:Q,BOM!A:A,'All Products'!A11,BOM!I:I,'All Products'!I$3) -> 1.6191797 | J11: =SUMIFS(BOM!Q:Q,BOM!A:A,'All Products'!A11,BOM!I:I,'All Products'!J$3)+0.03 -> 0.41 | K11: =(I11+J11)/G11 -> 0.7628495 | L11: =SUMIF(BOM!A:A,'All Products'!A11,BOM!S:S) -> 0.30300815 | M11: =SUMIF(BOM!A:A,'All Products'!A11,BOM!V:V) -> 0.2183325 | N11: =(L11+M11)/G11 -> 0.19599272 | O11: 0 | P11: =I11+J11+M11+L11+O11 -> 2.5505203 | Q11: =G11-P11 -> 0.10947967 | R11: =IFERROR((G11-P11)/G11,0) -> 0.041157772 | S11: 1170.4 | T11: =S11*F11 -> 2949.408 | U11: =IFERROR(S11*Q11,0) -> 128.13501 | V11: =(G11-P11)*S11 -> 128.13501 | W11: =V11-U11 -> 0 | Y11: =(G11-I11)/G11 -> 0.39128583 | AF11: N019CS
A12: 4486CS | B12: Reynolds | C12: FRUIT CUP 6 X 200G | D12: KG | E12: =VLOOKUP(A12,BOM!A:E,5,0) -> 1.2 | F12: 12.4 | G12: 12.79 | H12: Active | I12: =SUMIFS(BOM!Q:Q,BOM!A:A,'All Products'!A12,BOM!I:I,'All Products'!I$3) -> 3.2927673 | J12: =SUMIFS(BOM!Q:Q,BOM!A:A,'All Products'!A12,BOM!I:I,'All Products'!J$3)+0.03 -> 1.85 | K12: =(I12+J12)/G12 -> 0.40209283 | L12: =SUMIF(BOM!A:A,'All Products'!A12,BOM!S:S) -> 1.0761707 | M12: =SUMIF(BOM!A:A,'All Products'!A12,BOM!V:V) -> 0.8124 | N12: =(L12+M12)/G12 -> 0.14765994 | O12: 0 | P12: =I12+J12+M12+L12+O12 -> 7.031338 | Q12: =G12-P12 -> 5.758662 | R12: =IFERROR((G12-P12)/G12,0) -> 0.45024723 | S12: 1867.6 | T12: =S12*F12 -> 23158.24 | U12: =IFERROR(S12*Q12,0) -> 10754.877 | V12: =(G12-P12)*S12 -> 10754.877 | W12: =V12-U12 -> 0 | Y12: =(G12-I12)/G12 -> 0.74255142 | AF12: N037CS
A13: 655ACS | B13: Reynolds | C13: RED ONION SLICED 3MM 4x1KG | D13: KG | E13: =VLOOKUP(A13,BOM!A:E,5,0) -> 4 | F13: 7.82 | G13: 7.43 | H13: Active | I13: =SUMIFS(BOM!Q:Q,BOM!A:A,'All Products'!A13,BOM!I:I,'All Products'!I$3) -> 4.9687155 | J13: =SUMIFS(BOM!Q:Q,BOM!A:A,'All Products'!A13,BOM!I:I,'All Products'!J$3)+0.03 -> 0.63 | K13: =(I13+J13)/G13 -> 0.75352833 | L13: =SUMIF(BOM!A:A,'All Products'!A13,BOM!S:S) -> 1.24568 | M13: =SUMIF(BOM!A:A,'All Products'!A13,BOM!V:V) -> 0.592375 | N13: =(L13+M13)/G13 -> 0.24738291 | O13: 0 | P13: =I13+J13+M13+L13+O13 -> 7.4367705 | Q13: =G13-P13 -> -0.006770495 | R13: =IFERROR((G13-P13)/G13,0) -> -0.00091123755 | S13: 982.8 | T13: =S13*F13 -> 7685.496 | U13: =IFERROR(S13*Q13,0) -> -6.6540425 | V13: =(G13-P13)*S13 -> -6.6540425 | W13: =V13-U13 -> 0 | Y13: =(G13-I13)/G13 -> 0.33126306
A14: 104ACS | B14: Reynolds | C14: 5MM SLICED LEEK 4 X 600G | D14: KG | E14: =VLOOKUP(A14,BOM!A:E,5,0) -> 2.4 | F14: 10.21 | G14: 10.44 | H14: Active | I14: =SUMIFS(BOM!Q:Q,BOM!A:A,'All Products'!A14,BOM!I:I,'All Products'!I$3) -> 3.0361446 | J14: =SUMIFS(BOM!Q:Q,BOM!A:A,'All Products'!A14,BOM!I:I,'All Products'!J$3)+0.03 -> 0.63 | K14: =(I14+J14)/G14 -> 0.35116327 | L14: =SUMIF(BOM!A:A,'All Products'!A14,BOM!S:S) -> 0.62081904 | M14: =SUMIF(BOM!A:A,'All Products'!A14,BOM!V:V) -> 0.592375 | N14: =(L14+M14)/G14 -> 0.11620633 | O14: 0 | P14: =I14+J14+M14+L14+O14 -> 4.8793386 | Q14: =G14-P14 -> 5.5606614 | R14: =IFERROR((G14-P14)/G14,0) -> 0.5326304 | S14: 1491.4 | T14: =S14*F14 -> 15227.194 | U14: =IFERROR(S14*Q14,0) -> 8293.1704 | V14: =(G14-P14)*S14 -> 8293.1704 | W14: =V14-U14 -> 0 | Y14: =(G14-I14)/G14 -> 0.70918155
A15: 1854CS | B15: Reynolds | C15: PREP ORANGE SEGMENTS 2KG | D15: KG | E15: =VLOOKUP(A15,BOM!A:E,5,0) -> 2.7 | F15: 10.47 | G15: 10.82 | H15: Active | I15: =SUMIFS(BOM!Q:Q,BOM!A:A,'All Products'!A15,BOM!I:I,'All Products'!I$3) -> 3.4745 | J15: =SUMIFS(BOM!Q:Q,BOM!A:A,'All Products'!A15,BOM!I:I,'All Products'!J$3)+0.03 -> 0.75 | K15: =(I15+J15)/G15 -> 0.39043438 | L15: =SUMIF(BOM!A:A,'All Products'!A15,BOM!S:S) -> 3.3718361 | M15: =SUMIF(BOM!A:A,'All Products'!A15,BOM!V:V) -> 0.2708 | N15: =(L15+M15)/G15 -> 0.33665768 | O15: 0 | P15: =I15+J15+M15+L15+O15 -> 7.8671361 | Q15: =G15-P15 -> 2.9528639 | R15: =IFERROR((G15-P15)/G15,0) -> 0.27290794 | S15: 989.6 | T15: =S15*F15 -> 10361.112 | U15: =IFERROR(S15*Q15,0) -> 2922.1541 | V15: =(G15-P15)*S15 -> 2922.1541 | W15: =V15-U15 -> 0 | Y15: =(G15-I15)/G15 -> 0.6788817
A16: 1522CS | B16: Reynolds | C16: STIRFRY MIX WITH KALE 6 X 500G | D16: KG | E16: =VLOOKUP(A16,BOM!A:E,5,0) -> 3 | F16: 20.46 | G16: 21.06 | H16: Active | I16: =SUMIFS(BOM!Q:Q,BOM!A:A,'All Products'!A16,BOM!I:I,'All Products'!I$3) -> 2.5344022 | J16: =SUMIFS(BOM!Q:Q,BOM!A:A,'All Products'!A16,BOM!I:I,'All Products'!J$3)+0.03 -> 0.79 | K16: =(I16+J16)/G16 -> 0.15785385 | L16: =SUMIF(BOM!A:A,'All Products'!A16,BOM!S:S) -> 1.1874686 | M16: =SUMIF(BOM!A:A,'All Products'!A16,BOM!V:V) -> 0.8124 | N16: =(L16+M16)/G16 -> 0.094960523 | O16: 0 | P16: =I16+J16+M16+L16+O16 -> 5.3242708 | Q16: =G16-P16 -> 15.735729 | R16: =IFERROR((G16-P16)/G16,0) -> 0.74718562 | S16: 0 | T16: =S16*F16 -> 0 | U16: =IFERROR(S16*Q16,0) -> 0 | V16: =(G16-P16)*S16 -> 0 | W16: =V16-U16 -> 0 | Y16: =(G16-I16)/G16 -> 0.87965802
A17: 789ACS | B17: Reynolds | C17: STIR FRY VEG DL 1x1.5KG | D17: KG | E17: =VLOOKUP(A17,BOM!A:E,5,0) -> 1.5 | F17: 6.84 | G17: 6.98 | H17: Active | I17: =SUMIFS(BOM!Q:Q,BOM!A:A,'All Products'!A17,BOM!I:I,'All Products'!I$3) -> #N/A | J17: =SUMIFS(BOM!Q:Q,BOM!A:A,'All Products'!A17,BOM!I:I,'All Products'!J$3)+0.03 -> 0.4 | K17: =(I17+J17)/G17 -> #N/A | L17: =SUMIF(BOM!A:A,'All Products'!A17,BOM!S:S) -> 0.86058562 | M17: =SUMIF(BOM!A:A,'All Products'!A17,BOM!V:V) -> 0.2183325 | N17: =(L17+M17)/G17 -> 0.1545728 | O17: 0 | P17: =I17+J17+M17+L17+O17 -> #N/A | Q17: =G17-P17 -> #N/A | R17: =IFERROR((G17-P17)/G17,0) -> 0 | S17: 105.4 | T17: =S17*F17 -> 720.936 | U17: =IFERROR(S17*Q17,0) -> 0 | V17: =(G17-P17)*S17 -> #N/A | W17: =V17-U17 -> #N/A | Y17: =(G17-I17)/G17 -> #N/A
A18: 1185CS | B18: Reynolds | C18: PREP CABBAGE RED SHRED 2.5KG | D18: KG | E18: =VLOOKUP(A18,BOM!A:E,5,0) -> 2.5 | F18: 3.87 | G18: 3.95 | H18: Active | I18: =SUMIFS(BOM!Q:Q,BOM!A:A,'All Products'!A18,BOM!I:I,'All Products'!I$3) -> 1.6636047 | J18: =SUMIFS(BOM!Q:Q,BOM!A:A,'All Products'!A18,BOM!I:I,'All Products'!J$3)+0.03 -> 0.4 | K18: =(I18+J18)/G18 -> 0.52243158 | L18: =SUMIF(BOM!A:A,'All Products'!A18,BOM!S:S) -> 0.64536354 | M18: =SUMIF(BOM!A:A,'All Products'!A18,BOM!V:V) -> 0.2961875 | N18: =(L18+M18)/G18 -> 0.23836735 | O18: 0 | P18: =I18+J18+M18+L18+O18 -> 3.0051558 | Q18: =G18-P18 -> 0.94484422 | R18: =IFERROR((G18-P18)/G18,0) -> 0.23920107 | S18: 1063.8 | T18: =S18*F18 -> 4116.906 | U18: =IFERROR(S18*Q18,0) -> 1005.1253 | V18: =(G18-P18)*S18 -> 1005.1253 | W18: =V18-U18 -> 0 | Y18: =(G18-I18)/G18 -> 0.57883424
A19: 1536CS | B19: Reynolds | C19: BUTTERNUTSQSH DICED 25MM 2.5KG | D19: KG | E19: =VLOOKUP(A19,BOM!A:E,5,0) -> 2.5 | F19: 7.83 | G19: 7.81 | H19: Active | I19: =SUMIFS(BOM!Q:Q,BOM!A:A,'All Products'!A19,BOM!I:I,'All Products'!I$3) -> 2.2569444 | J19: =SUMIFS(BOM!Q:Q,BOM!A:A,'All Products'!A19,BOM!I:I,'All Products'!J$3)+0.03 -> 0.4 | K19: =(I19+J19)/G19 -> 0.34019775 | L19: =SUMIF(BOM!A:A,'All Products'!A19,BOM!S:S) -> 2.47105 | M19: =SUMIF(BOM!A:A,'All Products'!A19,BOM!V:V) -> 0.2961875 | N19: =(L19+M19)/G19 -> 0.35431978 | O19: 0 | P19: =I19+J19+M19+L19+O19 -> 5.4241819 | Q19: =G19-P19 -> 2.3858181 | R19: =IFERROR((G19-P19)/G19,0) -> 0.30548247 | S19: 1086.8 | T19: =S19*F19 -> 8509.644 | U19: =IFERROR(S19*Q19,0) -> 2592.9071 | V19: =(G19-P19)*S19 -> 2592.9071 | W19: =V19-U19 -> 0 | Y19: =(G19-I19)/G19 -> 0.71101864
A20: 808ACS | B20: Reynolds | C20: COURGETTI 2 X 500G | D20: KG | E20: =VLOOKUP(A20,BOM!A:E,5,0) -> 1 | F20: 4.98 | G20: 5.07 | H20: In Active | I20: =SUMIFS(BOM!Q:Q,BOM!A:A,'All Products'!A20,BOM!I:I,'All Products'!I$3) -> 0 | J20: =SUMIFS(BOM!Q:Q,BOM!A:A,'All Products'!A20,BOM!I:I,'All Products'!J$3)+0.03 -> 0.49 | K20: =(I20+J20)/G20 -> 0.096646943 | L20: =SUMIF(BOM!A:A,'All Products'!A20,BOM!S:S) -> 0.03385 | M20: =SUMIF(BOM!A:A,'All Products'!A20,BOM!V:V) -> 0.355425 | N20: =(L20+M20)/G20 -> 0.076780079 | O20: 0 | P20: =I20+J20+M20+L20+O20 -> 0.879275 | Q20: =G20-P20 -> 4.190725 | R20: =IFERROR((G20-P20)/G20,0) -> 0.82657298 | Y20: =(G20-I20)/G20 -> 1
A21: 1480CS | B21: Reynolds | C21: PREP ROOT VEG MIX CHNKY 2.5KG | D21: KG | E21: =VLOOKUP(A21,BOM!A:E,5,0) -> 2.5 | F21: 6.19 | G21: 6.24 | H21: Active | I21: =SUMIFS(BOM!Q:Q,BOM!A:A,'All Products'!A21,BOM!I:I,'All Products'!I$3) -> 2.3774492 | J21: =SUMIFS(BOM!Q:Q,BOM!A:A,'All Products'!A21,BOM!I:I,'All Products'!J$3)+0.03 -> 0.4 | K21: =(I21+J21)/G21 -> 0.44510404 | L21: =SUMIF(BOM!A:A,'All Products'!A21,BOM!S:S) -> 1.5760524 | M21: =SUMIF(BOM!A:A,'All Products'!A21,BOM!V:V) -> 0.2961875 | N21: =(L21+M21)/G21 -> 0.30003844 | O21: 0 | P21: =I21+J21+M21+L21+O21 -> 4.6496891 | Q21: =G21-P21 -> 1.5903109 | R21: =IFERROR((G21-P21)/G21,0) -> 0.25485752 | S21: 418.6 | T21: =S21*G21 -> 2612.064 | U21: =IFERROR(S21*Q21,0) -> 665.70416 | V21: =(G21-P21)*S21 -> 665.70416 | W21: =V21-U21 -> 0 | Y21: =(G21-I21)/G21 -> 0.61899853
A22: 1303CS | B22: Reynolds | C22: PREP WHITE ONION SLICED 2.5KG | D22: KG | E22: =VLOOKUP(A22,BOM!A:E,5,0) -> 2.5 | F22: 5.94 | G22: 5.98 | H22: Active | I22: =SUMIFS(BOM!Q:Q,BOM!A:A,'All Products'!A22,BOM!I:I,'All Products'!I$3) -> 2.4369562 | J22: =SUMIFS(BOM!Q:Q,BOM!A:A,'All Products'!A22,BOM!I:I,'All Products'!J$3)+0.03 -> 0.4 | K22: =(I22+J22)/G22 -> 0.47440738 | L22: =SUMIF(BOM!A:A,'All Products'!A22,BOM!S:S) -> 0.6177625 | M22: =SUMIF(BOM!A:A,'All Products'!A22,BOM!V:V) -> 0.2961875 | N22: =(L22+M22)/G22 -> 0.15283445 | O22: 0 | P22: =I22+J22+M22+L22+O22 -> 3.7509062 | Q22: =G22-P22 -> 2.2290938 | R22: =IFERROR((G22-P22)/G22,0) -> 0.37275817 | S22: 751.2 | T22: =S22*G22 -> 4492.176 | U22: =IFERROR(S22*Q22,0) -> 1674.4953 | V22: =(G22-P22)*S22 -> 1674.4953 | W22: =V22-U22 -> 0 | Y22: =(G22-I22)/G22 -> 0.59248225
A23: 1180CS | B23: Reynolds | C23: RED CABBAGE N CARROT SLAW 2X1K | D23: KG | E23: =VLOOKUP(A23,BOM!A:E,5,0) -> 2 | F23: 2.17 | G23: 2.33 | H23: Active | I23: =SUMIFS(BOM!Q:Q,BOM!A:A,'All Products'!A23,BOM!I:I,'All Products'!I$3) -> 1.0693587 | J23: =SUMIFS(BOM!Q:Q,BOM!A:A,'All Products'!A23,BOM!I:I,'All Products'!J$3)+0.03 -> 0.47 | K23: =(I23+J23)/G23 -> 0.66066899 | L23: =SUMIF(BOM!A:A,'All Products'!A23,BOM!S:S) -> 0.60690892 | M23: =SUMIF(BOM!A:A,'All Products'!A23,BOM!V:V) -> 0.2961875 | N23: =(L23+M23)/G23 -> 0.38759503 | O23: 0 | P23: =I23+J23+M23+L23+O23 -> 2.4424552 | Q23: =G23-P23 -> -0.11245517 | R23: =IFERROR((G23-P23)/G23,0) -> -0.04826402 | S23: 613.4 | T23: =S23*G23 -> 1429.222 | U23: =IFERROR(S23*Q23,0) -> -68.979999 | V23: =(G23-P23)*S23 -> -68.979999 | W23: =V23-U23 -> 0 | Y23: =(G23-I23)/G23 -> 0.54104775
A24: 765ACS | B24: Reynolds | C24: COLESLAW MIX 8x500G | D24: KG | E24: =VLOOKUP(A24,BOM!A:E,5,0) -> 4 | F24: 10.32 | G24: 10.6 | H24: Active | I24: =SUMIFS(BOM!Q:Q,BOM!A:A,'All Products'!A24,BOM!I:I,'All Products'!I$3) -> 2.0203659 | J24: =SUMIFS(BOM!Q:Q,BOM!A:A,'All Products'!A24,BOM!I:I,'All Products'!J$3)+0.03 -> 0.95 | K24: =(I24+J24)/G24 -> 0.2802232 | L24: =SUMIF(BOM!A:A,'All Products'!A24,BOM!S:S) -> 1.1291919 | M24: =SUMIF(BOM!A:A,'All Products'!A24,BOM!V:V) -> 0.77855 | N24: =(L24+M24)/G24 -> 0.17997565 | O24: 0 | P24: =I24+J24+M24+L24+O24 -> 4.8781078 | Q24: =G24-P24 -> 5.7218922 | R24: =IFERROR((G24-P24)/G24,0) -> 0.53980115 | S24: 576.2 | T24: =S24*G24 -> 6107.72 | U24: =IFERROR(S24*Q24,0) -> 3296.9543 | V24: =(G24-P24)*S24 -> 3296.9543 | W24: =V24-U24 -> 0 | Y24: =(G24-I24)/G24 -> 0.80939945
A25: 1855CS | B25: Reynolds | C25: PREP GRAPEFRUIT PINK SEG 2KG | D25: KG | E25: =VLOOKUP(A25,BOM!A:E,5,0) -> 2.7 | F25: 15 | G25: 15.38 | H25: Active | I25: =SUMIFS(BOM!Q:Q,BOM!A:A,'All Products'!A25,BOM!I:I,'All Products'!I$3) -> 4.6594846 | J25: =SUMIFS(BOM!Q:Q,BOM!A:A,'All Products'!A25,BOM!I:I,'All Products'!J$3)+0.03 -> 0.75 | K25: =(I25+J25)/G25 -> 0.35172202 | L25: =SUMIF(BOM!A:A,'All Products'!A25,BOM!S:S) -> 3.2022264 | M25: =SUMIF(BOM!A:A,'All Products'!A25,BOM!V:V) -> 0.2708 | N25: =(L25+M25)/G25 -> 0.22581446 | O25: 0 | P25: =I25+J25+M25+L25+O25 -> 8.882511 | Q25: =G25-P25 -> 6.497489 | R25: =IFERROR((G25-P25)/G25,0) -> 0.42246352 | S25: 518 | T25: =S25*G25 -> 7966.84 | U25: =IFERROR(S25*Q25,0) -> 3365.6993 | V25: =(G25-P25)*S25 -> 3365.6993 | W25: =V25-U25 -> 0 | Y25: =(G25-I25)/G25 -> 0.69704261
A26: 1822CS | B26: Reynolds | C26: LEMON WEDGES X 2KG | D26: KG | E26: =VLOOKUP(A26,BOM!A:E,5,0) -> 2 | F26: 6.32 | G26: 6.78 | H26: Active | I26: =SUMIFS(BOM!Q:Q,BOM!A:A,'All Products'!A26,BOM!I:I,'All Products'!I$3) -> 2.2985455 | J26: =SUMIFS(BOM!Q:Q,BOM!A:A,'All Products'!A26,BOM!I:I,'All Products'!J$3)+0.03 -> 0.75 | K26: =(I26+J26)/G26 -> 0.44963797 | L26: =SUMIF(BOM!A:A,'All Products'!A26,BOM!S:S) -> 2.3976211 | M26: =SUMIF(BOM!A:A,'All Products'!A26,BOM!V:V) -> 0.2708 | N26: =(L26+M26)/G26 -> 0.39357243 | O26: 0 | P26: =I26+J26+M26+L26+O26 -> 5.7169666 | Q26: =G26-P26 -> 1.0630334 | R26: =IFERROR((G26-P26)/G26,0) -> 0.15678959 | S26: 171.8 | T26: =S26*G26 -> 1164.804 | U26: =IFERROR(S26*Q26,0) -> 182.62914 | V26: =(G26-P26)*S26 -> 182.62914 | W26: =V26-U26 -> 0 | Y26: =(G26-I26)/G26 -> 0.6609815
A27: 719ACS | B27: Reynolds | C27: BENUGO PREP PINEAPPLE CUBE 2KG | D27: KG | E27: =VLOOKUP(A27,BOM!A:E,5,0) -> 2.7 | F27: 10.06 | G27: 10.26 | H27: Active | I27: =SUMIFS(BOM!Q:Q,BOM!A:A,'All Products'!A27,BOM!I:I,'All Products'!I$3) -> 3.5441 | J27: =SUMIFS(BOM!Q:Q,BOM!A:A,'All Products'!A27,BOM!I:I,'All Products'!J$3)+0.03 -> 0.75 | K27: =(I27+J27)/G27 -> 0.41852827 | L27: =SUMIF(BOM!A:A,'All Products'!A27,BOM!S:S) -> 1.0980321 | M27: =SUMIF(BOM!A:A,'All Products'!A27,BOM!V:V) -> 0.2708 | N27: =(L27+M27)/G27 -> 0.13341443 | O27: 0 | P27: =I27+J27+M27+L27+O27 -> 5.6629321 | Q27: =G27-P27 -> 4.5970679 | R27: =IFERROR((G27-P27)/G27,0) -> 0.4480573 | S27: 143.8 | T27: =S27*G27 -> 1475.388 | U27: =IFERROR(S27*Q27,0) -> 661.05837 | V27: =(G27-P27)*S27 -> 661.05837 | W27: =V27-U27 -> 0 | Y27: =(G27-I27)/G27 -> 0.65457115
A28: 1174CS | B28: Reynolds | C28: PREP CARROTS GRATED 4 X 1KG | D28: KG | E28: =VLOOKUP(A28,BOM!A:E,5,0) -> 4 | F28: 6.36 | G28: 6.56 | H28: Active | I28: =SUMIFS(BOM!Q:Q,BOM!A:A,'All Products'!A28,BOM!I:I,'All Products'!I$3) -> 2.0177884 | J28: =SUMIFS(BOM!Q:Q,BOM!A:A,'All Products'!A28,BOM!I:I,'All Products'!J$3)+0.03 -> 0.63 | K28: =(I28+J28)/G28 -> 0.40362628 | L28: =SUMIF(BOM!A:A,'All Products'!A28,BOM!S:S) -> 1.2258021 | M28: =SUMIF(BOM!A:A,'All Products'!A28,BOM!V:V) -> 0.592375 | N28: =(L28+M28)/G28 -> 0.27716115 | O28: 0 | P28: =I28+J28+M28+L28+O28 -> 4.4659655 | Q28: =G28-P28 -> 2.0940345 | R28: =IFERROR((G28-P28)/G28,0) -> 0.31921257 | S28: 325.8 | T28: =S28*G28 -> 2137.248 | U28: =IFERROR(S28*Q28,0) -> 682.23643 | V28: =(G28-P28)*S28 -> 682.23643 | W28: =V28-U28 -> 0 | Y28: =(G28-I28)/G28 -> 0.69241031
A29: 1852CS | B29: Reynolds | C29: PREP FRUIT SALAD TROP 2KG | D29: KG | E29: =VLOOKUP(A29,BOM!A:E,5,0) -> 2.7 | F29: 11.75 | G29: 12.09 | H29: Active | I29: =SUMIFS(BOM!Q:Q,BOM!A:A,'All Products'!A29,BOM!I:I,'All Products'!I$3) -> 5.530457 | J29: =SUMIFS(BOM!Q:Q,BOM!A:A,'All Products'!A29,BOM!I:I,'All Products'!J$3)+0.03 -> 0.75 | K29: =(I29+J29)/G29 -> 0.51947535 | L29: =SUMIF(BOM!A:A,'All Products'!A29,BOM!S:S) -> 3.0905482 | M29: =SUMIF(BOM!A:A,'All Products'!A29,BOM!V:V) -> 0.6093 | N29: =(L29+M29)/G29 -> 0.30602549 | O29: 0 | P29: =I29+J29+M29+L29+O29 -> 9.9803052 | Q29: =G29-P29 -> 2.1096948 | R29: =IFERROR((G29-P29)/G29,0) -> 0.17449916 | S29: 291.2 | T29: =S29*G29 -> 3520.608 | U29: =IFERROR(S29*Q29,0) -> 614.34313 | V29: =(G29-P29)*S29 -> 614.34313 | W29: =V29-U29 -> 0 | Y29: =(G29-I29)/G29 -> 0.54255939
A30: 502ACS | B30: Reynolds | C30: NHS PREP STEW PACK 2.5KG | D30: KG | E30: =VLOOKUP(A30,BOM!A:E,5,0) -> 2.5 | F30: 8.09 | G30: 8.42 | H30: Active | I30: =SUMIFS(BOM!Q:Q,BOM!A:A,'All Products'!A30,BOM!I:I,'All Products'!I$3) -> 2.1436438 | J30: =SUMIFS(BOM!Q:Q,BOM!A:A,'All Products'!A30,BOM!I:I,'All Products'!J$3)+0.03 -> 0.4 | K30: =(I30+J30)/G30 -> 0.30209547 | L30: =SUMIF(BOM!A:A,'All Products'!A30,BOM!S:S) -> 2.8236506 | M30: =SUMIF(BOM!A:A,'All Products'!A30,BOM!V:V) -> 0.2961875 | N30: =(L30+M30)/G30 -> 0.37052709 | O30: 0 | P30: =I30+J30+M30+L30+O30 -> 5.6634819 | Q30: =G30-P30 -> 2.7565181 | R30: =IFERROR((G30-P30)/G30,0) -> 0.32737744 | S30: 282.6 | T30: =S30*G30 -> 2379.492 | U30: =IFERROR(S30*Q30,0) -> 778.99201 | V30: =(G30-P30)*S30 -> 778.99201 | W30: =V30-U30 -> 0 | Y30: =(G30-I30)/G30 -> 0.74541047
A31: 1298CS | B31: Reynolds | C31: PREP ONION RED SLICED 2.5KG | D31: KG | E31: =VLOOKUP(A31,BOM!A:E,5,0) -> 2.5 | F31: 6.48 | G31: 6.01 | H31: Active | I31: =SUMIFS(BOM!Q:Q,BOM!A:A,'All Products'!A31,BOM!I:I,'All Products'!I$3) -> 3.1877446 | J31: =SUMIFS(BOM!Q:Q,BOM!A:A,'All Products'!A31,BOM!I:I,'All Products'!J$3)+0.03 -> 0.4 | K31: =(I31+J31)/G31 -> 0.5969625 | L31: =SUMIF(BOM!A:A,'All Products'!A31,BOM!S:S) -> 0.6177625 | M31: =SUMIF(BOM!A:A,'All Products'!A31,BOM!V:V) -> 0.2961875 | N31: =(L31+M31)/G31 -> 0.15207155 | O31: 0 | P31: =I31+J31+M31+L31+O31 -> 4.5016946 | Q31: =G31-P31 -> 1.5083054 | R31: =IFERROR((G31-P31)/G31,0) -> 0.25096595 | S31: 315.4 | T31: =S31*G31 -> 1895.554 | U31: =IFERROR(S31*Q31,0) -> 475.71951 | V31: =(G31-P31)*S31 -> 475.71951 | W31: =V31-U31 -> 0 | Y31: =(G31-I31)/G31 -> 0.46959324
A32: 484ACS | B32: Reynolds | C32: NHS DICED ONION 15MM 2.5KG | D32: KG | E32: =VLOOKUP(A32,BOM!A:E,5,0) -> 2.5 | F32: 7.01 | G32: 7.09 | H32: Active | I32: =SUMIFS(BOM!Q:Q,BOM!A:A,'All Products'!A32,BOM!I:I,'All Products'!I$3) -> 2.4336637 | J32: =SUMIFS(BOM!Q:Q,BOM!A:A,'All Products'!A32,BOM!I:I,'All Products'!J$3)+0.03 -> 0.4 | K32: =(I32+J32)/G32 -> 0.39967048 | L32: =SUMIF(BOM!A:A,'All Products'!A32,BOM!S:S) -> 0.423125 | M32: =SUMIF(BOM!A:A,'All Products'!A32,BOM!V:V) -> 0.2961875 | N32: =(L32+M32)/G32 -> 0.10145451 | O32: 0 | P32: =I32+J32+M32+L32+O32 -> 3.5529762 | Q32: =G32-P32 -> 3.5370238 | R32: =IFERROR((G32-P32)/G32,0) -> 0.49887501 | S32: 280.2 | T32: =S32*G32 -> 1986.618 | U32: =IFERROR(S32*Q32,0) -> 991.07407 | V32: =(G32-P32)*S32 -> 991.07407 | W32: =V32-U32 -> 0 | Y32: =(G32-I32)/G32 -> 0.65674701
... A41: 1311CS | B41: Reynolds | C41: PREP DICED ONION 5MM 1KG | D41: KG | E41: =VLOOKUP(A41,BOM!A:E,5,0) -> 1 | F41: 3.59 | G41: 3.62 | H41: Active | I41: =SUMIFS(BOM!Q:Q,BOM!A:A,'All Products'!A41,BOM!I:I,'All Products'!I$3) -> 1.059171 | J41: =SUMIFS(BOM!Q:Q,BOM!A:A,'All Products'!A41,BOM!I:I,'All Products'!J$3)+0.03 -> 0.4 | K41: =(I41+J41)/G41 -> 0.40308591 | L41: =SUMIF(BOM!A:A,'All Products'!A41,BOM!S:S) -> 0.220025 | M41: =SUMIF(BOM!A:A,'All Products'!A41,BOM!V:V) -> 0.2183325 | N41: =(L41+M41)/G41 -> 0.12109323 | O41: 0 | P41: =I41+J41+M41+L41+O41 -> 1.8975285 | Q41: =G41-P41 -> 1.7224715 | R41: =IFERROR((G41-P41)/G41,0) -> 0.47582086 | S41: 154.2 | T41: =S41*G41 -> 558.204 | U41: =IFERROR(S41*Q41,0) -> 265.60511 | V41: =(G41-P41)*S41 -> 265.60511 | W41: =V41-U41 -> 0 | Y41: =(G41-I41)/G41 -> 0.70741133
A42: 1193CS | B42: Reynolds | C42: PREP CABBAGE WHITE SHRED 2.5KG | D42: KG | E42: =VLOOKUP(A42,BOM!A:E,5,0) -> 2.5 | F42: 3.53 | G42: 3.6 | H42: Active | I42: =SUMIFS(BOM!Q:Q,BOM!A:A,'All Products'!A42,BOM!I:I,'All Products'!I$3) -> 1.4568326 | J42: =SUMIFS(BOM!Q:Q,BOM!A:A,'All Products'!A42,BOM!I:I,'All Products'!J$3)+0.03 -> 0.4 | K42: =(I42+J42)/G42 -> 0.51578685 | L42: =SUMIF(BOM!A:A,'All Products'!A42,BOM!S:S) -> 0.70047058 | M42: =SUMIF(BOM!A:A,'All Products'!A42,BOM!V:V) -> 0.2961875 | N42: =(L42+M42)/G42 -> 0.27684947 | O42: 0 | P42: =I42+J42+M42+L42+O42 -> 2.8534907 | Q42: =G42-P42 -> 0.74650927 | R42: =IFERROR((G42-P42)/G42,0) -> 0.20736369 | S42: 286.4 | T42: =S42*G42 -> 1031.04 | U42: =IFERROR(S42*Q42,0) -> 213.80026 | V42: =(G42-P42)*S42 -> 213.80026 | W42: =V42-U42 -> 0 | Y42: =(G42-I42)/G42 -> 0.59532427 | AA42: 2.86 | AB42: 2.44
A43: 487ACS | B43: Reynolds | C43: NHS PREP POTS QUARTERED 5KG | D43: KG | E43: =VLOOKUP(A43,BOM!A:E,5,0) -> 5 | F43: 9.26 | G43: 8.18 | H43: Active | I43: =SUMIFS(BOM!Q:Q,BOM!A:A,'All Products'!A43,BOM!I:I,'All Products'!I$3) -> 2.1049715 | J43: =SUMIFS(BOM!Q:Q,BOM!A:A,'All Products'!A43,BOM!I:I,'All Products'!J$3)+0.03 -> 0.4 | K43: =(I43+J43)/G43 -> 0.30623124 | L43: =SUMIF(BOM!A:A,'All Products'!A43,BOM!S:S) -> 4.518165 | M43: =SUMIF(BOM!A:A,'All Products'!A43,BOM!V:V) -> 0.4011225 | N43: =(L43+M43)/G43 -> 0.60137989 | O43: 0 | P43: =I43+J43+M43+L43+O43 -> 7.424259 | Q43: =G43-P43 -> 0.755741 | R43: =IFERROR((G43-P43)/G43,0) -> 0.092388876 | S43: 121.4 | T43: =S43*G43 -> 993.052 | U43: =IFERROR(S43*Q43,0) -> 91.746958 | V43: =(G43-P43)*S43 -> 91.746958 | W43: =V43-U43 -> 0 | Y43: =(G43-I43)/G43 -> 0.74266852
A44: 1335CS | B44: Reynolds | C44: PREP SWEET POTS WHOLE 2.5KG | D44: KG | E44: =VLOOKUP(A44,BOM!A:E,5,0) -> 2.5 | F44: 6.99 | G44: 6.41 | H44: Active | I44: =SUMIFS(BOM!Q:Q,BOM!A:A,'All Products'!A44,BOM!I:I,'All Products'!I$3) -> 2.6748397 | J44: =SUMIFS(BOM!Q:Q,BOM!A:A,'All Products'!A44,BOM!I:I,'All Products'!J$3)+0.03 -> 0.4 | K44: =(I44+J44)/G44 -> 0.47969419 | L44: =SUMIF(BOM!A:A,'All Products'!A44,BOM!S:S) -> 1.0250871 | M44: =SUMIF(BOM!A:A,'All Products'!A44,BOM!V:V) -> 0.2961875 | N44: =(L44+M44)/G44 -> 0.20612709 | O44: 0 | P44: =I44+J44+M44+L44+O44 -> 4.3961144 | Q44: =G44-P44 -> 2.0138856 | R44: =IFERROR((G44-P44)/G44,0) -> 0.31417872 | S44: 23.8 | T44: =S44*G44 -> 152.558 | U44: =IFERROR(S44*Q44,0) -> 47.930478 | V44: =(G44-P44)*S44 -> 47.930478 | W44: =V44-U44 -> 0 | Y44: =(G44-I44)/G44 -> 0.58270831
A45: 280ACS | B45: Reynolds | C45: NHS PREP SLICED CARROT 2.5KG | D45: KG | E45: =VLOOKUP(A45,BOM!A:E,5,0) -> 2.5 | F45: 4.04 | G45: 4.37 | H45: Active | I45: =SUMIFS(BOM!Q:Q,BOM!A:A,'All Products'!A45,BOM!I:I,'All Products'!I$3) -> 1.3221807 | J45: =SUMIFS(BOM!Q:Q,BOM!A:A,'All Products'!A45,BOM!I:I,'All Products'!J$3)+0.03 -> 0.4 | K45: =(I45+J45)/G45 -> 0.39409168 | L45: =SUMIF(BOM!A:A,'All Products'!A45,BOM!S:S) -> 1.4480148 | M45: =SUMIF(BOM!A:A,'All Products'!A45,BOM!V:V) -> 0.2961875 | N45: =(L45+M45)/G45 -> 0.39913096 | O45: 0 | P45: =I45+J45+M45+L45+O45 -> 3.466383 | Q45: =G45-P45 -> 0.90361703 | R45: =IFERROR((G45-P45)/G45,0) -> 0.20677735 | S45: 123.8 | T45: =S45*G45 -> 541.006 | U45: =IFERROR(S45*Q45,0) -> 111.86779 | V45: =(G45-P45)*S45 -> 111.86779 | W45: =V45-U45 -> 0 | Y45: =(G45-I45)/G45 -> 0.6974415
A46: 489ACS | B46: Reynolds | C46: NHS DICED BUTTERNUT 15MM 1KG | D46: KG | E46: =VLOOKUP(A46,BOM!A:E,5,0) -> 1 | F46: 2.33 | G46: 2.31 | H46: Active | I46: =SUMIFS(BOM!Q:Q,BOM!A:A,'All Products'!A46,BOM!I:I,'All Products'!I$3) -> 0.89652024 | J46: =SUMIFS(BOM!Q:Q,BOM!A:A,'All Products'!A46,BOM!I:I,'All Products'!J$3)+0.03 -> 0.4 | K46: =(I46+J46)/G46 -> 0.56126417 | L46: =SUMIF(BOM!A:A,'All Products'!A46,BOM!S:S) -> 0.57639525 | M46: =SUMIF(BOM!A:A,'All Products'!A46,BOM!V:V) -> 0.2183325 | N46: =(L46+M46)/G46 -> 0.34403799 | O46: 0 | P46: =I46+J46+M46+L46+O46 -> 2.091248 | Q46: =G46-P46 -> 0.21875201 | R46: =IFERROR((G46-P46)/G46,0) -> 0.094697838 | S46: 101.8 | T46: =S46*G46 -> 235.158 | U46: =IFERROR(S46*Q46,0) -> 22.268954 | V46: =(G46-P46)*S46 -> 22.268954 | W46: =V46-U46 -> 0 | Y46: =(G46-I46)/G46 -> 0.611896 | AA46: 553CEA COLESLAW MIX 1x500G
A47: 278ACS | B47: Reynolds | C47: NHS PREP DICED POTATO 20MM 5KG | D47: KG | E47: =VLOOKUP(A47,BOM!A:E,5,0) -> 5 | F47: 7.74 | G47: 7.28 | H47: Active | I47: =SUMIFS(BOM!Q:Q,BOM!A:A,'All Products'!A47,BOM!I:I,'All Products'!I$3) -> 4.6556129 | J47: =SUMIFS(BOM!Q:Q,BOM!A:A,'All Products'!A47,BOM!I:I,'All Products'!J$3)+0.03 -> 0.4 | K47: =(I47+J47)/G47 -> 0.69445232 | L47: =SUMIF(BOM!A:A,'All Products'!A47,BOM!S:S) -> 3.4814543 | M47: =SUMIF(BOM!A:A,'All Products'!A47,BOM!V:V) -> 0.4011225 | N47: =(L47+M47)/G47 -> 0.53332099 | O47: 0 | P47: =I47+J47+M47+L47+O47 -> 8.9381897 | Q47: =G47-P47 -> -1.6581897 | R47: =IFERROR((G47-P47)/G47,0) -> -0.22777331 | S47: 41 | T47: =S47*G47 -> 298.48 | U47: =IFERROR(S47*Q47,0) -> -67.985778 | V47: =(G47-P47)*S47 -> -67.985778 | W47: =V47-U47 -> 0 | Y47: =(G47-I47)/G47 -> 0.36049273 | AA47: N114CS COLESLAW MIX 1x500G
A48: 584ACS | B48: Reynolds | C48: PICKLED MOOLI 4 X 1.3KG | D48: KG | E48: =VLOOKUP(A48,BOM!A:E,5,0) -> 5.2 | F48: 17.24 | G48: 17.39 | H48: Active | I48: =SUMIFS(BOM!Q:Q,BOM!A:A,'All Products'!A48,BOM!I:I,'All Products'!I$3) -> 10.397029 | J48: =SUMIFS(BOM!Q:Q,BOM!A:A,'All Products'!A48,BOM!I:I,'All Products'!J$3)+0.03 -> 0.71 | K48: =(I48+J48)/G48 -> 0.63870205 | L48: =SUMIF(BOM!A:A,'All Products'!A48,BOM!S:S) -> 2.0633735 | M48: =SUMIF(BOM!A:A,'All Products'!A48,BOM!V:V) -> 0.822555 | N48: =(L48+M48)/G48 -> 0.16595333 | O48: 0 | P48: =I48+J48+M48+L48+O48 -> 13.992957 | Q48: =G48-P48 -> 3.3970429 | R48: =IFERROR((G48-P48)/G48,0) -> 0.19534462 | S48: 159.6 | T48: =S48*G48 -> 2775.444 | U48: =IFERROR(S48*Q48,0) -> 542.16805 | V48: =(G48-P48)*S48 -> 542.16805 | W48: =V48-U48 -> 0 | Y48: =(G48-I48)/G48 -> 0.40212602
A49: 497ACS | B49: Reynolds | C49: NHS DICED ONION 5MM 2.5KG | D49: KG | E49: =VLOOKUP(A49,BOM!A:E,5,0) -> 2.5 | F49: 6.33 | G49: 6.39 | H49: Active | I49: =SUMIFS(BOM!Q:Q,BOM!A:A,'All Products'!A49,BOM!I:I,'All Products'!I$3) -> 2.6479274 | J49: =SUMIFS(BOM!Q:Q,BOM!A:A,'All Products'!A49,BOM!I:I,'All Products'!J$3)+0.03 -> 0.4 | K49: =(I49+J49)/G49 -> 0.47698395 | L49: =SUMIF(BOM!A:A,'All Products'!A49,BOM!S:S) -> 0.5500625 | M49: =SUMIF(BOM!A:A,'All Products'!A49,BOM!V:V) -> 0.2961875 | N49: =(L49+M49)/G49 -> 0.13243349 | O49: 0 | P49: =I49+J49+M49+L49+O49 -> 3.8941774 | Q49: =G49-P49 -> 2.4958226 | R49: =IFERROR((G49-P49)/G49,0) -> 0.39058256 | S49: 26.4 | T49: =S49*G49 -> 168.696 | U49: =IFERROR(S49*Q49,0) -> 65.889715 | V49: =(G49-P49)*S49 -> 65.889715 | W49: =V49-U49 -> 0 | Y49: =(G49-I49)/G49 -> 0.58561386
A50: 490ACS | B50: Reynolds | C50: NHS CARROTS GRATED 1 X 1KG | D50: KG | E50: =VLOOKUP(A50,BOM!A:E,5,0) -> 1 | F50: 1.77 | G50: 1.89 | H50: Active | I50: =SUMIFS(BOM!Q:Q,BOM!A:A,'All Products'!A50,BOM!I:I,'All Products'!I$3) -> 0.5044471 | J50: =SUMIFS(BOM!Q:Q,BOM!A:A,'All Products'!A50,BOM!I:I,'All Products'!J$3)+0.03 -> 0.39 | K50: =(I50+J50)/G50 -> 0.47325243 | L50: =SUMIF(BOM!A:A,'All Products'!A50,BOM!S:S) -> 0.30645053 | M50: =SUMIF(BOM!A:A,'All Products'!A50,BOM!V:V) -> 0.186175 | N50: =(L50+M50)/G50 -> 0.26064843 | O50: 0 | P50: =I50+J50+M50+L50+O50 -> 1.3870726 | Q50: =G50-P50 -> 0.50292737 | R50: =IFERROR((G50-P50)/G50,0) -> 0.26609914 | S50: 46.4 | T50: =S50*G50 -> 87.696 | U50: =IFERROR(S50*Q50,0) -> 23.33583 | V50: =(G50-P50)*S50 -> 23.33583 | W50: =V50-U50 -> 0 | Y50: =(G50-I50)/G50 -> 0.73309677
A51: 281ACS | B51: Reynolds | C51: NHS DICED CARROT 10MM 2.5KG | D51: KG | E51: =VLOOKUP(A51,BOM!A:E,5,0) -> 2.5 | F51: 4.02 | G51: 4.37 | H51: Active | I51: =SUMIFS(BOM!Q:Q,BOM!A:A,'All Products'!A51,BOM!I:I,'All Products'!I$3) -> 1.333847 | J51: =SUMIFS(BOM!Q:Q,BOM!A:A,'All Products'!A51,BOM!I:I,'All Products'!J$3)+0.03 -> 0.4 | K51: =(I51+J51)/G51 -> 0.39676132 | L51: =SUMIF(BOM!A:A,'All Products'!A51,BOM!S:S) -> 1.0599463 | M51: =SUMIF(BOM!A:A,'All Products'!A51,BOM!V:V) -> 0.2961875 | N51: =(L51+M51)/G51 -> 0.31032809 | O51: 0 | P51: =I51+J51+M51+L51+O51 -> 3.0899807 | Q51: =G51-P51 -> 1.2800193 | R51: =IFERROR((G51-P51)/G51,0) -> 0.29291059 | S51: 35.4 | T51: =S51*G51 -> 154.698 | U51: =IFERROR(S51*Q51,0) -> 45.312682 | V51: =(G51-P51)*S51 -> 45.312682 | W51: =V51-U51 -> 0 | Y51: =(G51-I51)/G51 -> 0.69477186
A52: 1646CS | B52: Reynolds | C52: PREP BROCCOLI 1 X 1KG | D52: KG | E52: =VLOOKUP(A52,BOM!A:E,5,0) -> 1 | F52: 6.21 | G52: 6.34 | H52: Active | I52: =SUMIFS(BOM!Q:Q,BOM!A:A,'All Products'!A52,BOM!I:I,'All Products'!I$3) -> 1.7586207 | J52: =SUMIFS(BOM!Q:Q,BOM!A:A,'All Products'!A52,BOM!I:I,'All Products'!J$3)+0.03 -> 0.4 | K52: =(I52+J52)/G52 -> 0.34047645 | L52: =SUMIF(BOM!A:A,'All Products'!A52,BOM!S:S) -> 0.91395 | M52: =SUMIF(BOM!A:A,'All Products'!A52,BOM!V:V) -> 0.2183325 | N52: =(L52+M52)/G52 -> 0.17859345 | O52: 0 | P52: =I52+J52+M52+L52+O52 -> 3.2909032 | Q52: =G52-P52 -> 3.0490968 | R52: =IFERROR((G52-P52)/G52,0) -> 0.4809301 | S52: 271.8 | T52: =S52*G52 -> 1723.212 | U52: =IFERROR(S52*Q52,0) -> 828.74451 | V52: =(G52-P52)*S52 -> 828.74451 | W52: =V52-U52 -> 0 | Y52: =(G52-I52)/G52 -> 0.72261503
A53: 2089CS | B53: Reynolds | C53: PREP POT FONDANT OVAL 20EA | D53: Count | E53: =VLOOKUP(A53,BOM!A:E,5,0) -> 2.21 | F53: 21.01 | G53: 20.17 | H53: Active | I53: =SUMIFS(BOM!Q:Q,BOM!A:A,'All Products'!A53,BOM!I:I,'All Products'!I$3) -> 4.6433544 | J53: =SUMIFS(BOM!Q:Q,BOM!A:A,'All Products'!A53,BOM!I:I,'All Products'!J$3)+0.03 -> 0.4 | K53: =(I53+J53)/G53 -> 0.25004236 | L53: =SUMIF(BOM!A:A,'All Products'!A53,BOM!S:S) -> 1.9875258 | M53: =SUMIF(BOM!A:A,'All Products'!A53,BOM!V:V) -> 0.2708 | N53: =(L53+M53)/G53 -> 0.11196459 | O53: 0 | P53: =I53+J53+M53+L53+O53 -> 7.3016802 | Q53: =G53-P53 -> 12.86832 | R53: =IFERROR((G53-P53)/G53,0) -> 0.63799305 | S53: 56.4 | T53: =S53*G53 -> 1137.588 | U53: =IFERROR(S53*Q53,0) -> 725.77323 | V53: =(G53-P53)*S53 -> 725.77323 | W53: =V53-U53 -> 0 | Y53: =(G53-I53)/G53 -> 0.76978907
A54: 1307CS | B54: Reynolds | C54: PREP ONION RED DICED 5MM 2.5KG | D54: KG | E54: =VLOOKUP(A54,BOM!A:E,5,0) -> 2.5 | F54: 8.6 | G54: 8.16 | H54: Active | I54: =SUMIFS(BOM!Q:Q,BOM!A:A,'All Products'!A54,BOM!I:I,'All Products'!I$3) -> 3.3223535 | J54: =SUMIFS(BOM!Q:Q,BOM!A:A,'All Products'!A54,BOM!I:I,'All Products'!J$3)+0.03 -> 0.4 | K54: =(I54+J54)/G54 -> 0.45617078 | L54: =SUMIF(BOM!A:A,'All Products'!A54,BOM!S:S) -> 0.74261007 | M54: =SUMIF(BOM!A:A,'All Products'!A54,BOM!V:V) -> 0.2961875 | N54: =(L54+M54)/G54 -> 0.12730362 | O54: 0 | P54: =I54+J54+M54+L54+O54 -> 4.7611511 | Q54: =G54-P54 -> 3.3988489 | R54: =IFERROR((G54-P54)/G54,0) -> 0.4165256 | S54: 75.4 | T54: =S54*G54 -> 615.264 | U54: =IFERROR(S54*Q54,0) -> 256.27321 | V54: =(G54-P54)*S54 -> 256.27321 | W54: =V54-U54 -> 0 | Y54: =(G54-I54)/G54 -> 0.59284883
A55: 491ACS | B55: Reynolds | C55: NHS CABBAGE GREEN SHRED 2.5KG | D55: KG | E55: =VLOOKUP(A55,BOM!A:E,5,0) -> 2.5 | F55: 7.07 | G55: 7.64 | H55: Active | I55: =SUMIFS(BOM!Q:Q,BOM!A:A,'All Products'!A55,BOM!I:I,'All Products'!I$3) -> 2.6388889 | J55: =SUMIFS(BOM!Q:Q,BOM!A:A,'All Products'!A55,BOM!I:I,'All Products'!J$3)+0.03 -> 0.45 | K55: =(I55+J55)/G55 -> 0.40430483 | L55: =SUMIF(BOM!A:A,'All Products'!A55,BOM!S:S) -> 0.73650691 | M55: =SUMIF(BOM!A:A,'All Products'!A55,BOM!V:V) -> 0.2961875 | N55: =(L55+M55)/G55 -> 0.13516942 | O55: 0 | P55: =I55+J55+M55+L55+O55 -> 4.1215833 | Q55: =G55-P55 -> 3.5184167 | R55: =IFERROR((G55-P55)/G55,0) -> 0.46052575 | S55: 72.4 | T55: =S55*G55 -> 553.136 | U55: =IFERROR(S55*Q55,0) -> 254.73337 | V55: =(G55-P55)*S55 -> 254.73337 | W55: =V55-U55 -> 0 | Y55: =(G55-I55)/G55 -> 0.6545957
A56: 1863CS | B56: Reynolds | C56: PREP PINEAPPLE CUBED 2KG | D56: KG | E56: =VLOOKUP(A56,BOM!A:E,5,0) -> 2.7 | F56: 10.42 | G56: 10.63 | H56: Active | I56: =SUMIFS(BOM!Q:Q,BOM!A:A,'All Products'!A56,BOM!I:I,'All Products'!I$3) -> 3.5441 | J56: =SUMIFS(BOM!Q:Q,BOM!A:A,'All Products'!A56,BOM!I:I,'All Products'!J$3)+0.03 -> 0.75 | K56: =(I56+J56)/G56 -> 0.40396049 | L56: =SUMIF(BOM!A:A,'All Products'!A56,BOM!S:S) -> 1.0980321 | M56: =SUMIF(BOM!A:A,'All Products'!A56,BOM!V:V) -> 0.2708 | N56: =(L56+M56)/G56 -> 0.12877066 | O56: 0 | P56: =I56+J56+M56+L56+O56 -> 5.6629321 | Q56: =G56-P56 -> 4.9670679 | R56: =IFERROR((G56-P56)/G56,0) -> 0.46726886 | S56: 168.8 | T56: =S56*G56 -> 1794.344 | U56: =IFERROR(S56*Q56,0) -> 838.44107 | V56: =(G56-P56)*S56 -> 838.44107 | W56: =V56-U56 -> 0 | Y56: =(G56-I56)/G56 -> 0.66659454
A57: 2346CS | B57: Reynolds | C57: PREP STIR FRY MIX 1 X 2.5KG | D57: KG | E57: =VLOOKUP(A57,BOM!A:E,5,0) -> 2.5 | F57: 8.19 | G57: 8.35 | H57: Active | I57: =SUMIFS(BOM!Q:Q,BOM!A:A,'All Products'!A57,BOM!I:I,'All Products'!I$3) -> 2.9227058 | J57: =SUMIFS(BOM!Q:Q,BOM!A:A,'All Products'!A57,BOM!I:I,'All Products'!J$3)+0.03 -> 0.4 | K57: =(I57+J57)/G57 -> 0.39792884 | L57: =SUMIF(BOM!A:A,'All Products'!A57,BOM!S:S) -> 0.887361 | M57: =SUMIF(BOM!A:A,'All Products'!A57,BOM!V:V) -> 0.2961875 | N57: =(L57+M57)/G57 -> 0.14174234 | O57: 0 | P57: =I57+J57+M57+L57+O57 -> 4.5062543 | Q57: =G57-P57 -> 3.8437457 | R57: =IFERROR((G57-P57)/G57,0) -> 0.46032883 | S57: 6.4 | T57: =S57*G57 -> 53.44 | U57: =IFERROR(S57*Q57,0) -> 24.599972 | V57: =(G57-P57)*S57 -> 24.599972 | W57: =V57-U57 -> 0 | Y57: =(G57-I57)/G57 -> 0.64997535
A58: 1366CS | B58: Reynolds | C58: PREP PARSNIPS WHOLE 2.5KG | D58: KG | E58: =VLOOKUP(A58,BOM!A:E,5,0) -> 2.5 | F58: 9.56 | G58: 9.98 | H58: Active | I58: =SUMIFS(BOM!Q:Q,BOM!A:A,'All Products'!A58,BOM!I:I,'All Products'!I$3) -> 2.7957143 | J58: =SUMIFS(BOM!Q:Q,BOM!A:A,'All Products'!A58,BOM!I:I,'All Products'!J$3)+0.03 -> 0.4 | K58: =(I58+J58)/G58 -> 0.32021185 | L58: =SUMIF(BOM!A:A,'All Products'!A58,BOM!S:S) -> 2.2909196 | M58: =SUMIF(BOM!A:A,'All Products'!A58,BOM!V:V) -> 0.2961875 | N58: =(L58+M58)/G58 -> 0.25922917 | O58: 0 | P58: =I58+J58+M58+L58+O58 -> 5.7828214 | Q58: =G58-P58 -> 4.1971786 | R58: =IFERROR((G58-P58)/G58,0) -> 0.42055898 | S58: 9.2 | T58: =S58*G58 -> 91.816 | U58: =IFERROR(S58*Q58,0) -> 38.614043 | V58: =(G58-P58)*S58 -> 38.614043 | W58: =V58-U58 -> 0 | Y58: =(G58-I58)/G58 -> 0.71986831
A59: 1107CS | B59: Reynolds | C59: PREP POTS THINLY SLICED 2.5KG | D59: KG | E59: =VLOOKUP(A59,BOM!A:E,5,0) -> 2.5 | F59: 7.17 | G59: 6.68 | H59: Active | I59: =SUMIFS(BOM!Q:Q,BOM!A:A,'All Products'!A59,BOM!I:I,'All Products'!I$3) -> 1.0564353 | J59: =SUMIFS(BOM!Q:Q,BOM!A:A,'All Products'!A59,BOM!I:I,'All Products'!J$3)+0.03 -> 0.4 | K59: =(I59+J59)/G59 -> 0.21802924 | L59: =SUMIF(BOM!A:A,'All Products'!A59,BOM!S:S) -> 2.2309383 | M59: =SUMIF(BOM!A:A,'All Products'!A59,BOM!V:V) -> 0.2961875 | N59: =(L59+M59)/G59 -> 0.37831225 | O59: 0 | P59: =I59+J59+M59+L59+O59 -> 3.9835611 | Q59: =G59-P59 -> 2.6964389 | R59: =IFERROR((G59-P59)/G59,0) -> 0.40365851 | S59: 29.6 | T59: =S59*G59 -> 197.728 | U59: =IFERROR(S59*Q59,0) -> 79.814591 | V59: =(G59-P59)*S59 -> 79.814591 | W59: =V59-U59 -> 0 | Y59: =(G59-I59)/G59 -> 0.841851
... A73: 717ACS | B73: Reynolds | C73: CHERRY TOMATO HALF CUT 1x1KG | D73: KG | E73: =VLOOKUP(A73,BOM!A:E,5,0) -> 1 | F73: 4.04 | G73: 4.17 | H73: Active | I73: =SUMIFS(BOM!Q:Q,BOM!A:A,'All Products'!A73,BOM!I:I,'All Products'!I$3) -> 1.8597571 | J73: =SUMIFS(BOM!Q:Q,BOM!A:A,'All Products'!A73,BOM!I:I,'All Products'!J$3)+0.03 -> 0.94 | K73: =(I73+J73)/G73 -> 0.67140458 | L73: =SUMIF(BOM!A:A,'All Products'!A73,BOM!S:S) -> 0.27108932 | M73: =SUMIF(BOM!A:A,'All Products'!A73,BOM!V:V) -> 0.2183325 | N73: =(L73+M73)/G73 -> 0.11736734 | O73: 0 | P73: =I73+J73+M73+L73+O73 -> 3.2891789 | Q73: =G73-P73 -> 0.8808211 | R73: =IFERROR((G73-P73)/G73,0) -> 0.21122808 | S73: 20.4 | T73: =S73*G73 -> 85.068 | U73: =IFERROR(S73*Q73,0) -> 17.96875 | V73: =(G73-P73)*S73 -> 17.96875 | W73: =V73-U73 -> 0 | Y73: =(G73-I73)/G73 -> 0.55401509
A74: 2180CS | B74: Reynolds | C74: PREP CAULIFLORETS 2.5KG | D74: KG | E74: =VLOOKUP(A74,BOM!A:E,5,0) -> 2.5 | F74: 16.62 | G74: 19.69 | H74: Active | I74: =SUMIFS(BOM!Q:Q,BOM!A:A,'All Products'!A74,BOM!I:I,'All Products'!I$3) -> 3.6971831 | J74: =SUMIFS(BOM!Q:Q,BOM!A:A,'All Products'!A74,BOM!I:I,'All Products'!J$3)+0.03 -> 0.4 | K74: =(I74+J74)/G74 -> 0.20808446 | L74: =SUMIF(BOM!A:A,'All Products'!A74,BOM!S:S) -> 5.5820716 | M74: =SUMIF(BOM!A:A,'All Products'!A74,BOM!V:V) -> 0.2961875 | N74: =(L74+M74)/G74 -> 0.29854033 | O74: 0 | P74: =I74+J74+M74+L74+O74 -> 9.9754422 | Q74: =G74-P74 -> 9.7145578 | R74: =IFERROR((G74-P74)/G74,0) -> 0.49337521 | S74: 364 | T74: =S74*G74 -> 7167.16 | U74: =IFERROR(S74*Q74,0) -> 3536.099 | V74: =(G74-P74)*S74 -> 3536.099 | W74: =V74-U74 -> 0 | Y74: =(G74-I74)/G74 -> 0.81223042 | AE74: 5.7922535
A75: 495ACS | B75: Reynolds | C75: NHS RATATOUILLE LGE CUT 2.5KG | D75: KG | E75: =VLOOKUP(A75,BOM!A:E,5,0) -> 2.5 | F75: 8.93 | G75: 9.32 | H75: Active | I75: =SUMIFS(BOM!Q:Q,BOM!A:A,'All Products'!A75,BOM!I:I,'All Products'!I$3) -> 4.7258689 | J75: =SUMIFS(BOM!Q:Q,BOM!A:A,'All Products'!A75,BOM!I:I,'All Products'!J$3)+0.03 -> 0.4 | K75: =(I75+J75)/G75 -> 0.54998594 | L75: =SUMIF(BOM!A:A,'All Products'!A75,BOM!S:S) -> 2.599272 | M75: =SUMIF(BOM!A:A,'All Products'!A75,BOM!V:V) -> 0.2961875 | N75: =(L75+M75)/G75 -> 0.31067162 | O75: 0 | P75: =I75+J75+M75+L75+O75 -> 8.0213284 | Q75: =G75-P75 -> 1.2986716 | R75: =IFERROR((G75-P75)/G75,0) -> 0.13934244 | S75: 13.2 | T75: =S75*G75 -> 123.024 | U75: =IFERROR(S75*Q75,0) -> 17.142465 | V75: =(G75-P75)*S75 -> 17.142465 | W75: =V75-U75 -> 0 | Y75: =(G75-I75)/G75 -> 0.49293252
A76: 1865CS | B76: Reynolds | C76: PREP MELON CUBED ORANGE 2KG | D76: KG | E76: =VLOOKUP(A76,BOM!A:E,5,0) -> 2.7 | F76: 16.3 | G76: 17.17 | H76: Active | I76: =SUMIFS(BOM!Q:Q,BOM!A:A,'All Products'!A76,BOM!I:I,'All Products'!I$3) -> 6.265975 | J76: =SUMIFS(BOM!Q:Q,BOM!A:A,'All Products'!A76,BOM!I:I,'All Products'!J$3)+0.03 -> 0.75 | K76: =(I76+J76)/G76 -> 0.40861823 | L76: =SUMIF(BOM!A:A,'All Products'!A76,BOM!S:S) -> 2.3093222 | M76: =SUMIF(BOM!A:A,'All Products'!A76,BOM!V:V) -> 0.2708 | N76: =(L76+M76)/G76 -> 0.1502692 | O76: 0 | P76: =I76+J76+M76+L76+O76 -> 9.5960972 | Q76: =G76-P76 -> 7.5739028 | R76: =IFERROR((G76-P76)/G76,0) -> 0.44111257 | S76: 39.4 | T76: =S76*G76 -> 676.498 | U76: =IFERROR(S76*Q76,0) -> 298.41177 | V76: =(G76-P76)*S76 -> 298.41177 | W76: =V76-U76 -> 0 | Y76: =(G76-I76)/G76 -> 0.63506261
A77: 714ACS | B77: Reynolds | C77: CARROT GRATED 4X250G | D77: KG | E77: =VLOOKUP(A77,BOM!A:E,5,0) -> 1 | F77: 1.79 | G77: 2.02 | H77: Active | I77: =SUMIFS(BOM!Q:Q,BOM!A:A,'All Products'!A77,BOM!I:I,'All Products'!I$3) -> 0.5044471 | J77: =SUMIFS(BOM!Q:Q,BOM!A:A,'All Products'!A77,BOM!I:I,'All Products'!J$3)+0.03 -> 0.51 | K77: =(I77+J77)/G77 -> 0.50220153 | L77: =SUMIF(BOM!A:A,'All Products'!A77,BOM!S:S) -> 0.30645053 | M77: =SUMIF(BOM!A:A,'All Products'!A77,BOM!V:V) -> 0.592375 | N77: =(L77+M77)/G77 -> 0.44496313 | O77: 0 | P77: =I77+J77+M77+L77+O77 -> 1.9132726 | Q77: =G77-P77 -> 0.10672737 | R77: =IFERROR((G77-P77)/G77,0) -> 0.052835331 | S77: 0 | T77: =S77*G77 -> 0 | U77: =IFERROR(S77*Q77,0) -> 0 | V77: =(G77-P77)*S77 -> 0 | W77: =V77-U77 -> 0 | Y77: =(G77-I77)/G77 -> 0.75027371
A78: 716ACS | B78: Reynolds | C78: SPRING ONION SLICES 4MM 4X250G | D78: KG | E78: =VLOOKUP(A78,BOM!A:E,5,0) -> 1 | F78: 9.85 | G78: 10.56 | H78: Active | I78: =SUMIFS(BOM!Q:Q,BOM!A:A,'All Products'!A78,BOM!I:I,'All Products'!I$3) -> 4.2753333 | J78: =SUMIFS(BOM!Q:Q,BOM!A:A,'All Products'!A78,BOM!I:I,'All Products'!J$3)+0.03 -> 0.51 | K78: =(I78+J78)/G78 -> 0.45315657 | L78: =SUMIF(BOM!A:A,'All Products'!A78,BOM!S:S) -> 5.3192857 | M78: =SUMIF(BOM!A:A,'All Products'!A78,BOM!V:V) -> 0.592375 | N78: =(L78+M78)/G78 -> 0.55981636 | O78: 0 | P78: =I78+J78+M78+L78+O78 -> 10.696994 | Q78: =G78-P78 -> -0.13699405 | R78: =IFERROR((G78-P78)/G78,0) -> -0.012972921 | S78: 131.6 | T78: =S78*G78 -> 1389.696 | U78: =IFERROR(S78*Q78,0) -> -18.028417 | V78: =(G78-P78)*S78 -> -18.028417 | W78: =V78-U78 -> 0 | X78: Used cost of 2kg spring onion material "3644CS" as im unsure about the cost/kg of new spring onion 20X bunch | Y78: =(G78-I78)/G78 -> 0.59513889
A79: 1157CS | B79: Reynolds | C79: PINK STAR DRY SLAW 2 X 1KG | D79: KG | E79: =VLOOKUP(A79,BOM!A:E,5,0) -> 2 | F79: 3.8 | G79: 4.08 | H79: Active | I79: =SUMIFS(BOM!Q:Q,BOM!A:A,'All Products'!A79,BOM!I:I,'All Products'!I$3) -> #N/A | J79: =SUMIFS(BOM!Q:Q,BOM!A:A,'All Products'!A79,BOM!I:I,'All Products'!J$3)+0.03 -> 0.49 | K79: =(I79+J79)/G79 -> #N/A | L79: =SUMIF(BOM!A:A,'All Products'!A79,BOM!S:S) -> 0.58818338 | M79: =SUMIF(BOM!A:A,'All Products'!A79,BOM!V:V) -> 0.48744 | N79: =(L79+M79)/G79 -> 0.26363318 | O79: 0 | P79: =I79+J79+M79+L79+O79 -> #N/A | Q79: =G79-P79 -> #N/A | R79: =IFERROR((G79-P79)/G79,0) -> 0 | S79: 209.4 | T79: =S79*G79 -> 854.352 | U79: =IFERROR(S79*Q79,0) -> 0 | V79: =(G79-P79)*S79 -> #N/A | W79: =V79-U79 -> #N/A | Y79: =(G79-I79)/G79 -> #N/A
A80: 1875CS | B80: Reynolds | C80: PREP DICED MANGO 1KG | D80: KG | E80: =VLOOKUP(A80,BOM!A:E,5,0) -> 1.35 | F80: 7.93 | G80: 8.16 | H80: Active | I80: =SUMIFS(BOM!Q:Q,BOM!A:A,'All Products'!A80,BOM!I:I,'All Products'!I$3) -> 4.0496074 | J80: =SUMIFS(BOM!Q:Q,BOM!A:A,'All Products'!A80,BOM!I:I,'All Products'!J$3)+0.03 -> 0.73 | K80: =(I80+J80)/G80 -> 0.5857362 | L80: =SUMIF(BOM!A:A,'All Products'!A80,BOM!S:S) -> 1.4537472 | M80: =SUMIF(BOM!A:A,'All Products'!A80,BOM!V:V) -> 0.2183325 | N80: =(L80+M80)/G80 -> 0.20491173 | O80: 0 | P80: =I80+J80+M80+L80+O80 -> 6.4516872 | Q80: =G80-P80 -> 1.7083128 | R80: =IFERROR((G80-P80)/G80,0) -> 0.20935206 | S80: 20.8 | T80: =S80*G80 -> 169.728 | U80: =IFERROR(S80*Q80,0) -> 35.532907 | V80: =(G80-P80)*S80 -> 35.532907 | W80: =V80-U80 -> 0 | Y80: =(G80-I80)/G80 -> 0.50372458
A81: 790ACS | B81: Reynolds | C81: SHOESTRING POTATOES 3KG | D81: KG | E81: =VLOOKUP(A81,BOM!A:E,5,0) -> 3 | F81: 15.13 | G81: 14.55 | H81: Active | I81: =SUMIFS(BOM!Q:Q,BOM!A:A,'All Products'!A81,BOM!I:I,'All Products'!I$3) -> 1.5127052 | J81: =SUMIFS(BOM!Q:Q,BOM!A:A,'All Products'!A81,BOM!I:I,'All Products'!J$3)+0.03 -> 0.4 | K81: =(I81+J81)/G81 -> 0.1314574 | L81: =SUMIF(BOM!A:A,'All Products'!A81,BOM!S:S) -> 3.6628731 | M81: =SUMIF(BOM!A:A,'All Products'!A81,BOM!V:V) -> 0.2708 | N81: =(L81+M81)/G81 -> 0.27035554 | O81: 0 | P81: =I81+J81+M81+L81+O81 -> 5.8463784 | Q81: =G81-P81 -> 8.7036216 | R81: =IFERROR((G81-P81)/G81,0) -> 0.59818705 | S81: 0 | T81: =S81*G81 -> 0 | U81: =IFERROR(S81*Q81,0) -> 0 | V81: =(G81-P81)*S81 -> 0 | W81: =V81-U81 -> 0 | Y81: =(G81-I81)/G81 -> 0.89603401
A82: 498ACS | B82: Reynolds | C82: NHS PREP DICED ONION 5MM 1KG | D82: KG | E82: =VLOOKUP(A82,BOM!A:E,5,0) -> 1 | F82: 3.59 | G82: 3.64 | H82: Active | I82: =SUMIFS(BOM!Q:Q,BOM!A:A,'All Products'!A82,BOM!I:I,'All Products'!I$3) -> 1.059171 | J82: =SUMIFS(BOM!Q:Q,BOM!A:A,'All Products'!A82,BOM!I:I,'All Products'!J$3)+0.03 -> 0.4 | K82: =(I82+J82)/G82 -> 0.40087115 | L82: =SUMIF(BOM!A:A,'All Products'!A82,BOM!S:S) -> 0.220025 | M82: =SUMIF(BOM!A:A,'All Products'!A82,BOM!V:V) -> 0.2183325 | N82: =(L82+M82)/G82 -> 0.12042788 | O82: 0 | P82: =I82+J82+M82+L82+O82 -> 1.8975285 | Q82: =G82-P82 -> 1.7424715 | R82: =IFERROR((G82-P82)/G82,0) -> 0.47870097 | S82: 0 | T82: =S82*G82 -> 0 | U82: =IFERROR(S82*Q82,0) -> 0 | V82: =(G82-P82)*S82 -> 0 | W82: =V82-U82 -> 0 | Y82: =(G82-I82)/G82 -> 0.70901896
A83: 713ACS | B83: Reynolds | C83: BEETROOT GRATED 4X250G | D83: KG | E83: =VLOOKUP(A83,BOM!A:E,5,0) -> 1 | F83: 1.94 | G83: 1.93 | H83: In Active | I83: =SUMIFS(BOM!Q:Q,BOM!A:A,'All Products'!A83,BOM!I:I,'All Products'!I$3) -> 0.66346697 | J83: =SUMIFS(BOM!Q:Q,BOM!A:A,'All Products'!A83,BOM!I:I,'All Products'!J$3)+0.03 -> 0.51 | K83: =(I83+J83)/G83 -> 0.60801397 | L83: =SUMIF(BOM!A:A,'All Products'!A83,BOM!S:S) -> 0.5416 | M83: =SUMIF(BOM!A:A,'All Products'!A83,BOM!V:V) -> 0.592375 | N83: =(L83+M83)/G83 -> 0.58755181 | O83: 0 | P83: =I83+J83+M83+L83+O83 -> 2.307442 | Q83: =G83-P83 -> -0.37744197 | R83: =IFERROR((G83-P83)/G83,0) -> -0.19556579 | S83: 0 | T83: =S83*G83 -> 0 | U83: =IFERROR(S83*Q83,0) -> 0 | V83: =(G83-P83)*S83 -> 0 | W83: =V83-U83 -> 0 | Y83: =(G83-I83)/G83 -> 0.65623473 | AB83: =P83*1.57 -> 3.6226839 | AC83: =AB83-P83 -> 1.3152419 | AD83: =AC83/AB83 -> 0.36305732
A84: 492ACS | B84: Reynolds | C84: NHS CABBAGE RED SHRED 2.5KG | D84: KG | E84: =VLOOKUP(A84,BOM!A:E,5,0) -> 2.5 | F84: 3.88 | G84: 4 | H84: Active | I84: =SUMIFS(BOM!Q:Q,BOM!A:A,'All Products'!A84,BOM!I:I,'All Products'!I$3) -> 1.3555936 | J84: =SUMIFS(BOM!Q:Q,BOM!A:A,'All Products'!A84,BOM!I:I,'All Products'!J$3)+0.03 -> 0.4 | K84: =(I84+J84)/G84 -> 0.4388984 | L84: =SUMIF(BOM!A:A,'All Products'!A84,BOM!S:S) -> 0.7567636 | M84: =SUMIF(BOM!A:A,'All Products'!A84,BOM!V:V) -> 0.2961875 | N84: =(L84+M84)/G84 -> 0.26323778 | O84: 0 | P84: =I84+J84+M84+L84+O84 -> 2.8085447 | Q84: =G84-P84 -> 1.1914553 | R84: =IFERROR((G84-P84)/G84,0) -> 0.29786382 | S84: 8.6 | T84: =S84*G84 -> 34.4 | U84: =IFERROR(S84*Q84,0) -> 10.246516 | V84: =(G84-P84)*S84 -> 10.246516 | W84: =V84-U84 -> 0 | Y84: =(G84-I84)/G84 -> 0.6611016
A85: 500ACS | B85: Reynolds | C85: NHS PREP SWEDE DICED 2.5KG | D85: KG | E85: =VLOOKUP(A85,BOM!A:E,5,0) -> 2.5 | F85: 4.75 | G85: 4.28 | H85: Active | I85: =SUMIFS(BOM!Q:Q,BOM!A:A,'All Products'!A85,BOM!I:I,'All Products'!I$3) -> 1.5784798 | J85: =SUMIFS(BOM!Q:Q,BOM!A:A,'All Products'!A85,BOM!I:I,'All Products'!J$3)+0.03 -> 0.4 | K85: =(I85+J85)/G85 -> 0.46226163 | L85: =SUMIF(BOM!A:A,'All Products'!A85,BOM!S:S) -> 1.645355 | M85: =SUMIF(BOM!A:A,'All Products'!A85,BOM!V:V) -> 0.2961875 | N85: =(L85+M85)/G85 -> 0.45363141 | O85: 0 | P85: =I85+J85+M85+L85+O85 -> 3.9200222 | Q85: =G85-P85 -> 0.35997779 | R85: =IFERROR((G85-P85)/G85,0) -> 0.084106959 | S85: 0 | T85: =S85*G85 -> 0 | U85: =IFERROR(S85*Q85,0) -> 0 | V85: =(G85-P85)*S85 -> 0 | W85: =V85-U85 -> 0 | Y85: =(G85-I85)/G85 -> 0.63119632
A86: 481ACS | B86: Reynolds | C86: NHS SHR SAVOY CABBAGE 3MM 5KG | D86: KG | E86: =VLOOKUP(A86,BOM!A:E,5,0) -> 5 | F86: 19.15 | G86: 20.37 | H86: Active | I86: =SUMIFS(BOM!Q:Q,BOM!A:A,'All Products'!A86,BOM!I:I,'All Products'!I$3) -> 5.1630435 | J86: =SUMIFS(BOM!Q:Q,BOM!A:A,'All Products'!A86,BOM!I:I,'All Products'!J$3)+0.03 -> 0.4 | K86: =(I86+J86)/G86 -> 0.27309983 | L86: =SUMIF(BOM!A:A,'All Products'!A86,BOM!S:S) -> 1.1988542 | M86: =SUMIF(BOM!A:A,'All Products'!A86,BOM!V:V) -> 0.4011225 | N86: =(L86+M86)/G86 -> 0.078545737 | O86: 0 | P86: =I86+J86+M86+L86+O86 -> 7.1630201 | Q86: =G86-P86 -> 13.20698 | R86: =IFERROR((G86-P86)/G86,0) -> 0.64835444 | S86: 0 | T86: =S86*G86 -> 0 | U86: =IFERROR(S86*Q86,0) -> 0 | V86: =(G86-P86)*S86 -> 0 | W86: =V86-U86 -> 0 | Y86: =(G86-I86)/G86 -> 0.74653689
A87: 483ACS | B87: Reynolds | C87: NHS PREP ONION RED WHOLE 2.5KG | D87: KG | E87: =VLOOKUP(A87,BOM!A:E,5,0) -> 2.5 | F87: 6 | G87: 4.24 | H87: Active | I87: =SUMIFS(BOM!Q:Q,BOM!A:A,'All Products'!A87,BOM!I:I,'All Products'!I$3) -> 3.2792787 | J87: =SUMIFS(BOM!Q:Q,BOM!A:A,'All Products'!A87,BOM!I:I,'All Products'!J$3)+0.03 -> 0.4 | K87: =(I87+J87)/G87 -> 0.86775442 | L87: =SUMIF(BOM!A:A,'All Products'!A87,BOM!S:S) -> 0.423125 | M87: =SUMIF(BOM!A:A,'All Products'!A87,BOM!V:V) -> 0.2961875 | N87: =(L87+M87)/G87 -> 0.16964917 | O87: 0 | P87: =I87+J87+M87+L87+O87 -> 4.3985912 | Q87: =G87-P87 -> -0.15859123 | R87: =IFERROR((G87-P87)/G87,0) -> -0.037403592 | S87: 0 | T87: =S87*G87 -> 0 | U87: =IFERROR(S87*Q87,0) -> 0 | V87: =(G87-P87)*S87 -> 0 | W87: =V87-U87 -> 0 | Y87: =(G87-I87)/G87 -> 0.22658521
A88: 906ACS | B88: Reynolds | C88: BENUGO PREP DICED MANGO 1KG | D88: KG | E88: =VLOOKUP(A88,BOM!A:E,5,0) -> 1.35 | F88: 7.93 | G88: 8.16 | H88: Active | I88: =SUMIFS(BOM!Q:Q,BOM!A:A,'All Products'!A88,BOM!I:I,'All Products'!I$3) -> 4.0496074 | J88: =SUMIFS(BOM!Q:Q,BOM!A:A,'All Products'!A88,BOM!I:I,'All Products'!J$3)+0.03 -> 0.73 | K88: =(I88+J88)/G88 -> 0.5857362 | L88: =SUMIF(BOM!A:A,'All Products'!A88,BOM!S:S) -> 1.4537472 | M88: =SUMIF(BOM!A:A,'All Products'!A88,BOM!V:V) -> 0.2183325 | N88: =(L88+M88)/G88 -> 0.20491173 | O88: 0 | P88: =I88+J88+M88+L88+O88 -> 6.4516872 | Q88: =G88-P88 -> 1.7083128 | R88: =IFERROR((G88-P88)/G88,0) -> 0.20935206 | S88: 39 | T88: =S88*G88 -> 318.24 | U88: =IFERROR(S88*Q88,0) -> 66.624201 | V88: =(G88-P88)*S88 -> 66.624201 | W88: =V88-U88 -> 0 | Y88: =(G88-I88)/G88 -> 0.50372458
A89: 1477CS | B89: Reynolds | C89: PREP ROOT VEG DICED 2CM 5KG | D89: KG | E89: =VLOOKUP(A89,BOM!A:E,5,0) -> 5 | F89: 16.57 | G89: 17.11 | H89: Active | I89: =SUMIFS(BOM!Q:Q,BOM!A:A,'All Products'!A89,BOM!I:I,'All Products'!I$3) -> 3.8376588 | J89: =SUMIFS(BOM!Q:Q,BOM!A:A,'All Products'!A89,BOM!I:I,'All Products'!J$3)+0.03 -> 0.45 | K89: =(I89+J89)/G89 -> 0.25059373 | L89: =SUMIF(BOM!A:A,'All Products'!A89,BOM!S:S) -> 4.4859914 | M89: =SUMIF(BOM!A:A,'All Products'!A89,BOM!V:V) -> 0.4011225 | N89: =(L89+M89)/G89 -> 0.2856291 | O89: 0 | P89: =I89+J89+M89+L89+O89 -> 9.1747727 | Q89: =G89-P89 -> 7.9352273 | R89: =IFERROR((G89-P89)/G89,0) -> 0.46377717 | S89: 19.2 | T89: =S89*G89 -> 328.512 | U89: =IFERROR(S89*Q89,0) -> 152.35636 | V89: =(G89-P89)*S89 -> 152.35636 | W89: =V89-U89 -> 0 | Y89: =(G89-I89)/G89 -> 0.77570667
A90: 493ACS | B90: Reynolds | C90: NHS COLESLAW DRY MIX 1KG | D90: KG | E90: =VLOOKUP(A90,BOM!A:E,5,0) -> 1 | F90: 1.76 | G90: 1.83 | H90: Active | I90: =SUMIFS(BOM!Q:Q,BOM!A:A,'All Products'!A90,BOM!I:I,'All Products'!I$3) -> 0.45953517 | J90: =SUMIFS(BOM!Q:Q,BOM!A:A,'All Products'!A90,BOM!I:I,'All Products'!J$3)+0.03 -> 0.4 | K90: =(I90+J90)/G90 -> 0.46969135 | L90: =SUMIF(BOM!A:A,'All Products'!A90,BOM!S:S) -> 0.28806692 | M90: =SUMIF(BOM!A:A,'All Products'!A90,BOM!V:V) -> 0.2183325 | N90: =(L90+M90)/G90 -> 0.276721 | O90: 0 | P90: =I90+J90+M90+L90+O90 -> 1.3659346 | Q90: =G90-P90 -> 0.46406541 | R90: =IFERROR((G90-P90)/G90,0) -> 0.25358765 | S90: 0 | T90: =S90*G90 -> 0 | U90: =IFERROR(S90*Q90,0) -> 0 | V90: =(G90-P90)*S90 -> 0 | W90: =V90-U90 -> 0 | Y90: =(G90-I90)/G90 -> 0.74888789
A91: 1181CS | B91: Reynolds | C91: PREP 3MM SHR SAVOY CABBAGE 5KG | D91: KG | E91: =VLOOKUP(A91,BOM!A:E,5,0) -> 5 | F91: 18.96 | G91: 20.21 | H91: Active | I91: =SUMIFS(BOM!Q:Q,BOM!A:A,'All Products'!A91,BOM!I:I,'All Products'!I$3) -> 5.2777778 | J91: =SUMIFS(BOM!Q:Q,BOM!A:A,'All Products'!A91,BOM!I:I,'All Products'!J$3)+0.03 -> 0.45 | K91: =(I91+J91)/G91 -> 0.28341305 | L91: =SUMIF(BOM!A:A,'All Products'!A91,BOM!S:S) -> 1.4730138 | M91: =SUMIF(BOM!A:A,'All Products'!A91,BOM!V:V) -> 0.4011225 | N91: =(L91+M91)/G91 -> 0.092733118 | O91: 0 | P91: =I91+J91+M91+L91+O91 -> 7.6019141 | Q91: =G91-P91 -> 12.608086 | R91: =IFERROR((G91-P91)/G91,0) -> 0.62385383 | S91: 8.6 | T91: =S91*G91 -> 173.806 | U91: =IFERROR(S91*Q91,0) -> 108.42954 | V91: =(G91-P91)*S91 -> 108.42954 | W91: =V91-U91 -> 0 | Y91: =(G91-I91)/G91 -> 0.73885315
A92: 1853CS | B92: Reynolds | C92: PREP GRAPEFRUIT SEGMENTS 2KG | D92: KG | E92: =VLOOKUP(A92,BOM!A:E,5,0) -> 2.7 | F92: 16.69 | G92: 16.91 | H92: Active | I92: =SUMIFS(BOM!Q:Q,BOM!A:A,'All Products'!A92,BOM!I:I,'All Products'!I$3) -> 5.6748692 | J92: =SUMIFS(BOM!Q:Q,BOM!A:A,'All Products'!A92,BOM!I:I,'All Products'!J$3)+0.03 -> 0.75 | K92: =(I92+J92)/G92 -> 0.37994496 | L92: =SUMIF(BOM!A:A,'All Products'!A92,BOM!S:S) -> 3.2022264 | M92: =SUMIF(BOM!A:A,'All Products'!A92,BOM!V:V) -> 0.2708 | N92: =(L92+M92)/G92 -> 0.20538299 | O92: 0 | P92: =I92+J92+M92+L92+O92 -> 9.8978957 | Q92: =G92-P92 -> 7.0121043 | R92: =IFERROR((G92-P92)/G92,0) -> 0.41467205 | S92: 8.2 | T92: =S92*G92 -> 138.662 | U92: =IFERROR(S92*Q92,0) -> 57.499256 | V92: =(G92-P92)*S92 -> 57.499256 | W92: =V92-U92 -> 0 | Y92: =(G92-I92)/G92 -> 0.6644075
A93: 1860CS | B93: Reynolds | C93: PREP WATERMELON CUBES 2KG | D93: KG | E93: =VLOOKUP(A93,BOM!A:E,5,0) -> 2.7 | F93: 6.93 | G93: 7.25 | H93: Active | I93: =SUMIFS(BOM!Q:Q,BOM!A:A,'All Products'!A93,BOM!I:I,'All Products'!I$3) -> 2.9703295 | J93: =SUMIFS(BOM!Q:Q,BOM!A:A,'All Products'!A93,BOM!I:I,'All Products'!J$3)+0.03 -> 0.75 | K93: =(I93+J93)/G93 -> 0.5131489 | L93: =SUMIF(BOM!A:A,'All Products'!A93,BOM!S:S) -> 1.655359 | M93: =SUMIF(BOM!A:A,'All Products'!A93,BOM!V:V) -> 0.2708 | N93: =(L93+M93)/G93 -> 0.26567711 | O93: 0 | P93: =I93+J93+M93+L93+O93 -> 5.6464885 | Q93: =G93-P93 -> 1.6035115 | R93: =IFERROR((G93-P93)/G93,0) -> 0.221174 | S93: 21.6 | T93: =S93*G93 -> 156.6 | U93: =IFERROR(S93*Q93,0) -> 34.635848 | V93: =(G93-P93)*S93 -> 34.635848 | W93: =V93-U93 -> 0 | Y93: =(G93-I93)/G93 -> 0.59029938
A94: 2414CS | B94: Reynolds | C94: (S) COURGETTI 4 X 500G | D94: KG | E94: =VLOOKUP(A94,BOM!A:E,5,0) -> 2 | F94: 15.87 | G94: 16.18 | H94: In Active | I94: =SUMIFS(BOM!Q:Q,BOM!A:A,'All Products'!A94,BOM!I:I,'All Products'!I$3) -> 0 | J94: =SUMIFS(BOM!Q:Q,BOM!A:A,'All Products'!A94,BOM!I:I,'All Products'!J$3)+0.03 -> 0.67 | K94: =(I94+J94)/G94 -> 0.041409147 | L94: =SUMIF(BOM!A:A,'All Products'!A94,BOM!S:S) -> 0.0677 | M94: =SUMIF(BOM!A:A,'All Products'!A94,BOM!V:V) -> 0.822555 | N94: =(L94+M94)/G94 -> 0.055021941 | O94: 0 | P94: =I94+J94+M94+L94+O94 -> 1.560255 | Q94: =G94-P94 -> 14.619745 | R94: =IFERROR((G94-P94)/G94,0) -> 0.90356891 | Y94: =(G94-I94)/G94 -> 1 | AD94: =_xlfn.XLOOKUP(A94,AF:AF,AF:AF) -> #N/A
A95: 861ACS | B95: Reynolds | C95: PAD THAI MIX 4 X 600GR | D95: KG | E95: =VLOOKUP(A95,BOM!A:E,5,0) -> 2.4 | F95: 10.99 | G95: 10.99 | H95: Active | I95: =SUMIFS(BOM!Q:Q,BOM!A:A,'All Products'!A95,BOM!I:I,'All Products'!I$3) -> 4.717909 | J95: =SUMIFS(BOM!Q:Q,BOM!A:A,'All Products'!A95,BOM!I:I,'All Products'!J$3)+0.03 -> 0.63 | K95: =(I95+J95)/G95 -> 0.48661592 | L95: =SUMIF(BOM!A:A,'All Products'!A95,BOM!S:S) -> 1.684906 | M95: =SUMIF(BOM!A:A,'All Products'!A95,BOM!V:V) -> 0.592375 | N95: =(L95+M95)/G95 -> 0.20721392 | O95: 0 | P95: =I95+J95+M95+L95+O95 -> 7.62519 | Q95: =G95-P95 -> 3.36481 | R95: =IFERROR((G95-P95)/G95,0) -> 0.30617016 | S95: 0 | T95: =S95*G95 -> 0 | U95: =IFERROR(S95*Q95,0) -> 0 | V95: =(G95-P95)*S95 -> 0 | W95: =V95-U95 -> 0 | Y95: =(G95-I95)/G95 -> 0.57070892
A96: 2364CS | B96: Reynolds | C96: PREP 5MM DICED CARROT 1.5KG | D96: KG | E96: =VLOOKUP(A96,BOM!A:E,5,0) -> 1.5 | F96: 3.27 | G96: 3.37 | H96: Active | I96: =SUMIFS(BOM!Q:Q,BOM!A:A,'All Products'!A96,BOM!I:I,'All Products'!I$3) -> 0.79330839 | J96: =SUMIFS(BOM!Q:Q,BOM!A:A,'All Products'!A96,BOM!I:I,'All Products'!J$3)+0.03 -> 0.4 | K96: =(I96+J96)/G96 -> 0.35409745 | L96: =SUMIF(BOM!A:A,'All Products'!A96,BOM!S:S) -> 0.63040536 | M96: =SUMIF(BOM!A:A,'All Products'!A96,BOM!V:V) -> 0.2708 | N96: =(L96+M96)/G96 -> 0.26741999 | O96: 0 | P96: =I96+J96+M96+L96+O96 -> 2.0945138 | Q96: =G96-P96 -> 1.2754862 | R96: =IFERROR((G96-P96)/G96,0) -> 0.37848257 | S96: 11.6 | T96: =S96*G96 -> 39.092 | U96: =IFERROR(S96*Q96,0) -> 14.79564 | V96: =(G96-P96)*S96 -> 14.79564 | W96: =V96-U96 -> 0 | Y96: =(G96-I96)/G96 -> 0.76459692
A97: 2093CS | B97: Reynolds | C97: PREP POT FONDANT 50X70MM20EA | D97: Count | E97: =VLOOKUP(A97,BOM!A:E,5,0) -> 2.84 | F97: 27.18 | G97: 26.59 | H97: Active | I97: =SUMIFS(BOM!Q:Q,BOM!A:A,'All Products'!A97,BOM!I:I,'All Products'!I$3) -> 5.2757549 | J97: =SUMIFS(BOM!Q:Q,BOM!A:A,'All Products'!A97,BOM!I:I,'All Products'!J$3)+0.03 -> 0.4 | K97: =(I97+J97)/G97 -> 0.21345449 | L97: =SUMIF(BOM!A:A,'All Products'!A97,BOM!S:S) -> 2.7739613 | M97: =SUMIF(BOM!A:A,'All Products'!A97,BOM!V:V) -> 0.2708 | N97: =(L97+M97)/G97 -> 0.11450776 | O97: 0 | P97: =I97+J97+M97+L97+O97 -> 8.7205162 | Q97: =G97-P97 -> 17.869484 | R97: =IFERROR((G97-P97)/G97,0) -> 0.67203775 | S97: 38.4 | T97: =S97*G97 -> 1021.056 | U97: =IFERROR(S97*Q97,0) -> 686.18818 | V97: =(G97-P97)*S97 -> 686.18818 | W97: =V97-U97 -> 0 | Y97: =(G97-I97)/G97 -> 0.80158876
A98: 1424CS | B98: Reynolds | C98: PREP STEW PACK 2.5KG | D98: KG | E98: =VLOOKUP(A98,BOM!A:E,5,0) -> 2.5 | F98: 7.9 | G98: 8.23 | H98: Active | I98: =SUMIFS(BOM!Q:Q,BOM!A:A,'All Products'!A98,BOM!I:I,'All Products'!I$3) -> 2.1436438 | J98: =SUMIFS(BOM!Q:Q,BOM!A:A,'All Products'!A98,BOM!I:I,'All Products'!J$3)+0.03 -> 0.4 | K98: =(I98+J98)/G98 -> 0.30906972 | L98: =SUMIF(BOM!A:A,'All Products'!A98,BOM!S:S) -> 2.8236506 | M98: =SUMIF(BOM!A:A,'All Products'!A98,BOM!V:V) -> 0.2961875 | N98: =(L98+M98)/G98 -> 0.37908118 | O98: 0 | P98: =I98+J98+M98+L98+O98 -> 5.6634819 | Q98: =G98-P98 -> 2.5665181 | R98: =IFERROR((G98-P98)/G98,0) -> 0.3118491 | S98: 0 | T98: =S98*G98 -> 0 | U98: =IFERROR(S98*Q98,0) -> 0 | V98: =(G98-P98)*S98 -> 0 | W98: =V98-U98 -> 0 | Y98: =(G98-I98)/G98 -> 0.73953295
A99: 917ACS | B99: Reynolds | C99: GINGER DICED 1X300G | D99: KG | E99: =VLOOKUP(A99,BOM!A:E,5,0) -> 0.3 | F99: 1.61 | G99: 1.78 | H99: Active | I99: =SUMIFS(BOM!Q:Q,BOM!A:A,'All Products'!A99,BOM!I:I,'All Products'!I$3) -> 0.71438943 | J99: =SUMIFS(BOM!Q:Q,BOM!A:A,'All Products'!A99,BOM!I:I,'All Products'!J$3)+0.03 -> 0.145 | K99: =(I99+J99)/G99 -> 0.48280305 | L99: =SUMIF(BOM!A:A,'All Products'!A99,BOM!S:S) -> 0.0761625 | M99: =SUMIF(BOM!A:A,'All Products'!A99,BOM!V:V) -> 0.1607875 | N99: =(L99+M99)/G99 -> 0.13311798 | O99: 0 | P99: =I99+J99+M99+L99+O99 -> 1.0963394 | Q99: =G99-P99 -> 0.68366057 | R99: =IFERROR((G99-P99)/G99,0) -> 0.38407897 | S99: 4487.6 | T99: =S99*G99 -> 7987.928 | U99: =IFERROR(S99*Q99,0) -> 3067.9952 | V99: =(G99-P99)*S99 -> 3067.9952 | W99: =V99-U99 -> 0 | Y99: =(G99-I99)/G99 -> 0.59865762
A100: 1046CS | B100: Reynolds | C100: PREP CHIPS LONG THICK H/C 5KG | D100: KG | E100: =VLOOKUP(A100,BOM!A:E,5,0) -> 5 | F100: 12.38 | G100: 13.65 | H100: Active | I100: =SUMIFS(BOM!Q:Q,BOM!A:A,'All Products'!A100,BOM!I:I,'All Products'!I$3) -> 3.9398995 | J100: =SUMIFS(BOM!Q:Q,BOM!A:A,'All Products'!A100,BOM!I:I,'All Products'!J$3)+0.03 -> 0.45 | K100: =(I100+J100)/G100 -> 0.32160436 | L100: =SUMIF(BOM!A:A,'All Products'!A100,BOM!S:S) -> 1.3984558 | M100: =SUMIF(BOM!A:A,'All Products'!A100,BOM!V:V) -> 0.4011225 | N100: =(L100+M100)/G100 -> 0.13183724 | O100: 0 | P100: =I100+J100+M100+L100+O100 -> 6.1894779 | Q100: =G100-P100 -> 7.4605221 | R100: =IFERROR((G100-P100)/G100,0) -> 0.5465584 | S100: 0 | T100: =S100*G100 -> 0 | U100: =IFERROR(S100*Q100,0) -> 0 | V100: =(G100-P100)*S100 -> 0 | W100: =V100-U100 -> 0 | Y100: =(G100-I100)/G100 -> 0.71136267
A101: 1118CS | B101: Reynolds | C101: PREP CARROTS BATON 1KG | D101: KG | E101: =VLOOKUP(A101,BOM!A:E,5,0) -> 1 | F101: 2.07 | G101: 2.21 | H101: Active | I101: =SUMIFS(BOM!Q:Q,BOM!A:A,'All Products'!A101,BOM!I:I,'All Products'!I$3) -> 0.64071718 | J101: =SUMIFS(BOM!Q:Q,BOM!A:A,'All Products'!A101,BOM!I:I,'All Products'!J$3)+0.03 -> 0.4 | K101: =(I101+J101)/G101 -> 0.47091275 | L101: =SUMIF(BOM!A:A,'All Products'!A101,BOM!S:S) -> 0.3385 | M101: =SUMIF(BOM!A:A,'All Products'!A101,BOM!V:V) -> 0.2183325 | N101: =(L101+M101)/G101 -> 0.25196041 | O101: 0 | P101: =I101+J101+M101+L101+O101 -> 1.5975497 | Q101: =G101-P101 -> 0.61245032 | R101: =IFERROR((G101-P101)/G101,0) -> 0.27712684 | S101: 796.8 | T101: =S101*G101 -> 1760.928 | U101: =IFERROR(S101*Q101,0) -> 488.00041 | V101: =(G101-P101)*S101 -> 488.00041 | W101: =V101-U101 -> 0 | Y101: =(G101-I101)/G101 -> 0.71008272
A102: 1117CS | B102: Reynolds | C102: PREP CARROTS BATON 2.5KG | D102: KG | E102: =VLOOKUP(A102,BOM!A:E,5,0) -> 2.5 | F102: 4.13 | G102: 4.26 | H102: Active | I102: =SUMIFS(BOM!Q:Q,BOM!A:A,'All Products'!A102,BOM!I:I,'All Products'!I$3) -> 1.601793 | J102: =SUMIFS(BOM!Q:Q,BOM!A:A,'All Products'!A102,BOM!I:I,'All Products'!J$3)+0.03 -> 0.4 | K102: =(I102+J102)/G102 -> 0.46990445 | L102: =SUMIF(BOM!A:A,'All Products'!A102,BOM!S:S) -> 0.84625 | M102: =SUMIF(BOM!A:A,'All Products'!A102,BOM!V:V) -> 0.2961875 | N102: =(L102+M102)/G102 -> 0.26817782 | O102: 0 | P102: =I102+J102+M102+L102+O102 -> 3.1442305 | Q102: =G102-P102 -> 1.1157695 | R102: =IFERROR((G102-P102)/G102,0) -> 0.26191773 | S102: 703.8 | T102: =S102*G102 -> 2998.188 | U102: =IFERROR(S102*Q102,0) -> 785.2786 | V102: =(G102-P102)*S102 -> 785.2786 | W102: =V102-U102 -> 0 | Y102: =(G102-I102)/G102 -> 0.62399226
A103: 1152CS | B103: Reynolds | C103: PREP CARROTS SLICED 2.5KG | D103: KG | E103: =VLOOKUP(A103,BOM!A:E,5,0) -> 2.5 | F103: 3.59 | G103: 3.73 | H103: Active | I103: =SUMIFS(BOM!Q:Q,BOM!A:A,'All Products'!A103,BOM!I:I,'All Products'!I$3) -> 1.3221807 | J103: =SUMIFS(BOM!Q:Q,BOM!A:A,'All Products'!A103,BOM!I:I,'All Products'!J$3)+0.03 -> 0.4 | K103: =(I103+J103)/G103 -> 0.46171063 | L103: =SUMIF(BOM!A:A,'All Products'!A103,BOM!S:S) -> 1.4480148 | M103: =SUMIF(BOM!A:A,'All Products'!A103,BOM!V:V) -> 0.2961875 | N103: =(L103+M103)/G103 -> 0.46761456 | O103: 0 | P103: =I103+J103+M103+L103+O103 -> 3.466383 | Q103: =G103-P103 -> 0.26361703 | R103: =IFERROR((G103-P103)/G103,0) -> 0.070674806 | S103: 133.6 | T103: =S103*G103 -> 498.328 | U103: =IFERROR(S103*Q103,0) -> 35.219235 | V103: =(G103-P103)*S103 -> 35.219235 | W103: =V103-U103 -> 0 | Y103: =(G103-I103)/G103 -> 0.64552797
A104: 1173CS | B104: Reynolds | C104: PREP CARROTS WHOLE 2.5KG | D104: KG | E104: =VLOOKUP(A104,BOM!A:E,5,0) -> 2.5 | F104: 3.87 | G104: 4.04 | H104: Active | I104: =SUMIFS(BOM!Q:Q,BOM!A:A,'All Products'!A104,BOM!I:I,'All Products'!I$3) -> 1.295737 | J104: =SUMIFS(BOM!Q:Q,BOM!A:A,'All Products'!A104,BOM!I:I,'All Products'!J$3)+0.03 -> 0.4 | K104: =(I104+J104)/G104 -> 0.41973689 | L104: =SUMIF(BOM!A:A,'All Products'!A104,BOM!S:S) -> 0.97154381 | M104: =SUMIF(BOM!A:A,'All Products'!A104,BOM!V:V) -> 0.2961875 | N104: =(L104+M104)/G104 -> 0.31379488 | O104: 0 | P104: =I104+J104+M104+L104+O104 -> 2.9634684 | Q104: =G104-P104 -> 1.0765316 | R104: =IFERROR((G104-P104)/G104,0) -> 0.26646823 | S104: 637.8 | T104: =S104*G104 -> 2576.712 | U104: =IFERROR(S104*Q104,0) -> 686.61188 | V104: =(G104-P104)*S104 -> 686.61188 | W104: =V104-U104 -> 0 | Y104: =(G104-I104)/G104 -> 0.67927301
A105: 652ACS | B105: Reynolds | C105: BEEF TOMATO SLICED 5MM 2x1KG | D105: KG | E105: =VLOOKUP(A105,BOM!A:E,5,0) -> 2 | F105: 10.7 | G105: 10.55 | H105: Active | I105: =SUMIFS(BOM!Q:Q,BOM!A:A,'All Products'!A105,BOM!I:I,'All Products'!I$3) -> 3.4736842 | J105: =SUMIFS(BOM!Q:Q,BOM!A:A,'All Products'!A105,BOM!I:I,'All Products'!J$3)+0.03 -> 1.57 | K105: =(I105+J105)/G105 -> 0.47807433 | L105: =SUMIF(BOM!A:A,'All Products'!A105,BOM!S:S) -> 0.99023669 | M105: =SUMIF(BOM!A:A,'All Products'!A105,BOM!V:V) -> 0.48744 | N105: =(L105+M105)/G105 -> 0.14006414 | O105: 0 | P105: =I105+J105+M105+L105+O105 -> 6.5213609 | Q105: =G105-P105 -> 4.0286391 | R105: =IFERROR((G105-P105)/G105,0) -> 0.38186153 | S105: 387.6 | T105: =S105*G105 -> 4089.18 | U105: =IFERROR(S105*Q105,0) -> 1561.5005 | V105: =(G105-P105)*S105 -> 1561.5005 | W105: =V105-U105 -> 0 | Y105: =(G105-I105)/G105 -> 0.67074083
A106: 916ACS | B106: Reynolds | C106: PREP COURGETTE MATCHSTICKS 2X500G | D106: KG | E106: =VLOOKUP(A106,BOM!A:E,5,0) -> 1 | F106: 5.22 | G106: 5.13 | H106: Active | I106: =SUMIFS(BOM!Q:Q,BOM!A:A,'All Products'!A106,BOM!I:I,'All Products'!I$3) -> 1.4666667 | J106: =SUMIFS(BOM!Q:Q,BOM!A:A,'All Products'!A106,BOM!I:I,'All Products'!J$3)+0.03 -> 0.77 | K106: =(I106+J106)/G106 -> 0.4359974 | L106: =SUMIF(BOM!A:A,'All Products'!A106,BOM!S:S) -> 0.4062 | M106: =SUMIF(BOM!A:A,'All Products'!A106,BOM!V:V) -> 0.355425 | N106: =(L106+M106)/G106 -> 0.14846491 | O106: 0 | P106: =I106+J106+M106+L106+O106 -> 2.9982917 | Q106: =G106-P106 -> 2.1317083 | R106: =IFERROR((G106-P106)/G106,0) -> 0.41553769 | S106: 1333.6 | T106: =S106*G106 -> 6841.368 | U106: =IFERROR(S106*Q106,0) -> 2842.8462 | V106: =(G106-P106)*S106 -> 2842.8462 | W106: =V106-U106 -> 0 | Y106: =(G106-I106)/G106 -> 0.71410006
... A110: Z401CS | B110: Dnata | C110: PAK CHOI CHPD 25MM FR H/C 1KG | D110: KG | E110: =VLOOKUP(A110,BOM!A:E,5,0) -> 1 | F110: 5.94 | G110: 5.23 | H110: Active | I110: =SUMIFS(BOM!Q:Q,BOM!A:A,'All Products'!A110,BOM!I:I,'All Products'!I$3) -> 2.6905405 | J110: =SUMIFS(BOM!Q:Q,BOM!A:A,'All Products'!A110,BOM!I:I,'All Products'!J$3)+0.03 -> 0.17 | K110: =(I110+J110)/G110 -> 0.54694848 | L110: =SUMIF(BOM!A:A,'All Products'!A110,BOM!S:S) -> 1.1969482 | M110: =SUMIF(BOM!A:A,'All Products'!A110,BOM!V:V) -> 0.21720417 | N110: =(L110+M110)/G110 -> 0.27039242 | O110: 0 | P110: =I110+J110+M110+L110+O110 -> 4.2746929 | Q110: =G110-P110 -> 0.95530709 | R110: =IFERROR((G110-P110)/G110,0) -> 0.1826591 | S110: 2.2 | T110: =S110*G110 -> 11.506 | U110: =IFERROR(S110*Q110,0) -> 2.1016756 | V110: =(G110-P110)*S110 -> 2.1016756 | W110: =V110-U110 -> 0 | Y110: =(G110-I110)/G110 -> 0.4855563
A111: Z402CS | B111: Dnata | C111: POTS CHIP CUT 1.6 X 1.6 X 6CM H/C 1KG | D111: KG | E111: =VLOOKUP(A111,BOM!A:E,5,0) -> 1 | F111: 5.62 | G111: 5.63 | H111: In Active | I111: =SUMIFS(BOM!Q:Q,BOM!A:A,'All Products'!A111,BOM!I:I,'All Products'!I$3) -> 0 | J111: =SUMIFS(BOM!Q:Q,BOM!A:A,'All Products'!A111,BOM!I:I,'All Products'!J$3)+0.03 -> 0.17 | K111: =(I111+J111)/G111 -> 0.030195382 | L111: =SUMIF(BOM!A:A,'All Products'!A111,BOM!S:S) -> 0.03385 | M111: =SUMIF(BOM!A:A,'All Products'!A111,BOM!V:V) -> 0.21720417 | N111: =(L111+M111)/G111 -> 0.044592214 | O111: 0 | P111: =I111+J111+M111+L111+O111 -> 0.42105417 | Q111: =G111-P111 -> 5.2089458 | R111: =IFERROR((G111-P111)/G111,0) -> 0.9252124 | Y111: =(G111-I111)/G111 -> 1 | AD111: =_xlfn.XLOOKUP(A111,AF:AF,AF:AF) -> #N/A
A112: Z371CS | B112: Dnata | C112: RUSS POT SLC 1.5CM M/C RTW 1KG | D112: KG | E112: =VLOOKUP(A112,BOM!A:E,5,0) -> 1 | F112: 1.86 | G112: 1.85 | H112: Active | I112: =SUMIFS(BOM!Q:Q,BOM!A:A,'All Products'!A112,BOM!I:I,'All Products'!I$3) -> 0.63527156 | J112: =SUMIFS(BOM!Q:Q,BOM!A:A,'All Products'!A112,BOM!I:I,'All Products'!J$3)+0.03 -> 0.17 | K112: =(I112+J112)/G112 -> 0.43528193 | L112: =SUMIF(BOM!A:A,'All Products'!A112,BOM!S:S) -> 0.77445491 | M112: =SUMIF(BOM!A:A,'All Products'!A112,BOM!V:V) -> 0.21720417 | N112: =(L112+M112)/G112 -> 0.53603193 | O112: 0 | P112: =I112+J112+M112+L112+O112 -> 1.7969306 | Q112: =G112-P112 -> 0.053069363 | R112: =IFERROR((G112-P112)/G112,0) -> 0.028686142 | S112: 0.4 | T112: =S112*G112 -> 0.74 | U112: =IFERROR(S112*Q112,0) -> 0.021227745 | V112: =(G112-P112)*S112 -> 0.021227745 | W112: =V112-U112 -> 0 | Y112: =(G112-I112)/G112 -> 0.65660997
A113: Z370CS | B113: Dnata | C113: RUSS POT SLC 1.5CM M/C RTW 2.5 | D113: KG | E113: =VLOOKUP(A113,BOM!A:E,5,0) -> 2.5 | F113: 3.42 | G113: 3.33 | H113: Active | I113: =SUMIFS(BOM!Q:Q,BOM!A:A,'All Products'!A113,BOM!I:I,'All Products'!I$3) -> 1.5881789 | J113: =SUMIFS(BOM!Q:Q,BOM!A:A,'All Products'!A113,BOM!I:I,'All Products'!J$3)+0.03 -> 0.17 | K113: =(I113+J113)/G113 -> 0.52798165 | L113: =SUMIF(BOM!A:A,'All Products'!A113,BOM!S:S) -> 1.9361373 | M113: =SUMIF(BOM!A:A,'All Products'!A113,BOM!V:V) -> 0.2961875 | N113: =(L113+M113)/G113 -> 0.6703678 | O113: 0 | P113: =I113+J113+M113+L113+O113 -> 3.9905037 | Q113: =G113-P113 -> -0.66050368 | R113: =IFERROR((G113-P113)/G113,0) -> -0.19834945 | S113: 0 | T113: =S113*G113 -> 0 | U113: =IFERROR(S113*Q113,0) -> 0 | V113: =(G113-P113)*S113 -> 0 | W113: =V113-U113 -> 0 | Y113: =(G113-I113)/G113 -> 0.5230694
A114: Z136CS | B114: Dnata | C114: BEAN FINE 25MM H/C RTW 2.5KG | D114: KG | E114: =VLOOKUP(A114,BOM!A:E,5,0) -> 2.5 | F114: 35.75 | G114: 36.61 | H114: Active | I114: =SUMIFS(BOM!Q:Q,BOM!A:A,'All Products'!A114,BOM!I:I,'All Products'!I$3) -> #N/A | J114: =SUMIFS(BOM!Q:Q,BOM!A:A,'All Products'!A114,BOM!I:I,'All Products'!J$3)+0.03 -> 0.17 | K114: =(I114+J114)/G114 -> #N/A | L114: =SUMIF(BOM!A:A,'All Products'!A114,BOM!S:S) -> 15.595179 | M114: =SUMIF(BOM!A:A,'All Products'!A114,BOM!V:V) -> 0.2961875 | N114: =(L114+M114)/G114 -> 0.43407173 | O114: 0 | P114: =I114+J114+M114+L114+O114 -> #N/A | Q114: =G114-P114 -> #N/A | R114: =IFERROR((G114-P114)/G114,0) -> 0 | S114: 8.2 | T114: =S114*G114 -> 300.202 | U114: =IFERROR(S114*Q114,0) -> 0 | V114: =(G114-P114)*S114 -> #N/A | W114: =V114-U114 -> #N/A | Y114: =(G114-I114)/G114 -> #N/A
A115: Z332CS | B115: Dnata | C115: PEP GR DICE 2CM H/C SQ RTW 1KG | D115: KG | E115: =VLOOKUP(A115,BOM!A:E,5,0) -> 1 | F115: 8.05 | G115: 8.46 | H115: Active | I115: =SUMIFS(BOM!Q:Q,BOM!A:A,'All Products'!A115,BOM!I:I,'All Products'!I$3) -> 3.872 | J115: =SUMIFS(BOM!Q:Q,BOM!A:A,'All Products'!A115,BOM!I:I,'All Products'!J$3)+0.03 -> 0.17 | K115: =(I115+J115)/G115 -> 0.47777778 | L115: =SUMIF(BOM!A:A,'All Products'!A115,BOM!S:S) -> 2.284875 | M115: =SUMIF(BOM!A:A,'All Products'!A115,BOM!V:V) -> 0.21720417 | N115: =(L115+M115)/G115 -> 0.29575404 | O115: 0 | P115: =I115+J115+M115+L115+O115 -> 6.5440792 | Q115: =G115-P115 -> 1.9159208 | R115: =IFERROR((G115-P115)/G115,0) -> 0.22646818 | S115: 0 | T115: =S115*G115 -> 0 | U115: =IFERROR(S115*Q115,0) -> 0 | V115: =(G115-P115)*S115 -> 0 | W115: =V115-U115 -> 0 | Y115: =(G115-I115)/G115 -> 0.54231678
A116: Z331CS | B116: Dnata | C116: PEP GR DICE 2CM H/C SQ RTW 2.5 | D116: KG | E116: =VLOOKUP(A116,BOM!A:E,5,0) -> 2.5 | F116: 20.11 | G116: 21.11 | H116: Active | I116: =SUMIFS(BOM!Q:Q,BOM!A:A,'All Products'!A116,BOM!I:I,'All Products'!I$3) -> 9.68 | J116: =SUMIFS(BOM!Q:Q,BOM!A:A,'All Products'!A116,BOM!I:I,'All Products'!J$3)+0.03 -> 0.17 | K116: =(I116+J116)/G116 -> 0.46660351 | L116: =SUMIF(BOM!A:A,'All Products'!A116,BOM!S:S) -> 5.7121875 | M116: =SUMIF(BOM!A:A,'All Products'!A116,BOM!V:V) -> 0.2961875 | N116: =(L116+M116)/G116 -> 0.28462222 | O116: 0 | P116: =I116+J116+M116+L116+O116 -> 15.858375 | Q116: =G116-P116 -> 5.251625 | R116: =IFERROR((G116-P116)/G116,0) -> 0.24877428 | S116: 0.4 | T116: =S116*G116 -> 8.444 | U116: =IFERROR(S116*Q116,0) -> 2.10065 | V116: =(G116-P116)*S116 -> 2.10065 | W116: =V116-U116 -> 0 | Y116: =(G116-I116)/G116 -> 0.54144955
A117: Z336CS | B117: Dnata | C117: CARROT MINCED FR 1KG | D117: KG | E117: =VLOOKUP(A117,BOM!A:E,5,0) -> 1 | F117: 2.11 | G117: 2.28 | H117: Active | I117: =SUMIFS(BOM!Q:Q,BOM!A:A,'All Products'!A117,BOM!I:I,'All Products'!I$3) -> 0.69105976 | J117: =SUMIFS(BOM!Q:Q,BOM!A:A,'All Products'!A117,BOM!I:I,'All Products'!J$3)+0.03 -> 0.17 | K117: =(I117+J117)/G117 -> 0.37765779 | L117: =SUMIF(BOM!A:A,'All Products'!A117,BOM!S:S) -> 0.77414766 | M117: =SUMIF(BOM!A:A,'All Products'!A117,BOM!V:V) -> 0.21720417 | N117: =(L117+M117)/G117 -> 0.43480343 | O117: 0 | P117: =I117+J117+M117+L117+O117 -> 1.8524116 | Q117: =G117-P117 -> 0.42758842 | R117: =IFERROR((G117-P117)/G117,0) -> 0.18753878 | S117: 7.8 | T117: =S117*G117 -> 17.784 | U117: =IFERROR(S117*Q117,0) -> 3.3351897 | V117: =(G117-P117)*S117 -> 3.3351897 | W117: =V117-U117 -> 0 | Y117: =(G117-I117)/G117 -> 0.69690362
A118: Z335CS | B118: Dnata | C118: CARROT MINCED FR 2.5KG | D118: KG | E118: =VLOOKUP(A118,BOM!A:E,5,0) -> 2.5 | F118: 5.26 | G118: 5.69 | H118: Active | I118: =SUMIFS(BOM!Q:Q,BOM!A:A,'All Products'!A118,BOM!I:I,'All Products'!I$3) -> 1.7276494 | J118: =SUMIFS(BOM!Q:Q,BOM!A:A,'All Products'!A118,BOM!I:I,'All Products'!J$3)+0.03 -> 0.17 | K118: =(I118+J118)/G118 -> 0.33350604 | L118: =SUMIF(BOM!A:A,'All Products'!A118,BOM!S:S) -> 1.9353691 | M118: =SUMIF(BOM!A:A,'All Products'!A118,BOM!V:V) -> 0.2961875 | N118: =(L118+M118)/G118 -> 0.39218922 | O118: 0 | P118: =I118+J118+M118+L118+O118 -> 4.129206 | Q118: =G118-P118 -> 1.560794 | R118: =IFERROR((G118-P118)/G118,0) -> 0.27430474 | S118: 6.8 | T118: =S118*G118 -> 38.692 | U118: =IFERROR(S118*Q118,0) -> 10.613399 | V118: =(G118-P118)*S118 -> 10.613399 | W118: =V118-U118 -> 0 | Y118: =(G118-I118)/G118 -> 0.69637093
A119: Z337CS | B119: Dnata | C119: CARROT MINCED FR 250G | D119: KG | E119: =VLOOKUP(A119,BOM!A:E,5,0) -> 0.25 | F119: 0.53 | G119: 0.63 | H119: Active | I119: =SUMIFS(BOM!Q:Q,BOM!A:A,'All Products'!A119,BOM!I:I,'All Products'!I$3) -> 0.17276494 | J119: =SUMIFS(BOM!Q:Q,BOM!A:A,'All Products'!A119,BOM!I:I,'All Products'!J$3)+0.03 -> 0.08 | K119: =(I119+J119)/G119 -> 0.40121419 | L119: =SUMIF(BOM!A:A,'All Products'!A119,BOM!S:S) -> 0.19353691 | M119: =SUMIF(BOM!A:A,'All Products'!A119,BOM!V:V) -> 0.1607875 | N119: =(L119+M119)/G119 -> 0.56241971 | O119: 0 | P119: =I119+J119+M119+L119+O119 -> 0.60708935 | Q119: =G119-P119 -> 0.022910647 | R119: =IFERROR((G119-P119)/G119,0) -> 0.036366106 | S119: 11.6 | T119: =S119*G119 -> 7.308 | U119: =IFERROR(S119*Q119,0) -> 0.2657635 | V119: =(G119-P119)*S119 -> 0.2657635 | W119: =V119-U119 -> 0 | Y119: =(G119-I119)/G119 -> 0.72576994
A120: Z305CS | B120: Dnata | C120: CHILLI GRN SLC SEEDS M/C 1KG | D120: KG | E120: =VLOOKUP(A120,BOM!A:E,5,0) -> 1 | F120: 18.57 | G120: 18.96 | H120: Active | I120: =SUMIFS(BOM!Q:Q,BOM!A:A,'All Products'!A120,BOM!I:I,'All Products'!I$3) -> 3.5183084 | J120: =SUMIFS(BOM!Q:Q,BOM!A:A,'All Products'!A120,BOM!I:I,'All Products'!J$3)+0.03 -> 0.17 | K120: =(I120+J120)/G120 -> 0.19453103 | L120: =SUMIF(BOM!A:A,'All Products'!A120,BOM!S:S) -> 1.6473667 | M120: =SUMIF(BOM!A:A,'All Products'!A120,BOM!V:V) -> 0.21720417 | N120: =(L120+M120)/G120 -> 0.098342344 | O120: 0 | P120: =I120+J120+M120+L120+O120 -> 5.5528792 | Q120: =G120-P120 -> 13.407121 | R120: =IFERROR((G120-P120)/G120,0) -> 0.70712662 | S120: 13 | T120: =S120*G120 -> 246.48 | U120: =IFERROR(S120*Q120,0) -> 174.29257 | V120: =(G120-P120)*S120 -> 174.29257 | W120: =V120-U120 -> 0 | Y120: =(G120-I120)/G120 -> 0.81443521
A121: Z304CS | B121: Dnata | C121: CHILLI GRN SLC SEEDS M/C 2.5KG | D121: KG | E121: =VLOOKUP(A121,BOM!A:E,5,0) -> 2.5 | F121: 46.75 | G121: 47.86 | H121: Active | I121: =SUMIFS(BOM!Q:Q,BOM!A:A,'All Products'!A121,BOM!I:I,'All Products'!I$3) -> 8.795771 | J121: =SUMIFS(BOM!Q:Q,BOM!A:A,'All Products'!A121,BOM!I:I,'All Products'!J$3)+0.03 -> 0.17 | K121: =(I121+J121)/G121 -> 0.18733329 | L121: =SUMIF(BOM!A:A,'All Products'!A121,BOM!S:S) -> 4.1184167 | M121: =SUMIF(BOM!A:A,'All Products'!A121,BOM!V:V) -> 0.2961875 | N121: =(L121+M121)/G121 -> 0.092239953 | O121: 0 | P121: =I121+J121+M121+L121+O121 -> 13.380375 | Q121: =G121-P121 -> 34.479625 | R121: =IFERROR((G121-P121)/G121,0) -> 0.72042676 | S121: 0 | T121: =S121*G121 -> 0 | U121: =IFERROR(S121*Q121,0) -> 0 | V121: =(G121-P121)*S121 -> 0 | W121: =V121-U121 -> 0 | Y121: =(G121-I121)/G121 -> 0.81621874
A122: Z258CS | B122: Dnata | C122: CAR MATCH 2.5MM M/C RTW 1KG | D122: KG | E122: =VLOOKUP(A122,BOM!A:E,5,0) -> 1 | F122: 1.49 | G122: 1.52 | H122: In Active | I122: =SUMIFS(BOM!Q:Q,BOM!A:A,'All Products'!A122,BOM!I:I,'All Products'!I$3) -> 0 | J122: =SUMIFS(BOM!Q:Q,BOM!A:A,'All Products'!A122,BOM!I:I,'All Products'!J$3)+0.03 -> 0.17 | K122: =(I122+J122)/G122 -> 0.11184211 | L122: =SUMIF(BOM!A:A,'All Products'!A122,BOM!S:S) -> 0 | M122: =SUMIF(BOM!A:A,'All Products'!A122,BOM!V:V) -> 0.21720417 | N122: =(L122+M122)/G122 -> 0.14289748 | O122: 0 | P122: =I122+J122+M122+L122+O122 -> 0.38720417 | Q122: =G122-P122 -> 1.1327958 | R122: =IFERROR((G122-P122)/G122,0) -> 0.74526042 | Y122: =(G122-I122)/G122 -> 1 | AD122: =_xlfn.XLOOKUP(A122,AF:AF,AF:AF) -> #N/A
A123: Z257CS | B123: Dnata | C123: CAR MATCH 2.5MM M/C RTW 2.5KG | D123: KG | E123: =VLOOKUP(A123,BOM!A:E,5,0) -> 2.5 | F123: 5.81 | G123: 5.93 | H123: In Active | I123: =SUMIFS(BOM!Q:Q,BOM!A:A,'All Products'!A123,BOM!I:I,'All Products'!I$3) -> 0 | J123: =SUMIFS(BOM!Q:Q,BOM!A:A,'All Products'!A123,BOM!I:I,'All Products'!J$3)+0.03 -> 0.17 | K123: =(I123+J123)/G123 -> 0.028667791 | L123: =SUMIF(BOM!A:A,'All Products'!A123,BOM!S:S) -> 0 | M123: =SUMIF(BOM!A:A,'All Products'!A123,BOM!V:V) -> 0.2961875 | N123: =(L123+M123)/G123 -> 0.049947302 | O123: 0 | P123: =I123+J123+M123+L123+O123 -> 0.4661875 | Q123: =G123-P123 -> 5.4638125 | R123: =IFERROR((G123-P123)/G123,0) -> 0.92138491 | Y123: =(G123-I123)/G123 -> 1 | AD123: =_xlfn.XLOOKUP(A123,AF:AF,AF:AF) -> #N/A
A124: Z339CS | B124: Dnata | C124: CARROT WHL PEELED HAND CUT 2.5 | D124: KG | E124: =VLOOKUP(A124,BOM!A:E,5,0) -> 2.5 | F124: 3.67 | G124: 3.96 | H124: Active | I124: =SUMIFS(BOM!Q:Q,BOM!A:A,'All Products'!A124,BOM!I:I,'All Products'!I$3) -> 1.295737 | J124: =SUMIFS(BOM!Q:Q,BOM!A:A,'All Products'!A124,BOM!I:I,'All Products'!J$3)+0.03 -> 0.17 | K124: =(I124+J124)/G124 -> 0.37013562 | L124: =SUMIF(BOM!A:A,'All Products'!A124,BOM!S:S) -> 1.0561688 | M124: =SUMIF(BOM!A:A,'All Products'!A124,BOM!V:V) -> 0.2961875 | N124: =(L124+M124)/G124 -> 0.34150412 | O124: 0 | P124: =I124+J124+M124+L124+O124 -> 2.8180934 | Q124: =G124-P124 -> 1.1419066 | R124: =IFERROR((G124-P124)/G124,0) -> 0.28836026 | S124: 0 | T124: =S124*G124 -> 0 | U124: =IFERROR(S124*Q124,0) -> 0 | V124: =(G124-P124)*S124 -> 0 | W124: =V124-U124 -> 0 | Y124: =(G124-I124)/G124 -> 0.67279368
...

Sheet BOM
A1: ITEM_CODE | B1: Customer | C1: ITEM_NAME | D1: UoM | E1: Pack Size (UoM) | F1: Material code | G1: Material Description | H1: Material/Process description | I1: Material/Category | J1: Output Qty % | K1: Output Qty | L1: Total Output qty | M1: Yield | N1: STD Material Per Qty | O1: UOM | P1: Price | Q1: M.Cost/pcs | R1: Labour Min/KG Out put | S1: Labour Cost (Processing)/Product | T1: Total Labour Hr/Product | U1: Labour Min/Packing | V1: Labour Cost (Packing)/Product | W1: Total Labour Hr/Packing | X1: Labour cost/product | Y1: Total Labour cost | Z1: Produced Qty | AA1: STD Consumption Qty | AB1: Total Material Cost | AC1: STD Labour Hrs | AD1: Total Labour Cost | AE1: Chemical Used | AF1: Chemical cost/kg input | AG1: Chemical cost/Product | AH1: Total Chemical Cost | AI1: Total Cost | AJ1: Sales Price | AK1: Sales Value | AL1: Low risk | AM1: High care | AN1: Labour Rate/Min | AO1: =20.31/60 -> 0.3385 | AP1: Time Factor | AQ1: total time/product | AR1: Group | AT1: Washed
A2: 1145CS | B2: Reynolds | C2: PREP CARROTS JULIENNE 1KG | D2: KG | E2: 1 | F2: =VLOOKUP(H2,'RM Used'!A:B,2,0) -> 032ACS | G2: =IFERROR(VLOOKUP(F2,'RM Cost'!A:B,2,0),"") -> RM - LRG PROCESSING CARROT X 1000KG | H2: Carrot - Julienne | I2: =VLOOKUP(F2,'RM Used'!B:D,3,0) -> RM-FOOD | J2: 1 | K2: =IF(I2="RM-FOOD",J2*E2,"") -> 1 | L2: =IFERROR(K2*Z2,0) -> 1 | M2: {=_xlfn.IFS(BOM!I2="RM-PACKING","100%",B2="Reynolds",VLOOKUP(H2,'Yield & Time'!A:V,22,0),BOM!B2="Dnata",VLOOKUP(BOM!H2,'Yield & Time'!A:M,13,0),B2="NK",VLOOKUP(H2,'Yield & Time'!A:X,24,0))} -> 0.7533 | N2: =IFERROR(IF(I2="RM-FOOD",(E2*J2)/M2,1),0) -> 1.3274924 | O2: =VLOOKUP(H2,'RM Used'!A:E,5,0) -> KG | P2: =VLOOKUP(H2,'RM Used'!A:F,6,0) -> 0.38 | Q2: =P2*N2 -> 0.5044471 | R2: =IFERROR(IF(B2="Reynolds",VLOOKUP(H2,'Yield & Time'!A:U,21,0),VLOOKUP(H2,'Yield & Time'!A:L,12,0)),0) -> 0.90531915 | S2: =R2*J2*E2*AO$1 -> 0.30645053 | T2: =(R2*Z2*J2*E2)/60 -> 0.015088652 | U2: =IF(A1=A2,0,VLOOKUP(A2,'Packing Time'!A:F,6,0)) -> 0.55 | V2: =U2*AO$1 -> 0.186175 | W2: =(U2*Z2)/60 -> 0.0091666667 | X2: =((R2*J2*E2)+U2)*AO$1*AP2 -> 0.54188809 | Y2: =X2*Z2 -> 0.54188809 | Z2: 1 | AA2: =Z2*N2 -> 1.3274924 | AB2: =AA2*P2 -> 0.5044471 | AC2: =(((R2*J2*E2)+U2)/60)*Z2*AP2 -> 0.026680851 | AD2: =AC2*60*AO$1 -> 0.54188809 | AE2: =VLOOKUP(H2,'Yield & Time'!A:R,18,0) -> CHLORINE | AF2: =IFERROR(VLOOKUP(AE2,'Chemical Cost'!A:D,4,0),0) -> 0.027756518 | AG2: =AF2*N2/3 -> 0.012282189 | AH2: =AF2*AA2/3 -> 0.012282189 | AI2: =IFERROR((Q2*Z2)+(Z2*X2)+AH2,0) -> 1.0586174 | AJ2: =IFERROR(VLOOKUP(A2,'All Products'!A:F,6,0),0) -> 1.67 | AK2: =AJ2*Z2*J2 -> 1.67 | AL2: 0.85 | AM2: 0.15 | AN2: #N/A | AP2: 1.1 | AQ2: =(((R2*J2*E2)+U2)/60)*AP2 -> 0.026680851 | AR2: =_xlfn.XLOOKUP(F2,'RM Cost'!A:A,'RM Cost'!S:S) -> 0 | AS2: =_xlfn.XLOOKUP(A2,[3]Sheet1!$B:$B,[3]Sheet1!$B:$B) -> 1145CS | AT2: =_xlfn.XLOOKUP(H2,'Yield & Time'!A:A,'Yield & Time'!O:O) -> Yes
A3: 1145CS | B3: Reynolds | C3: PREP CARROTS JULIENNE 1KG | D3: KG | E3: 1 | F3: =VLOOKUP(H3,'RM Used'!A:B,2,0) -> P0001 | G3: =IFERROR(VLOOKUP(F3,'RM Cost'!A:B,2,0),"") -> SOL 30EL # PPLUS 630x1000 BLUE -1 | H3: SOL 30EL # PPLUS 630x1000 BLUE -1 | I3: =VLOOKUP(F3,'RM Used'!B:D,3,0) -> RM-PACKING | J3: 1 | K3: =IF(I3="RM-FOOD",J3*E3,"") | L3: =IFERROR(K3*Z3,0) -> 0 | M3: {=_xlfn.IFS(BOM!I3="RM-PACKING","100%",B3="Reynolds",VLOOKUP(H3,'Yield & Time'!A:V,22,0),BOM!B3="Dnata",VLOOKUP(BOM!H3,'Yield & Time'!A:M,13,0),B3="NK",VLOOKUP(H3,'Yield & Time'!A:X,24,0))} -> 100% | N3: =IFERROR(IF(I3="RM-FOOD",(E3*J3)/M3,1),0) -> 1 | O3: =VLOOKUP(H3,'RM Used'!A:E,5,0) -> Count | P3: =VLOOKUP(H3,'RM Used'!A:F,6,0) -> 0.08 | Q3: =P3*N3 -> 0.08 | R3: =IFERROR(IF(B3="Reynolds",VLOOKUP(H3,'Yield & Time'!A:U,21,0),VLOOKUP(H3,'Yield & Time'!A:L,12,0)),0) -> 0 | S3: =R3*J3*E3*AO$1 -> 0 | T3: =(R3*Z3*J3*E3)/60 -> 0 | U3: =IF(A2=A3,0,VLOOKUP(A3,'Packing Time'!A:F,6,0)) -> 0 | V3: =U3*AO$1 -> 0 | W3: =(U3*Z3)/60 -> 0 | X3: =((R3*J3*E3)+U3)*AO$1*AP3 -> 0 | Y3: =X3*Z3 -> 0 | Z3: 1 | AA3: =Z3*N3 -> 1 | AB3: =AA3*P3 -> 0.08 | AC3: =(((R3*J3*E3)+U3)/60)*Z3*AP3 -> 0 | AD3: =AC3*60*AO$1 -> 0 | AF3: =IFERROR(VLOOKUP(AE3,'Chemical Cost'!A:D,4,0),0) -> 0 | AG3: =AF3*N3/3 -> 0 | AH3: =AF3*AA3/3 -> 0 | AI3: =IFERROR((Q3*Z3)+(Z3*X3)+AH3,0) -> 0.08 | AJ3: =IFERROR(VLOOKUP(A3,'All Products'!A:F,6,0),0) -> 1.67 | AL3: 0.85 | AM3: 0.15 | AN3: #N/A | AP3: 1.1 | AQ3: =(((R3*J3*E3)+U3)/60)*AP3 -> 0 | AR3: =_xlfn.XLOOKUP(F3,'RM Cost'!A:A,'RM Cost'!S:S) -> 0 | AS3: =_xlfn.XLOOKUP(A3,[3]Sheet1!$B:$B,[3]Sheet1!$B:$B) -> 1145CS | AT3: =_xlfn.XLOOKUP(H3,'Yield & Time'!A:A,'Yield & Time'!F:F) -> #N/A
A4: 1145CS | B4: Reynolds | C4: PREP CARROTS JULIENNE 1KG | D4: KG | E4: 1 | F4: =VLOOKUP(H4,'RM Used'!A:B,2,0) -> P0016 | G4: =IFERROR(VLOOKUP(F4,'RM Cost'!A:B,2,0),"") -> REY 40 30 BOX | H4: black box | I4: =VLOOKUP(F4,'RM Used'!B:D,3,0) -> RM-PACKING | J4: 1 | K4: =IF(I4="RM-FOOD",J4*E4,"") | L4: =IFERROR(K4*Z4,0) -> 0 | M4: {=_xlfn.IFS(BOM!I4="RM-PACKING","100%",B4="Reynolds",VLOOKUP(H4,'Yield & Time'!A:V,22,0),BOM!B4="Dnata",VLOOKUP(BOM!H4,'Yield & Time'!A:M,13,0),B4="NK",VLOOKUP(H4,'Yield & Time'!A:X,24,0))} -> 100% | N4: =IFERROR(IF(I4="RM-FOOD",(E4*J4)/M4,1),0) -> 1 | O4: =VLOOKUP(H4,'RM Used'!A:E,5,0) -> Count | P4: =VLOOKUP(H4,'RM Used'!A:F,6,0) -> 0.28 | Q4: =P4*N4 -> 0.28 | R4: =IFERROR(IF(B4="Reynolds",VLOOKUP(H4,'Yield & Time'!A:U,21,0),VLOOKUP(H4,'Yield & Time'!A:L,12,0)),0) -> 0 | S4: =R4*J4*E4*AO$1 -> 0 | T4: =(R4*Z4*J4*E4)/60 -> 0 | U4: =IF(A3=A4,0,VLOOKUP(A4,'Packing Time'!A:F,6,0)) -> 0 | V4: =U4*AO$1 -> 0 | W4: =(U4*Z4)/60 -> 0 | X4: =((R4*J4*E4)+U4)*AO$1*AP4 -> 0 | Y4: =X4*Z4 -> 0 | Z4: 1 | AA4: =Z4*N4 -> 1 | AB4: =AA4*P4 -> 0.28 | AC4: =(((R4*J4*E4)+U4)/60)*Z4*AP4 -> 0 | AD4: =AC4*60*AO$1 -> 0 | AF4: =IFERROR(VLOOKUP(AE4,'Chemical Cost'!A:D,4,0),0) -> 0 | AG4: =AF4*N4/3 -> 0 | AH4: =AF4*AA4/3 -> 0 | AI4: =IFERROR((Q4*Z4)+(Z4*X4)+AH4,0) -> 0.28 | AJ4: =IFERROR(VLOOKUP(A4,'All Products'!A:F,6,0),0) -> 1.67 | AL4: 0.85 | AM4: 0.15 | AN4: #N/A | AP4: 1.1 | AQ4: =(((R4*J4*E4)+U4)/60)*AP4 -> 0 | AR4: =_xlfn.XLOOKUP(F4,'RM Cost'!A:A,'RM Cost'!S:S) -> 0 | AS4: =_xlfn.XLOOKUP(A4,[3]Sheet1!$B:$B,[3]Sheet1!$B:$B) -> 1145CS | AT4: =_xlfn.XLOOKUP(H4,'Yield & Time'!A:A,'Yield & Time'!F:F) -> #N/A
A5: 1480CS | B5: Reynolds | C5: PREP ROOT VEG MIX CHNKY 2.5KG | D5: KG | E5: 2.5 | F5: =VLOOKUP(H5,'RM Used'!A:B,2,0) -> 032ACS | G5: =IFERROR(VLOOKUP(F5,'RM Cost'!A:B,2,0),"") -> RM - LRG PROCESSING CARROT X 1000KG | H5: Carrot - Peeled & Diced 25mm | I5: =VLOOKUP(F5,'RM Used'!B:D,3,0) -> RM-FOOD | J5: 0.25 | K5: =IF(I5="RM-FOOD",J5*E5,"") -> 0.625 | L5: =IFERROR(K5*Z5,0) -> 0.625 | M5: {=_xlfn.IFS(BOM!I5="RM-PACKING","100%",B5="Reynolds",VLOOKUP(H5,'Yield & Time'!A:V,22,0),BOM!B5="Dnata",VLOOKUP(BOM!H5,'Yield & Time'!A:M,13,0),B5="NK",VLOOKUP(H5,'Yield & Time'!A:X,24,0))} -> 0.71506674 | N5: =IFERROR(IF(I5="RM-FOOD",(E5*J5)/M5,1),0) -> 0.87404429 | O5: =VLOOKUP(H5,'RM Used'!A:E,5,0) -> KG | P5: =VLOOKUP(H5,'RM Used'!A:F,6,0) -> 0.38 | Q5: =P5*N5 -> 0.33213683 | R5: =IFERROR(IF(B5="Reynolds",VLOOKUP(H5,'Yield & Time'!A:U,21,0),VLOOKUP(H5,'Yield & Time'!A:L,12,0)),0) -> 1.2475449 | S5: =R5*J5*E5*AO$1 -> 0.26393372 | T5: =(R5*Z5*J5*E5)/60 -> 0.01299526 | U5: =IF(A4=A5,0,VLOOKUP(A5,'Packing Time'!A:F,6,0)) -> 0.875 | V5: =U5*AO$1 -> 0.2961875 | W5: =(U5*Z5)/60 -> 0.014583333 | X5: =((R5*J5*E5)+U5)*AO$1*AP5 -> 0.61613334 | Y5: =X5*Z5 -> 0.61613334 | Z5: 1 | AA5: =Z5*N5 -> 0.87404429 | AB5: =AA5*P5 -> 0.33213683 | AC5: =(((R5*J5*E5)+U5)/60)*Z5*AP5 -> 0.030336452 | AD5: =AC5*60*AO$1 -> 0.61613334 | AF5: =IFERROR(VLOOKUP(AE5,'Chemical Cost'!A:D,4,0),0) -> 0 | AG5: =AF5*N5/3 -> 0 | AH5: =AF5*AA5/3 -> 0 | AI5: =IFERROR((Q5*Z5)+(Z5*X5)+AH5,0) -> 0.94827018 | AJ5: =IFERROR(VLOOKUP(A5,'All Products'!A:F,6,0),0) -> 6.19 | AK5: =AJ5*Z5*J5 -> 1.5475 | AL5: 1 | AN5: #N/A | AP5: 1.1 | AQ5: =(((R5*J5*E5)+U5)/60)*AP5 -> 0.030336452 | AR5: =_xlfn.XLOOKUP(F5,'RM Cost'!A:A,'RM Cost'!S:S) -> 0 | AS5: =_xlfn.XLOOKUP(A5,[3]Sheet1!$B:$B,[3]Sheet1!$B:$B) -> 1480CS | AT5: =_xlfn.XLOOKUP(H5,'Yield & Time'!A:A,'Yield & Time'!F:F) -> 0
A6: 1480CS | B6: Reynolds | C6: PREP ROOT VEG MIX CHNKY 2.5KG | D6: KG | E6: 2.5 | F6: =VLOOKUP(H6,'RM Used'!A:B,2,0) -> 3277CS | G6: =IFERROR(VLOOKUP(F6,'RM Cost'!A:B,2,0),"") -> RM - SWEDE 12.5KG | H6: Swede - Diced 25MM | I6: =VLOOKUP(F6,'RM Used'!B:D,3,0) -> RM-FOOD | J6: 0.25 | K6: =IF(I6="RM-FOOD",J6*E6,"") -> 0.625 | L6: =IFERROR(K6*Z6,0) -> 0.625 | M6: {=_xlfn.IFS(BOM!I6="RM-PACKING","100%",B6="Reynolds",VLOOKUP(H6,'Yield & Time'!A:V,22,0),BOM!B6="Dnata",VLOOKUP(BOM!H6,'Yield & Time'!A:M,13,0),B6="NK",VLOOKUP(H6,'Yield & Time'!A:X,24,0))} -> 0.82357724 | N6: =IFERROR(IF(I6="RM-FOOD",(E6*J6)/M6,1),0) -> 0.7588845 | O6: =VLOOKUP(H6,'RM Used'!A:E,5,0) -> KG | P6: =VLOOKUP(H6,'RM Used'!A:F,6,0) -> 0.52 | Q6: =P6*N6 -> 0.39461994 | R6: =IFERROR(IF(B6="Reynolds",VLOOKUP(H6,'Yield & Time'!A:U,21,0),VLOOKUP(H6,'Yield & Time'!A:L,12,0)),0) -> 1.9442895 | S6: =R6*J6*E6*AO$1 -> 0.41133874 | T6: =(R6*Z6*J6*E6)/60 -> 0.020253015 | U6: =IF(A5=A6,0,VLOOKUP(A6,'Packing Time'!A:F,6,0)) -> 0 | V6: =U6*AO$1 -> 0 | W6: =(U6*Z6)/60 -> 0 | X6: =((R6*J6*E6)+U6)*AO$1*AP6 -> 0.45247261 | Y6: =X6*Z6 -> 0.45247261 | Z6: 1 | AA6: =Z6*N6 -> 0.7588845 | AB6: =AA6*P6 -> 0.39461994 | AC6: =(((R6*J6*E6)+U6)/60)*Z6*AP6 -> 0.022278317 | AD6: =AC6*60*AO$1 -> 0.45247261 | AF6: =IFERROR(VLOOKUP(AE6,'Chemical Cost'!A:D,4,0),0) -> 0 | AG6: =AF6*N6/3 -> 0 | AH6: =AF6*AA6/3 -> 0 | AI6: =IFERROR((Q6*Z6)+(Z6*X6)+AH6,0) -> 0.84709255 | AJ6: =IFERROR(VLOOKUP(A6,'All Products'!A:F,6,0),0) -> 6.19 | AK6: =AJ6*Z6*J6 -> 1.5475 | AL6: 1 | AN6: #N/A | AP6: 1.1 | AQ6: =(((R6*J6*E6)+U6)/60)*AP6 -> 0.022278317 | AR6: =_xlfn.XLOOKUP(F6,'RM Cost'!A:A,'RM Cost'!S:S) -> 0 | AS6: =_xlfn.XLOOKUP(A6,[3]Sheet1!$B:$B,[3]Sheet1!$B:$B) -> 1480CS | AT6: =_xlfn.XLOOKUP(H6,'Yield & Time'!A:A,'Yield & Time'!F:F) -> 0
A7: 1480CS | B7: Reynolds | C7: PREP ROOT VEG MIX CHNKY 2.5KG | D7: KG | E7: 2.5 | F7: =VLOOKUP(H7,'RM Used'!A:B,2,0) -> 3342CS | G7: =IFERROR(VLOOKUP(F7,'RM Cost'!A:B,2,0),"") -> RM - ORI MOOLI X 15 EA | H7: Mooli - Diced 25mm | I7: =VLOOKUP(F7,'RM Used'!B:D,3,0) -> RM-FOOD | J7: 0.25 | K7: =IF(I7="RM-FOOD",J7*E7,"") -> 0.625 | L7: =IFERROR(K7*Z7,0) -> 0.625 | M7: {=_xlfn.IFS(BOM!I7="RM-PACKING","100%",B7="Reynolds",VLOOKUP(H7,'Yield & Time'!A:V,22,0),BOM!B7="Dnata",VLOOKUP(BOM!H7,'Yield & Time'!A:M,13,0),B7="NK",VLOOKUP(H7,'Yield & Time'!A:X,24,0))} -> 0.82 | N7: =IFERROR(IF(I7="RM-FOOD",(E7*J7)/M7,1),0) -> 0.76219512 | O7: =VLOOKUP(H7,'RM Used'!A:E,5,0) -> KG | P7: =VLOOKUP(H7,'RM Used'!A:F,6,0) -> 1.23 | Q7: =P7*N7 -> 0.9375 | R7: =IFERROR(IF(B7="Reynolds",VLOOKUP(H7,'Yield & Time'!A:U,21,0),VLOOKUP(H7,'Yield & Time'!A:L,12,0)),0) -> 1.351626 | S7: =R7*J7*E7*AO$1 -> 0.28595338 | T7: =(R7*Z7*J7*E7)/60 -> 0.014079438 | U7: =IF(A6=A7,0,VLOOKUP(A7,'Packing Time'!A:F,6,0)) -> 0 | V7: =U7*AO$1 -> 0 | W7: =(U7*Z7)/60 -> 0 | X7: =((R7*J7*E7)+U7)*AO$1*AP7 -> 0.31454872 | Y7: =X7*Z7 -> 0.31454872 | Z7: 1 | AA7: =Z7*N7 -> 0.76219512 | AB7: =AA7*P7 -> 0.9375 | AC7: =(((R7*J7*E7)+U7)/60)*Z7*AP7 -> 0.015487381 | AD7: =AC7*60*AO$1 -> 0.31454872 | AF7: =IFERROR(VLOOKUP(AE7,'Chemical Cost'!A:D,4,0),0) -> 0 | AG7: =AF7*N7/3 -> 0 | AH7: =AF7*AA7/3 -> 0 | AI7: =IFERROR((Q7*Z7)+(Z7*X7)+AH7,0) -> 1.2520487 | AJ7: =IFERROR(VLOOKUP(A7,'All Products'!A:F,6,0),0) -> 6.19 | AK7: =AJ7*Z7*J7 -> 1.5475 | AL7: 1 | AN7: #N/A | AP7: 1.1 | AQ7: =(((R7*J7*E7)+U7)/60)*AP7 -> 0.015487381 | AR7: =_xlfn.XLOOKUP(F7,'RM Cost'!A:A,'RM Cost'!S:S) -> 0 | AS7: =_xlfn.XLOOKUP(A7,[3]Sheet1!$B:$B,[3]Sheet1!$B:$B) -> 1480CS | AT7: =_xlfn.XLOOKUP(H7,'Yield & Time'!A:A,'Yield & Time'!F:F) -> 0
A8: 1480CS | B8: Reynolds | C8: PREP ROOT VEG MIX CHNKY 2.5KG | D8: KG | E8: 2.5 | F8: =VLOOKUP(H8,'RM Used'!A:B,2,0) -> 3191CS | G8: =IFERROR(VLOOKUP(F8,'RM Cost'!A:B,2,0),"") -> RM - PARSNIPS 10KG | H8: Parsnip - Diced 25mm MC | I8: =VLOOKUP(F8,'RM Used'!B:D,3,0) -> RM-FOOD | J8: 0.25 | K8: =IF(I8="RM-FOOD",J8*E8,"") -> 0.625 | L8: =IFERROR(K8*Z8,0) -> 0.625 | M8: {=_xlfn.IFS(BOM!I8="RM-PACKING","100%",B8="Reynolds",VLOOKUP(H8,'Yield & Time'!A:V,22,0),BOM!B8="Dnata",VLOOKUP(BOM!H8,'Yield & Time'!A:M,13,0),B8="NK",VLOOKUP(H8,'Yield & Time'!A:X,24,0))} -> 0.66601942 | N8: =IFERROR(IF(I8="RM-FOOD",(E8*J8)/M8,1),0) -> 0.93841108 | O8: =VLOOKUP(H8,'RM Used'!A:E,5,0) -> KG | P8: =VLOOKUP(H8,'RM Used'!A:F,6,0) -> 0.76 | Q8: =P8*N8 -> 0.71319242 | R8: =IFERROR(IF(B8="Reynolds",VLOOKUP(H8,'Yield & Time'!A:U,21,0),VLOOKUP(H8,'Yield & Time'!A:L,12,0)),0) -> 2.9061224 | S8: =R8*J8*E8*AO$1 -> 0.61482653 | T8: =(R8*Z8*J8*E8)/60 -> 0.030272109 | U8: =IF(A7=A8,0,VLOOKUP(A8,'Packing Time'!A:F,6,0)) -> 0 | V8: =U8*AO$1 -> 0 | W8: =(U8*Z8)/60 -> 0 | X8: =((R8*J8*E8)+U8)*AO$1*AP8 -> 0.67630918 | Y8: =X8*Z8 -> 0.67630918 | Z8: 1 | AA8: =Z8*N8 -> 0.93841108 | AB8: =AA8*P8 -> 0.71319242 | AC8: =(((R8*J8*E8)+U8)/60)*Z8*AP8 -> 0.03329932 | AD8: =AC8*60*AO$1 -> 0.67630918 | AE8: =VLOOKUP(H8,'Yield & Time'!A:R,18,0) -> SODIUM METABISULPHITE | AF8: =IFERROR(VLOOKUP(AE8,'Chemical Cost'!A:D,4,0),0) -> 0.0097586225 | AG8: =AF8*N8/3 -> 0.0030525332 | AH8: =AF8*AA8/3 -> 0.0030525332 | AI8: =IFERROR((Q8*Z8)+(Z8*X8)+AH8,0) -> 1.3925541 | AJ8: =IFERROR(VLOOKUP(A8,'All Products'!A:F,6,0),0) -> 6.19 | AK8: =AJ8*Z8*J8 -> 1.5475 | AL8: 1 | AN8: #N/A | AP8: 1.1 | AQ8: =(((R8*J8*E8)+U8)/60)*AP8 -> 0.03329932 | AR8: =_xlfn.XLOOKUP(F8,'RM Cost'!A:A,'RM Cost'!S:S) -> 0 | AS8: =_xlfn.XLOOKUP(A8,[3]Sheet1!$B:$B,[3]Sheet1!$B:$B) -> 1480CS | AT8: =_xlfn.XLOOKUP(H8,'Yield & Time'!A:A,'Yield & Time'!F:F) -> 0
A9: 1480CS | B9: Reynolds | C9: PREP ROOT VEG MIX CHNKY 2.5KG | D9: KG | E9: 2.5 | F9: =VLOOKUP(H9,'RM Used'!A:B,2,0) -> P0020 | G9: =IFERROR(VLOOKUP(F9,'RM Cost'!A:B,2,0),"") -> PALE BLUE BAG 430X430MM | H9: BLUE TINT BAGS ON A ROLL - SMALL | I9: =VLOOKUP(F9,'RM Used'!B:D,3,0) -> RM-PACKING | J9: 1 | K9: =IF(I9="RM-FOOD",J9*E9,"") | L9: =IFERROR(K9*Z9,0) -> 0 | M9: {=_xlfn.IFS(BOM!I9="RM-PACKING","100%",B9="Reynolds",VLOOKUP(H9,'Yield & Time'!A:V,22,0),BOM!B9="Dnata",VLOOKUP(BOM!H9,'Yield & Time'!A:M,13,0),B9="NK",VLOOKUP(H9,'Yield & Time'!A:X,24,0))} -> 100% | N9: =IFERROR(IF(I9="RM-FOOD",(E9*J9)/M9,1),0) -> 1 | O9: =VLOOKUP(H9,'RM Used'!A:E,5,0) -> Count | P9: =VLOOKUP(H9,'RM Used'!A:F,6,0) -> 0.09 | Q9: =P9*N9 -> 0.09 | R9: =IFERROR(IF(B9="Reynolds",VLOOKUP(H9,'Yield & Time'!A:U,21,0),VLOOKUP(H9,'Yield & Time'!A:L,12,0)),0) -> 0 | S9: =R9*J9*E9*AO$1 -> 0 | T9: =(R9*Z9*J9*E9)/60 -> 0 | U9: =IF(A8=A9,0,VLOOKUP(A9,'Packing Time'!A:F,6,0)) -> 0 | V9: =U9*AO$1 -> 0 | W9: =(U9*Z9)/60 -> 0 | X9: =((R9*J9*E9)+U9)*AO$1*AP9 -> 0 | Y9: =X9*Z9 -> 0 | Z9: 1 | AA9: =Z9*N9 -> 1 | AB9: =AA9*P9 -> 0.09 | AC9: =(((R9*J9*E9)+U9)/60)*Z9*AP9 -> 0 | AD9: =AC9*60*AO$1 -> 0 | AF9: =IFERROR(VLOOKUP(AE9,'Chemical Cost'!A:D,4,0),0) -> 0 | AG9: =AF9*N9/3 -> 0 | AH9: =AF9*AA9/3 -> 0 | AI9: =IFERROR((Q9*Z9)+(Z9*X9)+AH9,0) -> 0.09 | AJ9: =IFERROR(VLOOKUP(A9,'All Products'!A:F,6,0),0) -> 6.19 | AL9: 1 | AN9: #N/A | AP9: 1.1 | AQ9: =(((R9*J9*E9)+U9)/60)*AP9 -> 0 | AR9: =_xlfn.XLOOKUP(F9,'RM Cost'!A:A,'RM Cost'!S:S) -> 0 | AS9: =_xlfn.XLOOKUP(A9,[3]Sheet1!$B:$B,[3]Sheet1!$B:$B) -> 1480CS | AT9: =_xlfn.XLOOKUP(H9,'Yield & Time'!A:A,'Yield & Time'!F:F) -> #N/A
A10: 1480CS | B10: Reynolds | C10: PREP ROOT VEG MIX CHNKY 2.5KG | D10: KG | E10: 2.5 | F10: =VLOOKUP(H10,'RM Used'!A:B,2,0) -> P0016 | G10: =IFERROR(VLOOKUP(F10,'RM Cost'!A:B,2,0),"") -> REY 40 30 BOX | H10: black box | I10: =VLOOKUP(F10,'RM Used'!B:D,3,0) -> RM-PACKING | J10: 1 | K10: =IF(I10="RM-FOOD",J10*E10,"") | L10: =IFERROR(K10*Z10,0) -> 0 | M10: {=_xlfn.IFS(BOM!I10="RM-PACKING","100%",B10="Reynolds",VLOOKUP(H10,'Yield & Time'!A:V,22,0),BOM!B10="Dnata",VLOOKUP(BOM!H10,'Yield & Time'!A:M,13,0),B10="NK",VLOOKUP(H10,'Yield & Time'!A:X,24,0))} -> 100% | N10: =IFERROR(IF(I10="RM-FOOD",(E10*J10)/M10,1),0) -> 1 | O10: =VLOOKUP(H10,'RM Used'!A:E,5,0) -> Count | P10: =VLOOKUP(H10,'RM Used'!A:F,6,0) -> 0.28 | Q10: =P10*N10 -> 0.28 | R10: =IFERROR(IF(B10="Reynolds",VLOOKUP(H10,'Yield & Time'!A:U,21,0),VLOOKUP(H10,'Yield & Time'!A:L,12,0)),0) -> 0 | S10: =R10*J10*E10*AO$1 -> 0 | T10: =(R10*Z10*J10*E10)/60 -> 0 | U10: =IF(A9=A10,0,VLOOKUP(A10,'Packing Time'!A:F,6,0)) -> 0 | V10: =U10*AO$1 -> 0 | W10: =(U10*Z10)/60 -> 0 | X10: =((R10*J10*E10)+U10)*AO$1*AP10 -> 0 | Y10: =X10*Z10 -> 0 | Z10: 1 | AA10: =Z10*N10 -> 1 | AB10: =AA10*P10 -> 0.28 | AC10: =(((R10*J10*E10)+U10)/60)*Z10*AP10 -> 0 | AD10: =AC10*60*AO$1 -> 0 | AF10: =IFERROR(VLOOKUP(AE10,'Chemical Cost'!A:D,4,0),0) -> 0 | AG10: =AF10*N10/3 -> 0 | AH10: =AF10*AA10/3 -> 0 | AI10: =IFERROR((Q10*Z10)+(Z10*X10)+AH10,0) -> 0.28 | AJ10: =IFERROR(VLOOKUP(A10,'All Products'!A:F,6,0),0) -> 6.19 | AL10: 1 | AN10: #N/A | AP10: 1.1 | AQ10: =(((R10*J10*E10)+U10)/60)*AP10 -> 0 | AR10: =_xlfn.XLOOKUP(F10,'RM Cost'!A:A,'RM Cost'!S:S) -> 0 | AS10: =_xlfn.XLOOKUP(A10,[3]Sheet1!$B:$B,[3]Sheet1!$B:$B) -> 1480CS | AT10: =_xlfn.XLOOKUP(H10,'Yield & Time'!A:A,'Yield & Time'!F:F) -> #N/A
A11: 765ACS | B11: Reynolds | C11: COLESLAW MIX 8x500G | D11: KG | E11: 4 | F11: =VLOOKUP(H11,'RM Used'!A:B,2,0) -> 032ACS | G11: =IFERROR(VLOOKUP(F11,'RM Cost'!A:B,2,0),"") -> RM - LRG PROCESSING CARROT X 1000KG | H11: Carrot - Julienne | I11: =VLOOKUP(F11,'RM Used'!B:D,3,0) -> RM-FOOD | J11: 0.5 | K11: =IF(I11="RM-FOOD",J11*E11,"") -> 2 | L11: =IFERROR(K11*Z11,0) -> 2 | M11: {=_xlfn.IFS(BOM!I11="RM-PACKING","100%",B11="Reynolds",VLOOKUP(H11,'Yield & Time'!A:V,22,0),BOM!B11="Dnata",VLOOKUP(BOM!H11,'Yield & Time'!A:M,13,0),B11="NK",VLOOKUP(H11,'Yield & Time'!A:X,24,0))} -> 0.7533 | N11: =IFERROR(IF(I11="RM-FOOD",(E11*J11)/M11,1),0) -> 2.6549847 | O11: =VLOOKUP(H11,'RM Used'!A:E,5,0) -> KG | P11: =VLOOKUP(H11,'RM Used'!A:F,6,0) -> 0.38 | Q11: =P11*N11 -> 1.0088942 | R11: =IFERROR(IF(B11="Reynolds",VLOOKUP(H11,'Yield & Time'!A:U,21,0),VLOOKUP(H11,'Yield & Time'!A:L,12,0)),0) -> 0.90531915 | S11: =R11*J11*E11*AO$1 -> 0.61290106 | T11: =(R11*Z11*J11*E11)/60 -> 0.030177305 | U11: =IF(A10=A11,0,VLOOKUP(A11,'Packing Time'!A:F,6,0)) -> 2.3 | V11: =U11*AO$1 -> 0.77855 | W11: =(U11*Z11)/60 -> 0.038333333 | X11: =((R11*J11*E11)+U11)*AO$1*AP11 -> 1.5305962 | Y11: =X11*Z11 -> 1.5305962 | Z11: 1 | AA11: =Z11*N11 -> 2.6549847 | AB11: =AA11*P11 -> 1.0088942 | AC11: =(((R11*J11*E11)+U11)/60)*Z11*AP11 -> 0.075361702 | AD11: =AC11*60*AO$1 -> 1.5305962 | AE11: =VLOOKUP(H11,'Yield & Time'!A:R,18,0) -> CHLORINE | AF11: =IFERROR(VLOOKUP(AE11,'Chemical Cost'!A:D,4,0),0) -> 0.027756518 | AG11: =AF11*N11/3 -> 0.024564377 | AH11: =AF11*AA11/3 -> 0.024564377 | AI11: =IFERROR((Q11*Z11)+(Z11*X11)+AH11,0) -> 2.5640547 | AJ11: =IFERROR(VLOOKUP(A11,'All Products'!A:F,6,0),0) -> 10.32 | AK11: =AJ11*Z11*J11 -> 5.16 | AL11: 0.85 | AM11: 0.15 | AN11: #N/A | AP11: 1.1 | AQ11: =(((R11*J11*E11)+U11)/60)*AP11 -> 0.075361702 | AR11: =_xlfn.XLOOKUP(F11,'RM Cost'!A:A,'RM Cost'!S:S) -> 0 | AS11: =_xlfn.XLOOKUP(A11,[3]Sheet1!$B:$B,[3]Sheet1!$B:$B) -> 765ACS | AT11: =_xlfn.XLOOKUP(H11,'Yield & Time'!A:A,'Yield & Time'!O:O) -> Yes
A12: 765ACS | B12: Reynolds | C12: COLESLAW MIX 8x500G | D12: KG | E12: 4 | F12: =VLOOKUP(H12,'RM Used'!A:B,2,0) -> S3998CS | G12: =IFERROR(VLOOKUP(F12,'RM Cost'!A:B,2,0),"") -> RM - DECORED RED CABBAGE 1/3 1200KG | H12: CABB RED SHR 3MM M/C RTE | I12: =VLOOKUP(F12,'RM Used'!B:D,3,0) -> RM-FOOD | J12: 0.5 | K12: =IF(I12="RM-FOOD",J12*E12,"") -> 2 | L12: =IFERROR(K12*Z12,0) -> 2 | M12: {=_xlfn.IFS(BOM!I12="RM-PACKING","100%",B12="Reynolds",VLOOKUP(H12,'Yield & Time'!A:V,22,0),BOM!B12="Dnata",VLOOKUP(BOM!H12,'Yield & Time'!A:M,13,0),B12="NK",VLOOKUP(H12,'Yield & Time'!A:X,24,0))} -> 0.7513804 | N12: =IFERROR(IF(I12="RM-FOOD",(E12*J12)/M12,1),0) -> 2.6617676 | O12: =VLOOKUP(H12,'RM Used'!A:E,5,0) -> KG | P12: =VLOOKUP(H12,'RM Used'!A:F,6,0) -> 0.38 | Q12: =P12*N12 -> 1.0114717 | R12: =IFERROR(IF(B12="Reynolds",VLOOKUP(H12,'Yield & Time'!A:U,21,0),VLOOKUP(H12,'Yield & Time'!A:L,12,0)),0) -> 0.76261571 | S12: =R12*J12*E12*AO$1 -> 0.51629083 | T12: =(R12*Z12*J12*E12)/60 -> 0.025420524 | U12: =IF(A11=A12,0,VLOOKUP(A12,'Packing Time'!A:F,6,0)) -> 0 | V12: =U12*AO$1 -> 0 | W12: =(U12*Z12)/60 -> 0 | X12: =((R12*J12*E12)+U12)*AO$1*AP12 -> 0.56791992 | Y12: =X12*Z12 -> 0.56791992 | Z12: 1 | AA12: =Z12*N12 -> 2.6617676 | AB12: =AA12*P12 -> 1.0114717 | AC12: =(((R12*J12*E12)+U12)/60)*Z12*AP12 -> 0.027962576 | AD12: =AC12*60*AO$1 -> 0.56791992 | AE12: =VLOOKUP(H12,'Yield & Time'!A:R,18,0) -> CHLORINE | AF12: =IFERROR(VLOOKUP(AE12,'Chemical Cost'!A:D,4,0),0) -> 0.027756518 | AG12: =AF12*N12/3 -> 0.024627133 | AH12: =AF12*AA12/3 -> 0.024627133 | AI12: =IFERROR((Q12*Z12)+(Z12*X12)+AH12,0) -> 1.6040187 | AJ12: =IFERROR(VLOOKUP(A12,'All Products'!A:F,6,0),0) -> 10.32 | AK12: =AJ12*Z12*J12 -> 5.16 | AL12: 0.85 | AM12: 0.15 | AN12: #N/A | AP12: 1.1 | AQ12: =(((R12*J12*E12)+U12)/60)*AP12 -> 0.027962576 | AR12: =_xlfn.XLOOKUP(F12,'RM Cost'!A:A,'RM Cost'!S:S) -> 0.29914854 | AS12: =_xlfn.XLOOKUP(A12,[3]Sheet1!$B:$B,[3]Sheet1!$B:$B) -> 765ACS | AT12: =_xlfn.XLOOKUP(H12,'Yield & Time'!A:A,'Yield & Time'!O:O) -> Yes
A13: 765ACS | B13: Reynolds | C13: COLESLAW MIX 8x500G | D13: KG | E13: 4 | F13: =VLOOKUP(H13,'RM Used'!A:B,2,0) -> P0005 | G13: =IFERROR(VLOOKUP(F13,'RM Cost'!A:B,2,0),"") -> SOL 30EL # PPLUS 630x1000 BLUE -8 | H13: SOL 30EL # PPLUS 630x1000 BLUE -8 | I13: =VLOOKUP(F13,'RM Used'!B:D,3,0) -> RM-PACKING | J13: 1 | K13: =IF(I13="RM-FOOD",J13*E13,"") | L13: =IFERROR(K13*Z13,0) -> 0 | M13: {=_xlfn.IFS(BOM!I13="RM-PACKING","100%",B13="Reynolds",VLOOKUP(H13,'Yield & Time'!A:V,22,0),BOM!B13="Dnata",VLOOKUP(BOM!H13,'Yield & Time'!A:M,13,0),B13="NK",VLOOKUP(H13,'Yield & Time'!A:X,24,0))} -> 100% | N13: =IFERROR(IF(I13="RM-FOOD",(E13*J13)/M13,1),0) -> 1 | O13: =VLOOKUP(H13,'RM Used'!A:E,5,0) -> Count | P13: =VLOOKUP(H13,'RM Used'!A:F,6,0) -> 0.64 | Q13: =P13*N13 -> 0.64 | R13: =IFERROR(IF(B13="Reynolds",VLOOKUP(H13,'Yield & Time'!A:U,21,0),VLOOKUP(H13,'Yield & Time'!A:L,12,0)),0) -> 0 | S13: =R13*J13*E13*AO$1 -> 0 | T13: =(R13*Z13*J13*E13)/60 -> 0 | U13: =IF(A12=A13,0,VLOOKUP(A13,'Packing Time'!A:F,6,0)) -> 0 | V13: =U13*AO$1 -> 0 | W13: =(U13*Z13)/60 -> 0 | X13: =((R13*J13*E13)+U13)*AO$1*AP13 -> 0 | Y13: =X13*Z13 -> 0 | Z13: 1 | AA13: =Z13*N13 -> 1 | AB13: =AA13*P13 -> 0.64 | AC13: =(((R13*J13*E13)+U13)/60)*Z13*AP13 -> 0 | AD13: =AC13*60*AO$1 -> 0 | AF13: =IFERROR(VLOOKUP(AE13,'Chemical Cost'!A:D,4,0),0) -> 0 | AG13: =AF13*N13/3 -> 0 | AH13: =AF13*AA13/3 -> 0 | AI13: =IFERROR((Q13*Z13)+(Z13*X13)+AH13,0) -> 0.64 | AJ13: =IFERROR(VLOOKUP(A13,'All Products'!A:F,6,0),0) -> 10.32 | AL13: 0.85 | AM13: 0.15 | AN13: #N/A | AP13: 1.1 | AQ13: =(((R13*J13*E13)+U13)/60)*AP13 -> 0 | AR13: =_xlfn.XLOOKUP(F13,'RM Cost'!A:A,'RM Cost'!S:S) -> 0 | AS13: =_xlfn.XLOOKUP(A13,[3]Sheet1!$B:$B,[3]Sheet1!$B:$B) -> 765ACS | AT13: =_xlfn.XLOOKUP(H13,'Yield & Time'!A:A,'Yield & Time'!F:F) -> #N/A
A14: 765ACS | B14: Reynolds | C14: COLESLAW MIX 8x500G | D14: KG | E14: 4 | F14: =VLOOKUP(H14,'RM Used'!A:B,2,0) -> P0016 | G14: =IFERROR(VLOOKUP(F14,'RM Cost'!A:B,2,0),"") -> REY 40 30 BOX | H14: black box | I14: =VLOOKUP(F14,'RM Used'!B:D,3,0) -> RM-PACKING | J14: 1 | K14: =IF(I14="RM-FOOD",J14*E14,"") | L14: =IFERROR(K14*Z14,0) -> 0 | M14: {=_xlfn.IFS(BOM!I14="RM-PACKING","100%",B14="Reynolds",VLOOKUP(H14,'Yield & Time'!A:V,22,0),BOM!B14="Dnata",VLOOKUP(BOM!H14,'Yield & Time'!A:M,13,0),B14="NK",VLOOKUP(H14,'Yield & Time'!A:X,24,0))} -> 100% | N14: =IFERROR(IF(I14="RM-FOOD",(E14*J14)/M14,1),0) -> 1 | O14: =VLOOKUP(H14,'RM Used'!A:E,5,0) -> Count | P14: =VLOOKUP(H14,'RM Used'!A:F,6,0) -> 0.28 | Q14: =P14*N14 -> 0.28 | R14: =IFERROR(IF(B14="Reynolds",VLOOKUP(H14,'Yield & Time'!A:U,21,0),VLOOKUP(H14,'Yield & Time'!A:L,12,0)),0) -> 0 | S14: =R14*J14*E14*AO$1 -> 0 | T14: =(R14*Z14*J14*E14)/60 -> 0 | U14: =IF(A13=A14,0,VLOOKUP(A14,'Packing Time'!A:F,6,0)) -> 0 | V14: =U14*AO$1 -> 0 | W14: =(U14*Z14)/60 -> 0 | X14: =((R14*J14*E14)+U14)*AO$1*AP14 -> 0 | Y14: =X14*Z14 -> 0 | Z14: 1 | AA14: =Z14*N14 -> 1 | AB14: =AA14*P14 -> 0.28 | AC14: =(((R14*J14*E14)+U14)/60)*Z14*AP14 -> 0 | AD14: =AC14*60*AO$1 -> 0 | AF14: =IFERROR(VLOOKUP(AE14,'Chemical Cost'!A:D,4,0),0) -> 0 | AG14: =AF14*N14/3 -> 0 | AH14: =AF14*AA14/3 -> 0 | AI14: =IFERROR((Q14*Z14)+(Z14*X14)+AH14,0) -> 0.28 | AJ14: =IFERROR(VLOOKUP(A14,'All Products'!A:F,6,0),0) -> 10.32 | AL14: 0.85 | AM14: 0.15 | AN14: #N/A | AP14: 1.1 | AQ14: =(((R14*J14*E14)+U14)/60)*AP14 -> 0 | AR14: =_xlfn.XLOOKUP(F14,'RM Cost'!A:A,'RM Cost'!S:S) -> 0 | AS14: =_xlfn.XLOOKUP(A14,[3]Sheet1!$B:$B,[3]Sheet1!$B:$B) -> 765ACS | AT14: =_xlfn.XLOOKUP(H14,'Yield & Time'!A:A,'Yield & Time'!F:F) -> #N/A
A15: 1254CS | B15: Reynolds | C15: COLESLAW DRY MIX 1KG | D15: KG | E15: 1 | F15: =VLOOKUP(H15,'RM Used'!A:B,2,0) -> S3997CS | G15: =IFERROR(VLOOKUP(F15,'RM Cost'!A:B,2,0),"") -> RM - DECORE WHITE CABBAGE 1/3 1200KG | H15: Cabbage White - Sliced | I15: =VLOOKUP(F15,'RM Used'!B:D,3,0) -> RM-FOOD | J15: 0.7 | K15: =IF(I15="RM-FOOD",J15*E15,"") -> 0.7 | L15: =IFERROR(K15*Z15,0) -> 0.7 | M15: {=_xlfn.IFS(BOM!I15="RM-PACKING","100%",B15="Reynolds",VLOOKUP(H15,'Yield & Time'!A:V,22,0),BOM!B15="Dnata",VLOOKUP(BOM!H15,'Yield & Time'!A:M,13,0),B15="NK",VLOOKUP(H15,'Yield & Time'!A:X,24,0))} -> 0.77222322 | N15: =IFERROR(IF(I15="RM-FOOD",(E15*J15)/M15,1),0) -> 0.90647365 | O15: =VLOOKUP(H15,'RM Used'!A:E,5,0) -> KG | P15: =VLOOKUP(H15,'RM Used'!A:F,6,0) -> 0.34 | Q15: =P15*N15 -> 0.30820104 | R15: =IFERROR(IF(B15="Reynolds",VLOOKUP(H15,'Yield & Time'!A:U,21,0),VLOOKUP(H15,'Yield & Time'!A:L,12,0)),0) -> 0.82773481 | S15: =R15*J15*E15*AO$1 -> 0.19613176 | T15: =(R15*Z15*J15*E15)/60 -> 0.0096569061 | U15: =IF(A14=A15,0,VLOOKUP(A15,'Packing Time'!A:F,6,0)) -> 0.55 | V15: =U15*AO$1 -> 0.186175 | W15: =(U15*Z15)/60 -> 0.0091666667 | X15: =((R15*J15*E15)+U15)*AO$1*AP15 -> 0.42053744 | Y15: =X15*Z15 -> 0.42053744 | Z15: 1 | AA15: =Z15*N15 -> 0.90647365 | AB15: =AA15*P15 -> 0.30820104 | AC15: =(((R15*J15*E15)+U15)/60)*Z15*AP15 -> 0.02070593 | AD15: =AC15*60*AO$1 -> 0.42053744 | AE15: =VLOOKUP(H15,'Yield & Time'!A:R,18,0) -> CHLORINE | AF15: =IFERROR(VLOOKUP(AE15,'Chemical Cost'!A:D,4,0),0) -> 0.027756518 | AG15: =AF15*N15/3 -> 0.0083868507 | AH15: =AF15*AA15/3 -> 0.0083868507 | AI15: =IFERROR((Q15*Z15)+(Z15*X15)+AH15,0) -> 0.73712533 | AJ15: =IFERROR(VLOOKUP(A15,'All Products'!A:F,6,0),0) -> 1.91 | AK15: =AJ15*Z15*J15 -> 1.337 | AL15: 0.8 | AM15: 0.2 | AN15: #N/A | AP15: 1.1 | AQ15: =(((R15*J15*E15)+U15)/60)*AP15 -> 0.02070593 | AR15: =_xlfn.XLOOKUP(F15,'RM Cost'!A:A,'RM Cost'!S:S) -> 0.29914854 | AS15: =_xlfn.XLOOKUP(A15,[3]Sheet1!$B:$B,[3]Sheet1!$B:$B) -> 1254CS | AT15: =_xlfn.XLOOKUP(H15,'Yield & Time'!A:A,'Yield & Time'!O:O) -> Yes
A16: 1254CS | B16: Reynolds | C16: COLESLAW DRY MIX 1KG | D16: KG | E16: 1 | F16: =VLOOKUP(H16,'RM Used'!A:B,2,0) -> 032ACS | G16: =IFERROR(VLOOKUP(F16,'RM Cost'!A:B,2,0),"") -> RM - LRG PROCESSING CARROT X 1000KG | H16: Carrot - Julienne | I16: =VLOOKUP(F16,'RM Used'!B:D,3,0) -> RM-FOOD | J16: 0.3 | K16: =IF(I16="RM-FOOD",J16*E16,"") -> 0.3 | L16: =IFERROR(K16*Z16,0) -> 0.3 | M16: {=_xlfn.IFS(BOM!I16="RM-PACKING","100%",B16="Reynolds",VLOOKUP(H16,'Yield & Time'!A:V,22,0),BOM!B16="Dnata",VLOOKUP(BOM!H16,'Yield & Time'!A:M,13,0),B16="NK",VLOOKUP(H16,'Yield & Time'!A:X,24,0))} -> 0.7533 | N16: =IFERROR(IF(I16="RM-FOOD",(E16*J16)/M16,1),0) -> 0.39824771 | O16: =VLOOKUP(H16,'RM Used'!A:E,5,0) -> KG | P16: =VLOOKUP(H16,'RM Used'!A:F,6,0) -> 0.38 | Q16: =P16*N16 -> 0.15133413 | R16: =IFERROR(IF(B16="Reynolds",VLOOKUP(H16,'Yield & Time'!A:U,21,0),VLOOKUP(H16,'Yield & Time'!A:L,12,0)),0) -> 0.90531915 | S16: =R16*J16*E16*AO$1 -> 0.09193516 | T16: =(R16*Z16*J16*E16)/60 -> 0.0045265957 | U16: =IF(A15=A16,0,VLOOKUP(A16,'Packing Time'!A:F,6,0)) -> 0 | V16: =U16*AO$1 -> 0 | W16: =(U16*Z16)/60 -> 0 | X16: =((R16*J16*E16)+U16)*AO$1*AP16 -> 0.10112868 | Y16: =X16*Z16 -> 0.10112868 | Z16: 1 | AA16: =Z16*N16 -> 0.39824771 | AB16: =AA16*P16 -> 0.15133413 | AC16: =(((R16*J16*E16)+U16)/60)*Z16*AP16 -> 0.0049792553 | AD16: =AC16*60*AO$1 -> 0.10112868 | AE16: =VLOOKUP(H16,'Yield & Time'!A:R,18,0) -> CHLORINE | AF16: =IFERROR(VLOOKUP(AE16,'Chemical Cost'!A:D,4,0),0) -> 0.027756518 | AG16: =AF16*N16/3 -> 0.0036846566 | AH16: =AF16*AA16/3 -> 0.0036846566 | AI16: =IFERROR((Q16*Z16)+(Z16*X16)+AH16,0) -> 0.25614746 | AJ16: =IFERROR(VLOOKUP(A16,'All Products'!A:F,6,0),0) -> 1.91 | AK16: =AJ16*Z16*J16 -> 0.573 | AL16: 0.8 | AM16: 0.2 | AN16: #N/A | AP16: 1.1 | AQ16: =(((R16*J16*E16)+U16)/60)*AP16 -> 0.0049792553 | AR16: =_xlfn.XLOOKUP(F16,'RM Cost'!A:A,'RM Cost'!S:S) -> 0 | AS16: =_xlfn.XLOOKUP(A16,[3]Sheet1!$B:$B,[3]Sheet1!$B:$B) -> 1254CS | AT16: =_xlfn.XLOOKUP(H16,'Yield & Time'!A:A,'Yield & Time'!O:O) -> Yes
A17: 1254CS | B17: Reynolds | C17: COLESLAW DRY MIX 1KG | D17: KG | E17: 1 | F17: =VLOOKUP(H17,'RM Used'!A:B,2,0) -> P0001 | G17: =IFERROR(VLOOKUP(F17,'RM Cost'!A:B,2,0),"") -> SOL 30EL # PPLUS 630x1000 BLUE -1 | H17: SOL 30EL # PPLUS 630x1000 BLUE -1 | I17: =VLOOKUP(F17,'RM Used'!B:D,3,0) -> RM-PACKING | J17: 1 | K17: =IF(I17="RM-FOOD",J17*E17,"") | L17: =IFERROR(K17*Z17,0) -> 0 | M17: {=_xlfn.IFS(BOM!I17="RM-PACKING","100%",B17="Reynolds",VLOOKUP(H17,'Yield & Time'!A:V,22,0),BOM!B17="Dnata",VLOOKUP(BOM!H17,'Yield & Time'!A:M,13,0),B17="NK",VLOOKUP(H17,'Yield & Time'!A:X,24,0))} -> 100% | N17: =IFERROR(IF(I17="RM-FOOD",(E17*J17)/M17,1),0) -> 1 | O17: =VLOOKUP(H17,'RM Used'!A:E,5,0) -> Count | P17: =VLOOKUP(H17,'RM Used'!A:F,6,0) -> 0.08 | Q17: =P17*N17 -> 0.08 | R17: =IFERROR(IF(B17="Reynolds",VLOOKUP(H17,'Yield & Time'!A:U,21,0),VLOOKUP(H17,'Yield & Time'!A:L,12,0)),0) -> 0 | S17: =R17*J17*E17*AO$1 -> 0 | T17: =(R17*Z17*J17*E17)/60 -> 0 | U17: =IF(A16=A17,0,VLOOKUP(A17,'Packing Time'!A:F,6,0)) -> 0 | V17: =U17*AO$1 -> 0 | W17: =(U17*Z17)/60 -> 0 | X17: =((R17*J17*E17)+U17)*AO$1*AP17 -> 0 | Y17: =X17*Z17 -> 0 | Z17: 1 | AA17: =Z17*N17 -> 1 | AB17: =AA17*P17 -> 0.08 | AC17: =(((R17*J17*E17)+U17)/60)*Z17*AP17 -> 0 | AD17: =AC17*60*AO$1 -> 0 | AF17: =IFERROR(VLOOKUP(AE17,'Chemical Cost'!A:D,4,0),0) -> 0 | AG17: =AF17*N17/3 -> 0 | AH17: =AF17*AA17/3 -> 0 | AI17: =IFERROR((Q17*Z17)+(Z17*X17)+AH17,0) -> 0.08 | AJ17: =IFERROR(VLOOKUP(A17,'All Products'!A:F,6,0),0) -> 1.91 | AL17: 0.8 | AM17: 0.2 | AN17: #N/A | AP17: 1.1 | AQ17: =(((R17*J17*E17)+U17)/60)*AP17 -> 0 | AR17: =_xlfn.XLOOKUP(F17,'RM Cost'!A:A,'RM Cost'!S:S) -> 0 | AS17: =_xlfn.XLOOKUP(A17,[3]Sheet1!$B:$B,[3]Sheet1!$B:$B) -> 1254CS | AT17: =_xlfn.XLOOKUP(H17,'Yield & Time'!A:A,'Yield & Time'!F:F) -> #N/A
A18: 1254CS | B18: Reynolds | C18: COLESLAW DRY MIX 1KG | D18: KG | E18: 1 | F18: =VLOOKUP(H18,'RM Used'!A:B,2,0) -> P0016 | G18: =IFERROR(VLOOKUP(F18,'RM Cost'!A:B,2,0),"") -> REY 40 30 BOX | H18: black box | I18: =VLOOKUP(F18,'RM Used'!B:D,3,0) -> RM-PACKING | J18: 1 | K18: =IF(I18="RM-FOOD",J18*E18,"") | L18: =IFERROR(K18*Z18,0) -> 0 | M18: {=_xlfn.IFS(BOM!I18="RM-PACKING","100%",B18="Reynolds",VLOOKUP(H18,'Yield & Time'!A:V,22,0),BOM!B18="Dnata",VLOOKUP(BOM!H18,'Yield & Time'!A:M,13,0),B18="NK",VLOOKUP(H18,'Yield & Time'!A:X,24,0))} -> 100% | N18: =IFERROR(IF(I18="RM-FOOD",(E18*J18)/M18,1),0) -> 1 | O18: =VLOOKUP(H18,'RM Used'!A:E,5,0) -> Count | P18: =VLOOKUP(H18,'RM Used'!A:F,6,0) -> 0.28 | Q18: =P18*N18 -> 0.28 | R18: =IFERROR(IF(B18="Reynolds",VLOOKUP(H18,'Yield & Time'!A:U,21,0),VLOOKUP(H18,'Yield & Time'!A:L,12,0)),0) -> 0 | S18: =R18*J18*E18*AO$1 -> 0 | T18: =(R18*Z18*J18*E18)/60 -> 0 | U18: =IF(A17=A18,0,VLOOKUP(A18,'Packing Time'!A:F,6,0)) -> 0 | V18: =U18*AO$1 -> 0 | W18: =(U18*Z18)/60 -> 0 | X18: =((R18*J18*E18)+U18)*AO$1*AP18 -> 0 | Y18: =X18*Z18 -> 0 | Z18: 1 | AA18: =Z18*N18 -> 1 | AB18: =AA18*P18 -> 0.28 | AC18: =(((R18*J18*E18)+U18)/60)*Z18*AP18 -> 0 | AD18: =AC18*60*AO$1 -> 0 | AF18: =IFERROR(VLOOKUP(AE18,'Chemical Cost'!A:D,4,0),0) -> 0 | AG18: =AF18*N18/3 -> 0 | AH18: =AF18*AA18/3 -> 0 | AI18: =IFERROR((Q18*Z18)+(Z18*X18)+AH18,0) -> 0.28 | AJ18: =IFERROR(VLOOKUP(A18,'All Products'!A:F,6,0),0) -> 1.91 | AL18: 0.8 | AM18: 0.2 | AN18: #N/A | AP18: 1.1 | AQ18: =(((R18*J18*E18)+U18)/60)*AP18 -> 0 | AR18: =_xlfn.XLOOKUP(F18,'RM Cost'!A:A,'RM Cost'!S:S) -> 0 | AS18: =_xlfn.XLOOKUP(A18,[3]Sheet1!$B:$B,[3]Sheet1!$B:$B) -> 1254CS | AT18: =_xlfn.XLOOKUP(H18,'Yield & Time'!A:A,'Yield & Time'!F:F) -> #N/A
A19: 1255CS | B19: Reynolds | C19: PREP COLESLAW DRY MIX 2.5KG | D19: KG | E19: 2.5 | F19: =VLOOKUP(H19,'RM Used'!A:B,2,0) -> S3997CS | G19: =IFERROR(VLOOKUP(F19,'RM Cost'!A:B,2,0),"") -> RM - DECORE WHITE CABBAGE 1/3 1200KG | H19: Cabbage White - Sliced | I19: =VLOOKUP(F19,'RM Used'!B:D,3,0) -> RM-FOOD | J19: 0.7 | K19: =IF(I19="RM-FOOD",J19*E19,"") -> 1.75 | L19: =IFERROR(K19*Z19,0) -> 1.75 | M19: {=_xlfn.IFS(BOM!I19="RM-PACKING","100%",B19="Reynolds",VLOOKUP(H19,'Yield & Time'!A:V,22,0),BOM!B19="Dnata",VLOOKUP(BOM!H19,'Yield & Time'!A:M,13,0),B19="NK",VLOOKUP(H19,'Yield & Time'!A:X,24,0))} -> 0.77222322 | N19: =IFERROR(IF(I19="RM-FOOD",(E19*J19)/M19,1),0) -> 2.2661841 | O19: =VLOOKUP(H19,'RM Used'!A:E,5,0) -> KG | P19: =VLOOKUP(H19,'RM Used'!A:F,6,0) -> 0.34 | Q19: =P19*N19 -> 0.7705026 | R19: =IFERROR(IF(B19="Reynolds",VLOOKUP(H19,'Yield & Time'!A:U,21,0),VLOOKUP(H19,'Yield & Time'!A:L,12,0)),0) -> 0.82773481 | S19: =R19*J19*E19*AO$1 -> 0.49032941 | T19: =(R19*Z19*J19*E19)/60 -> 0.024142265 | U19: =IF(A18=A19,0,VLOOKUP(A19,'Packing Time'!A:F,6,0)) -> 0.875 | V19: =U19*AO$1 -> 0.2961875 | W19: =(U19*Z19)/60 -> 0.014583333 | X19: =((R19*J19*E19)+U19)*AO$1*AP19 -> 0.8651686 | Y19: =X19*Z19 -> 0.8651686 | Z19: 1 | AA19: =Z19*N19 -> 2.2661841 | AB19: =AA19*P19 -> 0.7705026 | AC19: =(((R19*J19*E19)+U19)/60)*Z19*AP19 -> 0.042598158 | AD19: =AC19*60*AO$1 -> 0.8651686 | AE19: =VLOOKUP(H19,'Yield & Time'!A:R,18,0) -> CHLORINE | AF19: =IFERROR(VLOOKUP(AE19,'Chemical Cost'!A:D,4,0),0) -> 0.027756518 | AG19: =AF19*N19/3 -> 0.020967127 | AH19: =AF19*AA19/3 -> 0.020967127 | AI19: =IFERROR((Q19*Z19)+(Z19*X19)+AH19,0) -> 1.6566383 | AJ19: =IFERROR(VLOOKUP(A19,'All Products'!A:F,6,0),0) -> 3.29 | AK19: =AJ19*Z19*J19 -> 2.303 | AL19: 0.8 | AM19: 0.2 | AN19: #N/A | AP19: 1.1 | AQ19: =(((R19*J19*E19)+U19)/60)*AP19 -> 0.042598158 | AR19: =_xlfn.XLOOKUP(F19,'RM Cost'!A:A,'RM Cost'!S:S) -> 0.29914854 | AS19: =_xlfn.XLOOKUP(A19,[3]Sheet1!$B:$B,[3]Sheet1!$B:$B) -> 1255CS | AT19: =_xlfn.XLOOKUP(H19,'Yield & Time'!A:A,'Yield & Time'!O:O) -> Yes
A20: 1255CS | B20: Reynolds | C20: PREP COLESLAW DRY MIX 2.5KG | D20: KG | E20: 2.5 | F20: =VLOOKUP(H20,'RM Used'!A:B,2,0) -> 032ACS | G20: =IFERROR(VLOOKUP(F20,'RM Cost'!A:B,2,0),"") -> RM - LRG PROCESSING CARROT X 1000KG | H20: Carrot - Julienne | I20: =VLOOKUP(F20,'RM Used'!B:D,3,0) -> RM-FOOD | J20: 0.3 | K20: =IF(I20="RM-FOOD",J20*E20,"") -> 0.75 | L20: =IFERROR(K20*Z20,0) -> 0.75 | M20: {=_xlfn.IFS(BOM!I20="RM-PACKING","100%",B20="Reynolds",VLOOKUP(H20,'Yield & Time'!A:V,22,0),BOM!B20="Dnata",VLOOKUP(BOM!H20,'Yield & Time'!A:M,13,0),B20="NK",VLOOKUP(H20,'Yield & Time'!A:X,24,0))} -> 0.7533 | N20: =IFERROR(IF(I20="RM-FOOD",(E20*J20)/M20,1),0) -> 0.99561928 | O20: =VLOOKUP(H20,'RM Used'!A:E,5,0) -> KG | P20: =VLOOKUP(H20,'RM Used'!A:F,6,0) -> 0.38 | Q20: =P20*N20 -> 0.37833532 | R20: =IFERROR(IF(B20="Reynolds",VLOOKUP(H20,'Yield & Time'!A:U,21,0),VLOOKUP(H20,'Yield & Time'!A:L,12,0)),0) -> 0.90531915 | S20: =R20*J20*E20*AO$1 -> 0.2298379 | T20: =(R20*Z20*J20*E20)/60 -> 0.011316489 | U20: =IF(A19=A20,0,VLOOKUP(A20,'Packing Time'!A:F,6,0)) -> 0 | V20: =U20*AO$1 -> 0 | W20: =(U20*Z20)/60 -> 0 | X20: =((R20*J20*E20)+U20)*AO$1*AP20 -> 0.25282169 | Y20: =X20*Z20 -> 0.25282169 | Z20: 1 | AA20: =Z20*N20 -> 0.99561928 | AB20: =AA20*P20 -> 0.37833532 | AC20: =(((R20*J20*E20)+U20)/60)*Z20*AP20 -> 0.012448138 | AD20: =AC20*60*AO$1 -> 0.25282169 | AE20: =VLOOKUP(H20,'Yield & Time'!A:R,18,0) -> CHLORINE | AF20: =IFERROR(VLOOKUP(AE20,'Chemical Cost'!A:D,4,0),0) -> 0.027756518 | AG20: =AF20*N20/3 -> 0.0092116415 | AH20: =AF20*AA20/3 -> 0.0092116415 | AI20: =IFERROR((Q20*Z20)+(Z20*X20)+AH20,0) -> 0.64036865 | AJ20: =IFERROR(VLOOKUP(A20,'All Products'!A:F,6,0),0) -> 3.29 | AK20: =AJ20*Z20*J20 -> 0.987 | AL20: 0.8 | AM20: 0.2 | AN20: #N/A | AP20: 1.1 | AQ20: =(((R20*J20*E20)+U20)/60)*AP20 -> 0.012448138 | AR20: =_xlfn.XLOOKUP(F20,'RM Cost'!A:A,'RM Cost'!S:S) -> 0 | AS20: =_xlfn.XLOOKUP(A20,[3]Sheet1!$B:$B,[3]Sheet1!$B:$B) -> 1255CS | AT20: =_xlfn.XLOOKUP(H20,'Yield & Time'!A:A,'Yield & Time'!O:O) -> Yes
A21: 1255CS | B21: Reynolds | C21: PREP COLESLAW DRY MIX 2.5KG | D21: KG | E21: 2.5 | F21: =VLOOKUP(H21,'RM Used'!A:B,2,0) -> P0001 | G21: =IFERROR(VLOOKUP(F21,'RM Cost'!A:B,2,0),"") -> SOL 30EL # PPLUS 630x1000 BLUE -1 | H21: SOL 30EL # PPLUS 630x1000 BLUE -1 | I21: =VLOOKUP(F21,'RM Used'!B:D,3,0) -> RM-PACKING | J21: 1 | K21: =IF(I21="RM-FOOD",J21*E21,"") | L21: =IFERROR(K21*Z21,0) -> 0 | M21: {=_xlfn.IFS(BOM!I21="RM-PACKING","100%",B21="Reynolds",VLOOKUP(H21,'Yield & Time'!A:V,22,0),BOM!B21="Dnata",VLOOKUP(BOM!H21,'Yield & Time'!A:M,13,0),B21="NK",VLOOKUP(H21,'Yield & Time'!A:X,24,0))} -> 100% | N21: =IFERROR(IF(I21="RM-FOOD",(E21*J21)/M21,1),0) -> 1 | O21: =VLOOKUP(H21,'RM Used'!A:E,5,0) -> Count | P21: =VLOOKUP(H21,'RM Used'!A:F,6,0) -> 0.08 | Q21: =P21*N21 -> 0.08 | R21: =IFERROR(IF(B21="Reynolds",VLOOKUP(H21,'Yield & Time'!A:U,21,0),VLOOKUP(H21,'Yield & Time'!A:L,12,0)),0) -> 0 | S21: =R21*J21*E21*AO$1 -> 0 | T21: =(R21*Z21*J21*E21)/60 -> 0 | U21: =IF(A20=A21,0,VLOOKUP(A21,'Packing Time'!A:F,6,0)) -> 0 | V21: =U21*AO$1 -> 0 | W21: =(U21*Z21)/60 -> 0 | X21: =((R21*J21*E21)+U21)*AO$1*AP21 -> 0 | Y21: =X21*Z21 -> 0 | Z21: 1 | AA21: =Z21*N21 -> 1 | AB21: =AA21*P21 -> 0.08 | AC21: =(((R21*J21*E21)+U21)/60)*Z21*AP21 -> 0 | AD21: =AC21*60*AO$1 -> 0 | AF21: =IFERROR(VLOOKUP(AE21,'Chemical Cost'!A:D,4,0),0) -> 0 | AG21: =AF21*N21/3 -> 0 | AH21: =AF21*AA21/3 -> 0 | AI21: =IFERROR((Q21*Z21)+(Z21*X21)+AH21,0) -> 0.08 | AJ21: =IFERROR(VLOOKUP(A21,'All Products'!A:F,6,0),0) -> 3.29 | AL21: 0.8 | AM21: 0.2 | AN21: #N/A | AP21: 1.1 | AQ21: =(((R21*J21*E21)+U21)/60)*AP21 -> 0 | AR21: =_xlfn.XLOOKUP(F21,'RM Cost'!A:A,'RM Cost'!S:S) -> 0 | AS21: =_xlfn.XLOOKUP(A21,[3]Sheet1!$B:$B,[3]Sheet1!$B:$B) -> 1255CS | AT21: =_xlfn.XLOOKUP(H21,'Yield & Time'!A:A,'Yield & Time'!F:F) -> #N/A
A22: 1255CS | B22: Reynolds | C22: PREP COLESLAW DRY MIX 2.5KG | D22: KG | E22: 2.5 | F22: =VLOOKUP(H22,'RM Used'!A:B,2,0) -> P0016 | G22: =IFERROR(VLOOKUP(F22,'RM Cost'!A:B,2,0),"") -> REY 40 30 BOX | H22: black box | I22: =VLOOKUP(F22,'RM Used'!B:D,3,0) -> RM-PACKING | J22: 1 | K22: =IF(I22="RM-FOOD",J22*E22,"") | L22: =IFERROR(K22*Z22,0) -> 0 | M22: {=_xlfn.IFS(BOM!I22="RM-PACKING","100%",B22="Reynolds",VLOOKUP(H22,'Yield & Time'!A:V,22,0),BOM!B22="Dnata",VLOOKUP(BOM!H22,'Yield & Time'!A:M,13,0),B22="NK",VLOOKUP(H22,'Yield & Time'!A:X,24,0))} -> 100% | N22: =IFERROR(IF(I22="RM-FOOD",(E22*J22)/M22,1),0) -> 1 | O22: =VLOOKUP(H22,'RM Used'!A:E,5,0) -> Count | P22: =VLOOKUP(H22,'RM Used'!A:F,6,0) -> 0.28 | Q22: =P22*N22 -> 0.28 | R22: =IFERROR(IF(B22="Reynolds",VLOOKUP(H22,'Yield & Time'!A:U,21,0),VLOOKUP(H22,'Yield & Time'!A:L,12,0)),0) -> 0 | S22: =R22*J22*E22*AO$1 -> 0 | T22: =(R22*Z22*J22*E22)/60 -> 0 | U22: =IF(A21=A22,0,VLOOKUP(A22,'Packing Time'!A:F,6,0)) -> 0 | V22: =U22*AO$1 -> 0 | W22: =(U22*Z22)/60 -> 0 | X22: =((R22*J22*E22)+U22)*AO$1*AP22 -> 0 | Y22: =X22*Z22 -> 0 | Z22: 1 | AA22: =Z22*N22 -> 1 | AB22: =AA22*P22 -> 0.28 | AC22: =(((R22*J22*E22)+U22)/60)*Z22*AP22 -> 0 | AD22: =AC22*60*AO$1 -> 0 | AF22: =IFERROR(VLOOKUP(AE22,'Chemical Cost'!A:D,4,0),0) -> 0 | AG22: =AF22*N22/3 -> 0 | AH22: =AF22*AA22/3 -> 0 | AI22: =IFERROR((Q22*Z22)+(Z22*X22)+AH22,0) -> 0.28 | AJ22: =IFERROR(VLOOKUP(A22,'All Products'!A:F,6,0),0) -> 3.29 | AL22: 0.8 | AM22: 0.2 | AN22: #N/A | AP22: 1.1 | AQ22: =(((R22*J22*E22)+U22)/60)*AP22 -> 0 | AR22: =_xlfn.XLOOKUP(F22,'RM Cost'!A:A,'RM Cost'!S:S) -> 0 | AS22: =_xlfn.XLOOKUP(A22,[3]Sheet1!$B:$B,[3]Sheet1!$B:$B) -> 1255CS | AT22: =_xlfn.XLOOKUP(H22,'Yield & Time'!A:A,'Yield & Time'!F:F) -> #N/A
A23: 1522CS | B23: Reynolds | C23: STIRFRY MIX WITH KALE 6 X 500G | D23: KG | E23: 3 | F23: =VLOOKUP(H23,'RM Used'!A:B,2,0) -> S3997CS | G23: =IFERROR(VLOOKUP(F23,'RM Cost'!A:B,2,0),"") -> RM - DECORE WHITE CABBAGE 1/3 1200KG | H23: Cabbage White - Shredded | I23: =VLOOKUP(F23,'RM Used'!B:D,3,0) -> RM-FOOD | J23: 0.37 | K23: =IF(I23="RM-FOOD",J23*E23,"") -> 1.11 | L23: =IFERROR(K23*Z23,0) -> 1.11 | M23: {=_xlfn.IFS(BOM!I23="RM-PACKING","100%",B23="Reynolds",VLOOKUP(H23,'Yield & Time'!A:V,22,0),BOM!B23="Dnata",VLOOKUP(BOM!H23,'Yield & Time'!A:M,13,0),B23="NK",VLOOKUP(H23,'Yield & Time'!A:X,24,0))} -> 0.7434525 | N23: =IFERROR(IF(I23="RM-FOOD",(E23*J23)/M23,1),0) -> 1.4930342 | O23: =VLOOKUP(H23,'RM Used'!A:E,5,0) -> KG | P23: =VLOOKUP(H23,'RM Used'!A:F,6,0) -> 0.34 | Q23: =P23*N23 -> 0.50763162 | R23: =IFERROR(IF(B23="Reynolds",VLOOKUP(H23,'Yield & Time'!A:U,21,0),VLOOKUP(H23,'Yield & Time'!A:L,12,0)),0) -> 0.79828722 | S23: =R23*J23*E23*AO$1 -> 0.29994445 | T23: =(R23*Z23*J23*E23)/60 -> 0.014768314 | U23: =IF(A22=A23,0,VLOOKUP(A23,'Packing Time'!A:F,6,0)) -> 2.4 | V23: =U23*AO$1 -> 0.8124 | W23: =(U23*Z23)/60 -> 0.04 | X23: =((R23*J23*E23)+U23)*AO$1*AP23 -> 1.7797511 | Y23: =X23*Z23 -> 1.7797511 | Z23: 1 | AA23: =Z23*N23 -> 1.4930342 | AB23: =AA23*P23 -> 0.50763162 | AC23: =(((R23*J23*E23)+U23)/60)*Z23*AP23 -> 0.087629302 | AD23: =AC23*60*AO$1 -> 1.7797511 | AE23: =VLOOKUP(H23,'Yield & Time'!A:R,18,0) -> CHLORINE | AF23: =IFERROR(VLOOKUP(AE23,'Chemical Cost'!A:D,4,0),0) -> 0.027756518 | AG23: =AF23*N23/3 -> 0.01381381 | AH23: =AF23*AA23/3 -> 0.01381381 | AI23: =IFERROR((Q23*Z23)+(Z23*X23)+AH23,0) -> 2.3011966 | AJ23: =IFERROR(VLOOKUP(A23,'All Products'!A:F,6,0),0) -> 20.46 | AK23: =AJ23*Z23*J23 -> 7.5702 | AL23: 0.85 | AM23: 0.15 | AN23: #N/A | AP23: 1.6 | AQ23: =(((R23*J23*E23)+U23)/60)*AP23 -> 0.087629302 | AR23: =_xlfn.XLOOKUP(F23,'RM Cost'!A:A,'RM Cost'!S:S) -> 0.29914854 | AS23: =_xlfn.XLOOKUP(A23,[3]Sheet1!$B:$B,[3]Sheet1!$B:$B) -> #N/A
A24: 1522CS | B24: Reynolds | C24: STIRFRY MIX WITH KALE 6 X 500G | D24: KG | E24: 3 | F24: =VLOOKUP(H24,'RM Used'!A:B,2,0) -> 3080CS | G24: =IFERROR(VLOOKUP(F24,'RM Cost'!A:B,2,0),"") -> RM - SAVOY CABBAGE 1 X 5KG | H24: SAVOY SHRED 3MM M/C RTW | I24: =VLOOKUP(F24,'RM Used'!B:D,3,0) -> RM-FOOD | J24: 0.3 | K24: =IF(I24="RM-FOOD",J24*E24,"") -> 0.9 | L24: =IFERROR(K24*Z24,0) -> 0.9 | M24: {=_xlfn.IFS(BOM!I24="RM-PACKING","100%",B24="Reynolds",VLOOKUP(H24,'Yield & Time'!A:V,22,0),BOM!B24="Dnata",VLOOKUP(BOM!H24,'Yield & Time'!A:M,13,0),B24="NK",VLOOKUP(H24,'Yield & Time'!A:X,24,0))} -> 0.72 | N24: =IFERROR(IF(I24="RM-FOOD",(E24*J24)/M24,1),0) -> 1.25 | O24: =VLOOKUP(H24,'RM Used'!A:E,5,0) -> KG | P24: =VLOOKUP(H24,'RM Used'!A:F,6,0) -> 0.76 | Q24: =P24*N24 -> 0.95 | R24: =IFERROR(IF(B24="Reynolds",VLOOKUP(H24,'Yield & Time'!A:U,21,0),VLOOKUP(H24,'Yield & Time'!A:L,12,0)),0) -> 0.87031835 | S24: =R24*J24*E24*AO$1 -> 0.26514249 | T24: =(R24*Z24*J24*E24)/60 -> 0.013054775 | U24: =IF(A23=A24,0,VLOOKUP(A24,'Packing Time'!A:F,6,0)) -> 0 | V24: =U24*AO$1 -> 0 | W24: =(U24*Z24)/60 -> 0 | X24: =((R24*J24*E24)+U24)*AO$1*AP24 -> 0.42422798 | Y24: =X24*Z24 -> 0.42422798 | Z24: 1 | AA24: =Z24*N24 -> 1.25 | AB24: =AA24*P24 -> 0.95 | AC24: =(((R24*J24*E24)+U24)/60)*Z24*AP24 -> 0.02088764 | AD24: =AC24*60*AO$1 -> 0.42422798 | AE24: =VLOOKUP(H24,'Yield & Time'!A:R,18,0) -> CHLORINE | AF24: =IFERROR(VLOOKUP(AE24,'Chemical Cost'!A:D,4,0),0) -> 0.027756518 | AG24: =AF24*N24/3 -> 0.011565216 | AH24: =AF24*AA24/3 -> 0.011565216 | AI24: =IFERROR((Q24*Z24)+(Z24*X24)+AH24,0) -> 1.3857932 | AJ24: =IFERROR(VLOOKUP(A24,'All Products'!A:F,6,0),0) -> 20.46 | AK24: =AJ24*Z24*J24 -> 6.138 | AL24: 0.85 | AM24: 0.15 | AN24: #N/A | AP24: 1.6 | AQ24: =(((R24*J24*E24)+U24)/60)*AP24 -> 0.02088764 | AR24: =_xlfn.XLOOKUP(F24,'RM Cost'!A:A,'RM Cost'!S:S) -> 0 | AS24: =_xlfn.XLOOKUP(A24,[3]Sheet1!$B:$B,[3]Sheet1!$B:$B) -> #N/A
A25: 1522CS | B25: Reynolds | C25: STIRFRY MIX WITH KALE 6 X 500G | D25: KG | E25: 3 | F25: =VLOOKUP(H25,'RM Used'!A:B,2,0) -> 032ACS | G25: =IFERROR(VLOOKUP(F25,'RM Cost'!A:B,2,0),"") -> RM - LRG PROCESSING CARROT X 1000KG | H25: Carrot - Julienne | I25: =VLOOKUP(F25,'RM Used'!B:D,3,0) -> RM-FOOD | J25: 0.2 | K25: =IF(I25="RM-FOOD",J25*E25,"") -> 0.6 | L25: =IFERROR(K25*Z25,0) -> 0.6 | M25: {=_xlfn.IFS(BOM!I25="RM-PACKING","100%",B25="Reynolds",VLOOKUP(H25,'Yield & Time'!A:V,22,0),BOM!B25="Dnata",VLOOKUP(BOM!H25,'Yield & Time'!A:M,13,0),B25="NK",VLOOKUP(H25,'Yield & Time'!A:X,24,0))} -> 0.7533 | N25: =IFERROR(IF(I25="RM-FOOD",(E25*J25)/M25,1),0) -> 0.79649542 | O25: =VLOOKUP(H25,'RM Used'!A:E,5,0) -> KG | P25: =VLOOKUP(H25,'RM Used'!A:F,6,0) -> 0.38 | Q25: =P25*N25 -> 0.30266826 | R25: =IFERROR(IF(B25="Reynolds",VLOOKUP(H25,'Yield & Time'!A:U,21,0),VLOOKUP(H25,'Yield & Time'!A:L,12,0)),0) -> 0.90531915 | S25: =R25*J25*E25*AO$1 -> 0.18387032 | T25: =(R25*Z25*J25*E25)/60 -> 0.0090531915 | U25: =IF(A24=A25,0,VLOOKUP(A25,'Packing Time'!A:F,6,0)) -> 0 | V25: =U25*AO$1 -> 0 | W25: =(U25*Z25)/60 -> 0 | X25: =((R25*J25*E25)+U25)*AO$1*AP25 -> 0.29419251 | Y25: =X25*Z25 -> 0.29419251 | Z25: 1 | AA25: =Z25*N25 -> 0.79649542 | AB25: =AA25*P25 -> 0.30266826 | AC25: =(((R25*J25*E25)+U25)/60)*Z25*AP25 -> 0.014485106 | AD25: =AC25*60*AO$1 -> 0.29419251 | AE25: =VLOOKUP(H25,'Yield & Time'!A:R,18,0) -> CHLORINE | AF25: =IFERROR(VLOOKUP(AE25,'Chemical Cost'!A:D,4,0),0) -> 0.027756518 | AG25: =AF25*N25/3 -> 0.0073693132 | AH25: =AF25*AA25/3 -> 0.0073693132 | AI25: =IFERROR((Q25*Z25)+(Z25*X25)+AH25,0) -> 0.60423008 | AJ25: =IFERROR(VLOOKUP(A25,'All Products'!A:F,6,0),0) -> 20.46 | AK25: =AJ25*Z25*J25 -> 4.092 | AL25: 0.85 | AM25: 0.15 | AN25: #N/A | AP25: 1.6 | AQ25: =(((R25*J25*E25)+U25)/60)*AP25 -> 0.014485106 | AR25: =_xlfn.XLOOKUP(F25,'RM Cost'!A:A,'RM Cost'!S:S) -> 0 | AS25: =_xlfn.XLOOKUP(A25,[3]Sheet1!$B:$B,[3]Sheet1!$B:$B) -> #N/A
A26: 1522CS | B26: Reynolds | C26: STIRFRY MIX WITH KALE 6 X 500G | D26: KG | E26: 3 | F26: =VLOOKUP(H26,'RM Used'!A:B,2,0) -> 3112CS | G26: =IFERROR(VLOOKUP(F26,'RM Cost'!A:B,2,0),"") -> WHOLE LEAF CURLY KALE 5X1KG | H26: Kale - Shredded | I26: =VLOOKUP(F26,'RM Used'!B:D,3,0) -> RM-FOOD | J26: 0.13 | K26: =IF(I26="RM-FOOD",J26*E26,"") -> 0.39 | L26: =IFERROR(K26*Z26,0) -> 0.39 | M26: {=_xlfn.IFS(BOM!I26="RM-PACKING","100%",B26="Reynolds",VLOOKUP(H26,'Yield & Time'!A:V,22,0),BOM!B26="Dnata",VLOOKUP(BOM!H26,'Yield & Time'!A:M,13,0),B26="NK",VLOOKUP(H26,'Yield & Time'!A:X,24,0))} -> 0.73052363 | N26: =IFERROR(IF(I26="RM-FOOD",(E26*J26)/M26,1),0) -> 0.53386364 | O26: =VLOOKUP(H26,'RM Used'!A:E,5,0) -> KG | P26: =VLOOKUP(H26,'RM Used'!A:F,6,0) -> 1.45 | Q26: =P26*N26 -> 0.77410227 | R26: =IFERROR(IF(B26="Reynolds",VLOOKUP(H26,'Yield & Time'!A:U,21,0),VLOOKUP(H26,'Yield & Time'!A:L,12,0)),0) -> 3.3216783 | S26: =R26*J26*E26*AO$1 -> 0.43851136 | T26: =(R26*Z26*J26*E26)/60 -> 0.021590909 | U26: =IF(A25=A26,0,VLOOKUP(A26,'Packing Time'!A:F,6,0)) -> 0 | V26: =U26*AO$1 -> 0 | W26: =(U26*Z26)/60 -> 0 | X26: =((R26*J26*E26)+U26)*AO$1*AP26 -> 0.70161818 | Y26: =X26*Z26 -> 0.70161818 | Z26: 1 | AA26: =Z26*N26 -> 0.53386364 | AB26: =AA26*P26 -> 0.77410227 | AC26: =(((R26*J26*E26)+U26)/60)*Z26*AP26 -> 0.034545455 | AD26: =AC26*60*AO$1 -> 0.70161818 | AE26: =VLOOKUP(H26,'Yield & Time'!A:R,18,0) -> CHLORINE | AF26: =IFERROR(VLOOKUP(AE26,'Chemical Cost'!A:D,4,0),0) -> 0.027756518 | AG26: =AF26*N26/3 -> 0.0049393986 | AH26: =AF26*AA26/3 -> 0.0049393986 | AI26: =IFERROR((Q26*Z26)+(Z26*X26)+AH26,0) -> 1.4806599 | AJ26: =IFERROR(VLOOKUP(A26,'All Products'!A:F,6,0),0) -> 20.46 | AK26: =AJ26*Z26*J26 -> 2.6598 | AL26: 0.85 | AM26: 0.15 | AN26: #N/A | AP26: 1.6 | AQ26: =(((R26*J26*E26)+U26)/60)*AP26 -> 0.034545455 | AR26: =_xlfn.XLOOKUP(F26,'RM Cost'!A:A,'RM Cost'!S:S) -> 0 | AS26: =_xlfn.XLOOKUP(A26,[3]Sheet1!$B:$B,[3]Sheet1!$B:$B) -> #N/A
A27: 1522CS | B27: Reynolds | C27: STIRFRY MIX WITH KALE 6 X 500G | D27: KG | E27: 3 | F27: =VLOOKUP(H27,'RM Used'!A:B,2,0) -> P0004 | G27: =IFERROR(VLOOKUP(F27,'RM Cost'!A:B,2,0),"") -> SOL 30EL # PPLUS 630x1000 BLUE -6 | H27: SOL 30EL # PPLUS 630x1000 BLUE -6 | I27: =VLOOKUP(F27,'RM Used'!B:D,3,0) -> RM-PACKING | J27: 1 | K27: =IF(I27="RM-FOOD",J27*E27,"") | L27: =IFERROR(K27*Z27,0) -> 0 | M27: {=_xlfn.IFS(BOM!I27="RM-PACKING","100%",B27="Reynolds",VLOOKUP(H27,'Yield & Time'!A:V,22,0),BOM!B27="Dnata",VLOOKUP(BOM!H27,'Yield & Time'!A:M,13,0),B27="NK",VLOOKUP(H27,'Yield & Time'!A:X,24,0))} -> 100% | N27: =IFERROR(IF(I27="RM-FOOD",(E27*J27)/M27,1),0) -> 1 | O27: =VLOOKUP(H27,'RM Used'!A:E,5,0) -> Count | P27: =VLOOKUP(H27,'RM Used'!A:F,6,0) -> 0.48 | Q27: =P27*N27 -> 0.48 | R27: =IFERROR(IF(B27="Reynolds",VLOOKUP(H27,'Yield & Time'!A:U,21,0),VLOOKUP(H27,'Yield & Time'!A:L,12,0)),0) -> 0 | S27: =R27*J27*E27*AO$1 -> 0 | T27: =(R27*Z27*J27*E27)/60 -> 0 | U27: =IF(A26=A27,0,VLOOKUP(A27,'Packing Time'!A:F,6,0)) -> 0 | V27: =U27*AO$1 -> 0 | W27: =(U27*Z27)/60 -> 0 | X27: =((R27*J27*E27)+U27)*AO$1*AP27 -> 0 | Y27: =X27*Z27 -> 0 | Z27: 1 | AA27: =Z27*N27 -> 1 | AB27: =AA27*P27 -> 0.48 | AC27: =(((R27*J27*E27)+U27)/60)*Z27*AP27 -> 0 | AD27: =AC27*60*AO$1 -> 0 | AF27: =IFERROR(VLOOKUP(AE27,'Chemical Cost'!A:D,4,0),0) -> 0 | AG27: =AF27*N27/3 -> 0 | AH27: =AF27*AA27/3 -> 0 | AI27: =IFERROR((Q27*Z27)+(Z27*X27)+AH27,0) -> 0.48 | AJ27: =IFERROR(VLOOKUP(A27,'All Products'!A:F,6,0),0) -> 20.46 | AL27: 0.85 | AM27: 0.15 | AN27: #N/A | AP27: 1.6 | AQ27: =(((R27*J27*E27)+U27)/60)*AP27 -> 0 | AR27: =_xlfn.XLOOKUP(F27,'RM Cost'!A:A,'RM Cost'!S:S) -> 0 | AS27: =_xlfn.XLOOKUP(A27,[3]Sheet1!$B:$B,[3]Sheet1!$B:$B) -> #N/A
A28: 1522CS | B28: Reynolds | C28: STIRFRY MIX WITH KALE 6 X 500G | D28: KG | E28: 3 | F28: =VLOOKUP(H28,'RM Used'!A:B,2,0) -> P0016 | G28: =IFERROR(VLOOKUP(F28,'RM Cost'!A:B,2,0),"") -> REY 40 30 BOX | H28: black box | I28: =VLOOKUP(F28,'RM Used'!B:D,3,0) -> RM-PACKING | J28: 1 | K28: =IF(I28="RM-FOOD",J28*E28,"") | L28: =IFERROR(K28*Z28,0) -> 0 | M28: {=_xlfn.IFS(BOM!I28="RM-PACKING","100%",B28="Reynolds",VLOOKUP(H28,'Yield & Time'!A:V,22,0),BOM!B28="Dnata",VLOOKUP(BOM!H28,'Yield & Time'!A:M,13,0),B28="NK",VLOOKUP(H28,'Yield & Time'!A:X,24,0))} -> 100% | N28: =IFERROR(IF(I28="RM-FOOD",(E28*J28)/M28,1),0) -> 1 | O28: =VLOOKUP(H28,'RM Used'!A:E,5,0) -> Count | P28: =VLOOKUP(H28,'RM Used'!A:F,6,0) -> 0.28 | Q28: =P28*N28 -> 0.28 | R28: =IFERROR(IF(B28="Reynolds",VLOOKUP(H28,'Yield & Time'!A:U,21,0),VLOOKUP(H28,'Yield & Time'!A:L,12,0)),0) -> 0 | S28: =R28*J28*E28*AO$1 -> 0 | T28: =(R28*Z28*J28*E28)/60 -> 0 | U28: =IF(A27=A28,0,VLOOKUP(A28,'Packing Time'!A:F,6,0)) -> 0 | V28: =U28*AO$1 -> 0 | W28: =(U28*Z28)/60 -> 0 | X28: =((R28*J28*E28)+U28)*AO$1*AP28 -> 0 | Y28: =X28*Z28 -> 0 | Z28: 1 | AA28: =Z28*N28 -> 1 | AB28: =AA28*P28 -> 0.28 | AC28: =(((R28*J28*E28)+U28)/60)*Z28*AP28 -> 0 | AD28: =AC28*60*AO$1 -> 0 | AF28: =IFERROR(VLOOKUP(AE28,'Chemical Cost'!A:D,4,0),0) -> 0 | AG28: =AF28*N28/3 -> 0 | AH28: =AF28*AA28/3 -> 0 | AI28: =IFERROR((Q28*Z28)+(Z28*X28)+AH28,0) -> 0.28 | AJ28: =IFERROR(VLOOKUP(A28,'All Products'!A:F,6,0),0) -> 20.46 | AL28: 0.85 | AM28: 0.15 | AN28: #N/A | AP28: 1.6 | AQ28: =(((R28*J28*E28)+U28)/60)*AP28 -> 0 | AR28: =_xlfn.XLOOKUP(F28,'RM Cost'!A:A,'RM Cost'!S:S) -> 0 | AS28: =_xlfn.XLOOKUP(A28,[3]Sheet1!$B:$B,[3]Sheet1!$B:$B) -> #N/A
A29: 789ACS | B29: Reynolds | C29: STIR FRY VEG DL 1x1.5KG | D29: KG | E29: 1.5 | F29: =VLOOKUP(H29,'RM Used'!A:B,2,0) -> S3997CS | G29: =IFERROR(VLOOKUP(F29,'RM Cost'!A:B,2,0),"") -> RM - DECORE WHITE CABBAGE 1/3 1200KG | H29: Cabbage White - Shredded | I29: =VLOOKUP(F29,'RM Used'!B:D,3,0) -> RM-FOOD | J29: 0.3 | K29: =IF(I29="RM-FOOD",J29*E29,"") -> 0.45 | L29: =IFERROR(K29*Z29,0) -> 0.45 | M29: {=_xlfn.IFS(BOM!I29="RM-PACKING","100%",B29="Reynolds",VLOOKUP(H29,'Yield & Time'!A:V,22,0),BOM!B29="Dnata",VLOOKUP(BOM!H29,'Yield & Time'!A:M,13,0),B29="NK",VLOOKUP(H29,'Yield & Time'!A:X,24,0))} -> 0.7434525 | N29: =IFERROR(IF(I29="RM-FOOD",(E29*J29)/M29,1),0) -> 0.60528413 | O29: =VLOOKUP(H29,'RM Used'!A:E,5,0) -> KG | P29: =VLOOKUP(H29,'RM Used'!A:F,6,0) -> 0.34 | Q29: =P29*N29 -> 0.2057966 | R29: =IFERROR(IF(B29="Reynolds",VLOOKUP(H29,'Yield & Time'!A:U,21,0),VLOOKUP(H29,'Yield & Time'!A:L,12,0)),0) -> 0.79828722 | S29: =R29*J29*E29*AO$1 -> 0.1215991 | T29: =(R29*Z29*J29*E29)/60 -> 0.0059871541 | U29: =IF(A28=A29,0,VLOOKUP(A29,'Packing Time'!A:F,6,0)) -> 0.645 | V29: =U29*AO$1 -> 0.2183325 | W29: =(U29*Z29)/60 -> 0.01075 | X29: =((R29*J29*E29)+U29)*AO$1*AP29 -> 0.54389056 | Y29: =X29*Z29 -> 0.54389056 | Z29: 1 | AA29: =Z29*N29 -> 0.60528413 | AB29: =AA29*P29 -> 0.2057966 | AC29: =(((R29*J29*E29)+U29)/60)*Z29*AP29 -> 0.026779447 | AD29: =AC29*60*AO$1 -> 0.54389056 | AE29: =VLOOKUP(H29,'Yield & Time'!A:R,18,0) -> CHLORINE | AF29: =IFERROR(VLOOKUP(AE29,'Chemical Cost'!A:D,4,0),0) -> 0.027756518 | AG29: =AF29*N29/3 -> 0.0056001933 | AH29: =AF29*AA29/3 -> 0.0056001933 | AI29: =IFERROR((Q29*Z29)+(Z29*X29)+AH29,0) -> 0.75528736 | AJ29: =IFERROR(VLOOKUP(A29,'All Products'!A:F,6,0),0) -> 6.84 | AK29: =AJ29*Z29*J29 -> 2.052 | AL29: 0.8 | AM29: 0.2 | AN29: #N/A | AP29: 1.6 | AQ29: =(((R29*J29*E29)+U29)/60)*AP29 -> 0.026779447 | AR29: =_xlfn.XLOOKUP(F29,'RM Cost'!A:A,'RM Cost'!S:S) -> 0.29914854 | AS29: =_xlfn.XLOOKUP(A29,[3]Sheet1!$B:$B,[3]Sheet1!$B:$B) -> #N/A
A30: 789ACS | B30: Reynolds | C30: STIR FRY VEG DL 1x1.5KG | D30: KG | E30: 1.5 | F30: =VLOOKUP(H30,'RM Used'!A:B,2,0) -> 032ACS | G30: =IFERROR(VLOOKUP(F30,'RM Cost'!A:B,2,0),"") -> RM - LRG PROCESSING CARROT X 1000KG | H30: Carrot - Julienne | I30: =VLOOKUP(F30,'RM Used'!B:D,3,0) -> RM-FOOD | J30: 0.25 | K30: =IF(I30="RM-FOOD",J30*E30,"") -> 0.375 | L30: =IFERROR(K30*Z30,0) -> 0.375 | M30: {=_xlfn.IFS(BOM!I30="RM-PACKING","100%",B30="Reynolds",VLOOKUP(H30,'Yield & Time'!A:V,22,0),BOM!B30="Dnata",VLOOKUP(BOM!H30,'Yield & Time'!A:M,13,0),B30="NK",VLOOKUP(H30,'Yield & Time'!A:X,24,0))} -> 0.7533 | N30: =IFERROR(IF(I30="RM-FOOD",(E30*J30)/M30,1),0) -> 0.49780964 | O30: =VLOOKUP(H30,'RM Used'!A:E,5,0) -> KG | P30: =VLOOKUP(H30,'RM Used'!A:F,6,0) -> 0.38 | Q30: =P30*N30 -> 0.18916766 | R30: =IFERROR(IF(B30="Reynolds",VLOOKUP(H30,'Yield & Time'!A:U,21,0),VLOOKUP(H30,'Yield & Time'!A:L,12,0)),0) -> 0.90531915 | S30: =R30*J30*E30*AO$1 -> 0.11491895 | T30: =(R30*Z30*J30*E30)/60 -> 0.0056582447 | U30: =IF(A29=A30,0,VLOOKUP(A30,'Packing Time'!A:F,6,0)) -> 0 | V30: =U30*AO$1 -> 0 | W30: =(U30*Z30)/60 -> 0 | X30: =((R30*J30*E30)+U30)*AO$1*AP30 -> 0.18387032 | Y30: =X30*Z30 -> 0.18387032 | Z30: 1 | AA30: =Z30*N30 -> 0.49780964 | AB30: =AA30*P30 -> 0.18916766 | AC30: =(((R30*J30*E30)+U30)/60)*Z30*AP30 -> 0.0090531915 | AD30: =AC30*60*AO$1 -> 0.18387032 | AE30: =VLOOKUP(H30,'Yield & Time'!A:R,18,0) -> CHLORINE | AF30: =IFERROR(VLOOKUP(AE30,'Chemical Cost'!A:D,4,0),0) -> 0.027756518 | AG30: =AF30*N30/3 -> 0.0046058207 | AH30: =AF30*AA30/3 -> 0.0046058207 | AI30: =IFERROR((Q30*Z30)+(Z30*X30)+AH30,0) -> 0.3776438 | AJ30: =IFERROR(VLOOKUP(A30,'All Products'!A:F,6,0),0) -> 6.84 | AK30: =AJ30*Z30*J30 -> 1.71 | AL30: 0.8 | AM30: 0.2 | AN30: #N/A | AP30: 1.6 | AQ30: =(((R30*J30*E30)+U30)/60)*AP30 -> 0.0090531915 | AR30: =_xlfn.XLOOKUP(F30,'RM Cost'!A:A,'RM Cost'!S:S) -> 0 | AS30: =_xlfn.XLOOKUP(A30,[3]Sheet1!$B:$B,[3]Sheet1!$B:$B) -> #N/A
A31: 789ACS | B31: Reynolds | C31: STIR FRY VEG DL 1x1.5KG | D31: KG | E31: 1.5 | F31: =VLOOKUP(H31,'RM Used'!A:B,2,0) -> 3566CS | G31: =IFERROR(VLOOKUP(F31,'RM Cost'!A:B,2,0),"") -> PEPPERS RED X 5KG | H31: Pepper Red - Sliced 10mm | I31: =VLOOKUP(F31,'RM Used'!B:D,3,0) -> RM-FOOD | J31: 0.15 | K31: =IF(I31="RM-FOOD",J31*E31,"") -> 0.225 | L31: =IFERROR(K31*Z31,0) -> 0.225 | M31: {=_xlfn.IFS(BOM!I31="RM-PACKING","100%",B31="Reynolds",VLOOKUP(H31,'Yield & Time'!A:V,22,0),BOM!B31="Dnata",VLOOKUP(BOM!H31,'Yield & Time'!A:M,13,0),B31="NK",VLOOKUP(H31,'Yield & Time'!A:X,24,0))} -> 0.69679992 | N31: =IFERROR(IF(I31="RM-FOOD",(E31*J31)/M31,1),0) -> 0.32290474 | O31: =VLOOKUP(H31,'RM Used'!A:E,5,0) -> KG | P31: =VLOOKUP(H31,'RM Used'!A:F,6,0) -> 1.72 | Q31: =P31*N31 -> 0.55539616 | R31: =IFERROR(IF(B31="Reynolds",VLOOKUP(H31,'Yield & Time'!A:U,21,0),VLOOKUP(H31,'Yield & Time'!A:L,12,0)),0) -> 1.4647664 | S31: =R31*J31*E31*AO$1 -> 0.11156027 | T31: =(R31*Z31*J31*E31)/60 -> 0.0054928741 | U31: =IF(A30=A31,0,VLOOKUP(A31,'Packing Time'!A:F,6,0)) -> 0 | V31: =U31*AO$1 -> 0 | W31: =(U31*Z31)/60 -> 0 | X31: =((R31*J31*E31)+U31)*AO$1*AP31 -> 0.17849644 | Y31: =X31*Z31 -> 0.17849644 | Z31: 1 | AA31: =Z31*N31 -> 0.32290474 | AB31: =AA31*P31 -> 0.55539616 | AC31: =(((R31*J31*E31)+U31)/60)*Z31*AP31 -> 0.0087885986 | AD31: =AC31*60*AO$1 -> 0.17849644 | AE31: =VLOOKUP(H31,'Yield & Time'!A:R,18,0) -> CHLORINE | AF31: =IFERROR(VLOOKUP(AE31,'Chemical Cost'!A:D,4,0),0) -> 0.027756518 | AG31: =AF31*N31/3 -> 0.0029875704 | AH31: =AF31*AA31/3 -> 0.0029875704 | AI31: =IFERROR((Q31*Z31)+(Z31*X31)+AH31,0) -> 0.73688016 | AJ31: =IFERROR(VLOOKUP(A31,'All Products'!A:F,6,0),0) -> 6.84 | AK31: =AJ31*Z31*J31 -> 1.026 | AL31: 0.8 | AM31: 0.2 | AN31: #N/A | AP31: 1.6 | AQ31: =(((R31*J31*E31)+U31)/60)*AP31 -> 0.0087885986 | AR31: =_xlfn.XLOOKUP(F31,'RM Cost'!A:A,'RM Cost'!S:S) -> 0 | AS31: =_xlfn.XLOOKUP(A31,[3]Sheet1!$B:$B,[3]Sheet1!$B:$B) -> #N/A
A32: 789ACS | B32: Reynolds | C32: STIR FRY VEG DL 1x1.5KG | D32: KG | E32: 1.5 | F32: =VLOOKUP(H32,'RM Used'!A:B,2,0) -> 0930CS | G32: =IFERROR(VLOOKUP(F32,'RM Cost'!A:B,2,0),"") -> RM - COURGETTE STANDARD | H32: Courgette - Matchsticks | I32: =VLOOKUP(F32,'RM Used'!B:D,3,0) -> RM-FOOD | J32: 0.1 | K32: =IF(I32="RM-FOOD",J32*E32,"") -> 0.15 | L32: =IFERROR(K32*Z32,0) -> 0.15 | M32: {=_xlfn.IFS(BOM!I32="RM-PACKING","100%",B32="Reynolds",VLOOKUP(H32,'Yield & Time'!A:V,22,0),BOM!B32="Dnata",VLOOKUP(BOM!H32,'Yield & Time'!A:M,13,0),B32="NK",VLOOKUP(H32,'Yield & Time'!A:X,24,0))} -> 0.75 | N32: =IFERROR(IF(I32="RM-FOOD",(E32*J32)/M32,1),0) -> 0.2 | O32: =VLOOKUP(H32,'RM Used'!A:E,5,0) -> KG | P32: =VLOOKUP(H32,'RM Used'!A:F,6,0) -> 1.1 | Q32: =P32*N32 -> 0.22 | R32: =IFERROR(IF(B32="Reynolds",VLOOKUP(H32,'Yield & Time'!A:U,21,0),VLOOKUP(H32,'Yield & Time'!A:L,12,0)),0) -> 1.2 | S32: =R32*J32*E32*AO$1 -> 0.06093 | T32: =(R32*Z32*J32*E32)/60 -> 0.003 | U32: =IF(A31=A32,0,VLOOKUP(A32,'Packing Time'!A:F,6,0)) -> 0 | V32: =U32*AO$1 -> 0 | W32: =(U32*Z32)/60 -> 0 | X32: =((R32*J32*E32)+U32)*AO$1*AP32 -> 0.097488 | Y32: =X32*Z32 -> 0.097488 | Z32: 1 | AA32: =Z32*N32 -> 0.2 | AB32: =AA32*P32 -> 0.22 | AC32: =(((R32*J32*E32)+U32)/60)*Z32*AP32 -> 0.0048 | AD32: =AC32*60*AO$1 -> 0.097488 | AE32: =VLOOKUP(H32,'Yield & Time'!A:R,18,0) -> CHLORINE | AF32: =IFERROR(VLOOKUP(AE32,'Chemical Cost'!A:D,4,0),0) -> 0.027756518 | AG32: =AF32*N32/3 -> 0.0018504345 | AH32: =AF32*AA32/3 -> 0.0018504345 | AI32: =IFERROR((Q32*Z32)+(Z32*X32)+AH32,0) -> 0.31933843 | AJ32: =IFERROR(VLOOKUP(A32,'All Products'!A:F,6,0),0) -> 6.84 | AK32: =AJ32*Z32*J32 -> 0.684 | AL32: 0.8 | AM32: 0.2 | AN32: #N/A | AP32: 1.6 | AQ32: =(((R32*J32*E32)+U32)/60)*AP32 -> 0.0048 | AR32: =_xlfn.XLOOKUP(F32,'RM Cost'!A:A,'RM Cost'!S:S) -> 1.1644776 | AS32: =_xlfn.XLOOKUP(A32,[3]Sheet1!$B:$B,[3]Sheet1!$B:$B) -> #N/A
A33: 789ACS | B33: Reynolds | C33: STIR FRY VEG DL 1x1.5KG | D33: KG | E33: 1.5 | F33: =VLOOKUP(H33,'RM Used'!A:B,2,0) -> 3034CS | G33: =IFERROR(VLOOKUP(F33,'RM Cost'!A:B,2,0),"") -> RM - BROCCOLI 6KG | H33: Broccoli - Floret 25mm | I33: =VLOOKUP(F33,'RM Used'!B:D,3,0) -> RM-FOOD | J33: 0.1 | K33: =IF(I33="RM-FOOD",J33*E33,"") -> 0.15 | L33: =IFERROR(K33*Z33,0) -> 0.15 | M33: {=_xlfn.IFS(BOM!I33="RM-PACKING","100%",B33="Reynolds",VLOOKUP(H33,'Yield & Time'!A:V,22,0),BOM!B33="Dnata",VLOOKUP(BOM!H33,'Yield & Time'!A:M,13,0),B33="NK",VLOOKUP(H33,'Yield & Time'!A:X,24,0))} -> 0.58 | N33: =IFERROR(IF(I33="RM-FOOD",(E33*J33)/M33,1),0) -> 0.25862069 | O33: =VLOOKUP(H33,'RM Used'!A:E,5,0) -> KG | P33: =VLOOKUP(H33,'RM Used'!A:F,6,0) -> 1.02 | Q33: =P33*N33 -> 0.2637931 | R33: =IFERROR(IF(B33="Reynolds",VLOOKUP(H33,'Yield & Time'!A:U,21,0),VLOOKUP(H33,'Yield & Time'!A:L,12,0)),0) -> 2.7 | S33: =R33*J33*E33*AO$1 -> 0.1370925 | T33: =(R33*Z33*J33*E33)/60 -> 0.00675 | U33: =IF(A32=A33,0,VLOOKUP(A33,'Packing Time'!A:F,6,0)) -> 0 | V33: =U33*AO$1 -> 0 | W33: =(U33*Z33)/60 -> 0 | X33: =((R33*J33*E33)+U33)*AO$1*AP33 -> 0.219348 | Y33: =X33*Z33 -> 0.219348 | Z33: 1 | AA33: =Z33*N33 -> 0.25862069 | AB33: =AA33*P33 -> 0.2637931 | AC33: =(((R33*J33*E33)+U33)/60)*Z33*AP33 -> 0.0108 | AD33: =AC33*60*AO$1 -> 0.219348 | AF33: =IFERROR(VLOOKUP(AE33,'Chemical Cost'!A:D,4,0),0) -> 0 | AG33: =AF33*N33/3 -> 0 | AH33: =AF33*AA33/3 -> 0 | AI33: =IFERROR((Q33*Z33)+(Z33*X33)+AH33,0) -> 0.4831411 | AJ33: =IFERROR(VLOOKUP(A33,'All Products'!A:F,6,0),0) -> 6.84 | AK33: =AJ33*Z33*J33 -> 0.684 | AL33: 0.8 | AM33: 0.2 | AN33: #N/A | AP33: 1.6 | AQ33: =(((R33*J33*E33)+U33)/60)*AP33 -> 0.0108 | AR33: =_xlfn.XLOOKUP(F33,'RM Cost'!A:A,'RM Cost'!S:S) -> 0 | AS33: =_xlfn.XLOOKUP(A33,[3]Sheet1!$B:$B,[3]Sheet1!$B:$B) -> #N/A
A34: 789ACS | B34: Reynolds | C34: STIR FRY VEG DL 1x1.5KG | D34: KG | E34: 1.5 | F34: =VLOOKUP(H34,'RM Used'!A:B,2,0) -> 120ACS | G34: =IFERROR(VLOOKUP(F34,'RM Cost'!A:B,2,0),"") -> RM - BEANS EXTRA FINE PREMIUM 1.5KG | H34: Fine beans - top and tailed | I34: =VLOOKUP(F34,'RM Used'!B:D,3,0) -> RM-FOOD | J34: 0.05 | K34: =IF(I34="RM-FOOD",J34*E34,"") -> 0.075 | L34: =IFERROR(K34*Z34,0) -> 0.075 | M34: {=_xlfn.IFS(BOM!I34="RM-PACKING","100%",B34="Reynolds",VLOOKUP(H34,'Yield & Time'!A:V,22,0),BOM!B34="Dnata",VLOOKUP(BOM!H34,'Yield & Time'!A:M,13,0),B34="NK",VLOOKUP(H34,'Yield & Time'!A:X,24,0))} -> 0.74 | N34: =IFERROR(IF(I34="RM-FOOD",(E34*J34)/M34,1),0) -> 0.10135135 | O34: =VLOOKUP(H34,'RM Used'!A:E,5,0) -> KG | P34: =VLOOKUP(H34,'RM Used'!A:F,6,0) -> #N/A | Q34: =P34*N34 -> #N/A | R34: =IFERROR(IF(B34="Reynolds",VLOOKUP(H34,'Yield & Time'!A:U,21,0),VLOOKUP(H34,'Yield & Time'!A:L,12,0)),0) -> 12.387387 | S34: =R34*J34*E34*AO$1 -> 0.3144848 | T34: =(R34*Z34*J34*E34)/60 -> 0.015484234 | U34: =IF(A33=A34,0,VLOOKUP(A34,'Packing Time'!A:F,6,0)) -> 0 | V34: =U34*AO$1 -> 0 | W34: =(U34*Z34)/60 -> 0 | X34: =((R34*J34*E34)+U34)*AO$1*AP34 -> 0.50317568 | Y34: =X34*Z34 -> 0.50317568 | Z34: 1 | AA34: =Z34*N34 -> 0.10135135 | AB34: =AA34*P34 -> #N/A | AC34: =(((R34*J34*E34)+U34)/60)*Z34*AP34 -> 0.024774775 | AD34: =AC34*60*AO$1 -> 0.50317568 | AF34: =IFERROR(VLOOKUP(AE34,'Chemical Cost'!A:D,4,0),0) -> 0 | AG34: =AF34*N34/3 -> 0 | AH34: =AF34*AA34/3 -> 0 | AI34: =IFERROR((Q34*Z34)+(Z34*X34)+AH34,0) -> 0 | AJ34: =IFERROR(VLOOKUP(A34,'All Products'!A:F,6,0),0) -> 6.84 | AK34: =AJ34*Z34*J34 -> 0.342 | AL34: 0.8 | AM34: 0.2 | AN34: #N/A | AP34: 1.6 | AQ34: =(((R34*J34*E34)+U34)/60)*AP34 -> 0.024774775 | AR34: =_xlfn.XLOOKUP(F34,'RM Cost'!A:A,'RM Cost'!S:S) -> 0 | AS34: =_xlfn.XLOOKUP(A34,[3]Sheet1!$B:$B,[3]Sheet1!$B:$B) -> #N/A
A35: 789ACS | B35: Reynolds | C35: STIR FRY VEG DL 1x1.5KG | D35: KG | E35: 1.5 | F35: =VLOOKUP(H35,'RM Used'!A:B,2,0) -> 3138CS | G35: =IFERROR(VLOOKUP(F35,'RM Cost'!A:B,2,0),"") -> RM - MANGETOUT 2KG | H35: Mangetout - whole no prep | I35: =VLOOKUP(F35,'RM Used'!B:D,3,0) -> RM-FOOD | J35: 0.05 | K35: =IF(I35="RM-FOOD",J35*E35,"") -> 0.075 | L35: =IFERROR(K35*Z35,0) -> 0.075 | M35: {=_xlfn.IFS(BOM!I35="RM-PACKING","100%",B35="Reynolds",VLOOKUP(H35,'Yield & Time'!A:V,22,0),BOM!B35="Dnata",VLOOKUP(BOM!H35,'Yield & Time'!A:M,13,0),B35="NK",VLOOKUP(H35,'Yield & Time'!A:X,24,0))} -> 1 | N35: =IFERROR(IF(I35="RM-FOOD",(E35*J35)/M35,1),0) -> 0.075 | O35: =VLOOKUP(H35,'RM Used'!A:E,5,0) -> KG | P35: =VLOOKUP(H35,'RM Used'!A:F,6,0) -> 4.13 | Q35: =P35*N35 -> 0.30975 | R35: =IFERROR(IF(B35="Reynolds",VLOOKUP(H35,'Yield & Time'!A:U,21,0),VLOOKUP(H35,'Yield & Time'!A:L,12,0)),0) -> 0 | S35: =R35*J35*E35*AO$1 -> 0 | T35: =(R35*Z35*J35*E35)/60 -> 0 | U35: =IF(A34=A35,0,VLOOKUP(A35,'Packing Time'!A:F,6,0)) -> 0 | V35: =U35*AO$1 -> 0 | W35: =(U35*Z35)/60 -> 0 | X35: =((R35*J35*E35)+U35)*AO$1*AP35 -> 0 | Y35: =X35*Z35 -> 0 | Z35: 1 | AA35: =Z35*N35 -> 0.075 | AB35: =AA35*P35 -> 0.30975 | AC35: =(((R35*J35*E35)+U35)/60)*Z35*AP35 -> 0 | AD35: =AC35*60*AO$1 -> 0 | AF35: =IFERROR(VLOOKUP(AE35,'Chemical Cost'!A:D,4,0),0) -> 0 | AG35: =AF35*N35/3 -> 0 | AH35: =AF35*AA35/3 -> 0 | AI35: =IFERROR((Q35*Z35)+(Z35*X35)+AH35,0) -> 0.30975 | AJ35: =IFERROR(VLOOKUP(A35,'All Products'!A:F,6,0),0) -> 6.84 | AK35: =AJ35*Z35*J35 -> 0.342 | AL35: 0.8 | AM35: 0.2 | AN35: #N/A | AP35: 1.6 | AQ35: =(((R35*J35*E35)+U35)/60)*AP35 -> 0 | AR35: =_xlfn.XLOOKUP(F35,'RM Cost'!A:A,'RM Cost'!S:S) -> 0 | AS35: =_xlfn.XLOOKUP(A35,[3]Sheet1!$B:$B,[3]Sheet1!$B:$B) -> #N/A
A36: 789ACS | B36: Reynolds | C36: STIR FRY VEG DL 1x1.5KG | D36: KG | E36: 1.5 | F36: =VLOOKUP(H36,'RM Used'!A:B,2,0) -> P0020 | G36: =IFERROR(VLOOKUP(F36,'RM Cost'!A:B,2,0),"") -> PALE BLUE BAG 430X430MM | H36: BLUE TINT BAGS ON A ROLL - SMALL | I36: =VLOOKUP(F36,'RM Used'!B:D,3,0) -> RM-PACKING | J36: 1 | K36: =IF(I36="RM-FOOD",J36*E36,"") | L36: =IFERROR(K36*Z36,0) -> 0 | M36: {=_xlfn.IFS(BOM!I36="RM-PACKING","100%",B36="Reynolds",VLOOKUP(H36,'Yield & Time'!A:V,22,0),BOM!B36="Dnata",VLOOKUP(BOM!H36,'Yield & Time'!A:M,13,0),B36="NK",VLOOKUP(H36,'Yield & Time'!A:X,24,0))} -> 100% | N36: =IFERROR(IF(I36="RM-FOOD",(E36*J36)/M36,1),0) -> 1 | O36: =VLOOKUP(H36,'RM Used'!A:E,5,0) -> Count | P36: =VLOOKUP(H36,'RM Used'!A:F,6,0) -> 0.09 | Q36: =P36*N36 -> 0.09 | R36: =IFERROR(IF(B36="Reynolds",VLOOKUP(H36,'Yield & Time'!A:U,21,0),VLOOKUP(H36,'Yield & Time'!A:L,12,0)),0) -> 0 | S36: =R36*J36*E36*AO$1 -> 0 | T36: =(R36*Z36*J36*E36)/60 -> 0 | U36: =IF(A35=A36,0,VLOOKUP(A36,'Packing Time'!A:F,6,0)) -> 0 | V36: =U36*AO$1 -> 0 | W36: =(U36*Z36)/60 -> 0 | X36: =((R36*J36*E36)+U36)*AO$1*AP36 -> 0 | Y36: =X36*Z36 -> 0 | Z36: 1 | AA36: =Z36*N36 -> 1 | AB36: =AA36*P36 -> 0.09 | AC36: =(((R36*J36*E36)+U36)/60)*Z36*AP36 -> 0 | AD36: =AC36*60*AO$1 -> 0 | AF36: =IFERROR(VLOOKUP(AE36,'Chemical Cost'!A:D,4,0),0) -> 0 | AG36: =AF36*N36/3 -> 0 | AH36: =AF36*AA36/3 -> 0 | AI36: =IFERROR((Q36*Z36)+(Z36*X36)+AH36,0) -> 0.09 | AJ36: =IFERROR(VLOOKUP(A36,'All Products'!A:F,6,0),0) -> 6.84 | AL36: 1 | AN36: #N/A | AP36: 1.6 | AQ36: =(((R36*J36*E36)+U36)/60)*AP36 -> 0 | AR36: =_xlfn.XLOOKUP(F36,'RM Cost'!A:A,'RM Cost'!S:S) -> 0 | AS36: =_xlfn.XLOOKUP(A36,[3]Sheet1!$B:$B,[3]Sheet1!$B:$B) -> #N/A
A37: 789ACS | B37: Reynolds | C37: STIR FRY VEG DL 1x1.5KG | D37: KG | E37: 1.5 | F37: =VLOOKUP(H37,'RM Used'!A:B,2,0) -> P0016 | G37: =IFERROR(VLOOKUP(F37,'RM Cost'!A:B,2,0),"") -> REY 40 30 BOX | H37: black box | I37: =VLOOKUP(F37,'RM Used'!B:D,3,0) -> RM-PACKING | J37: 1 | K37: =IF(I37="RM-FOOD",J37*E37,"") | L37: =IFERROR(K37*Z37,0) -> 0 | M37: {=_xlfn.IFS(BOM!I37="RM-PACKING","100%",B37="Reynolds",VLOOKUP(H37,'Yield & Time'!A:V,22,0),BOM!B37="Dnata",VLOOKUP(BOM!H37,'Yield & Time'!A:M,13,0),B37="NK",VLOOKUP(H37,'Yield & Time'!A:X,24,0))} -> 100% | N37: =IFERROR(IF(I37="RM-FOOD",(E37*J37)/M37,1),0) -> 1 | O37: =VLOOKUP(H37,'RM Used'!A:E,5,0) -> Count | P37: =VLOOKUP(H37,'RM Used'!A:F,6,0) -> 0.28 | Q37: =P37*N37 -> 0.28 | R37: =IFERROR(IF(B37="Reynolds",VLOOKUP(H37,'Yield & Time'!A:U,21,0),VLOOKUP(H37,'Yield & Time'!A:L,12,0)),0) -> 0 | S37: =R37*J37*E37*AO$1 -> 0 | T37: =(R37*Z37*J37*E37)/60 -> 0 | U37: =IF(A36=A37,0,VLOOKUP(A37,'Packing Time'!A:F,6,0)) -> 0 | V37: =U37*AO$1 -> 0 | W37: =(U37*Z37)/60 -> 0 | X37: =((R37*J37*E37)+U37)*AO$1*AP37 -> 0 | Y37: =X37*Z37 -> 0 | Z37: 1 | AA37: =Z37*N37 -> 1 | AB37: =AA37*P37 -> 0.28 | AC37: =(((R37*J37*E37)+U37)/60)*Z37*AP37 -> 0 | AD37: =AC37*60*AO$1 -> 0 | AF37: =IFERROR(VLOOKUP(AE37,'Chemical Cost'!A:D,4,0),0) -> 0 | AG37: =AF37*N37/3 -> 0 | AH37: =AF37*AA37/3 -> 0 | AI37: =IFERROR((Q37*Z37)+(Z37*X37)+AH37,0) -> 0.28 | AJ37: =IFERROR(VLOOKUP(A37,'All Products'!A:F,6,0),0) -> 6.84 | AL37: 1 | AN37: #N/A | AP37: 1.6 | AQ37: =(((R37*J37*E37)+U37)/60)*AP37 -> 0 | AR37: =_xlfn.XLOOKUP(F37,'RM Cost'!A:A,'RM Cost'!S:S) -> 0 | AS37: =_xlfn.XLOOKUP(A37,[3]Sheet1!$B:$B,[3]Sheet1!$B:$B) -> #N/A
A38: 1180CS | B38: Reynolds | C38: RED CABBAGE N CARROT SLAW 2X1K | D38: KG | E38: 2 | F38: =VLOOKUP(H38,'RM Used'!A:B,2,0) -> S3998CS | G38: =IFERROR(VLOOKUP(F38,'RM Cost'!A:B,2,0),"") -> RM - DECORED RED CABBAGE 1/3 1200KG | H38: Cabbage Red - Sliced | I38: =VLOOKUP(F38,'RM Used'!B:D,3,0) -> RM-FOOD | J38: 0.8 | K38: =IF(I38="RM-FOOD",J38*E38,"") -> 1.6 | L38: =IFERROR(K38*Z38,0) -> 1.6 | M38: {=_xlfn.IFS(BOM!I38="RM-PACKING","100%",B38="Reynolds",VLOOKUP(H38,'Yield & Time'!A:V,22,0),BOM!B38="Dnata",VLOOKUP(BOM!H38,'Yield & Time'!A:M,13,0),B38="NK",VLOOKUP(H38,'Yield & Time'!A:X,24,0))} -> 0.7008 | N38: =IFERROR(IF(I38="RM-FOOD",(E38*J38)/M38,1),0) -> 2.283105 | O38: =VLOOKUP(H38,'RM Used'!A:E,5,0) -> KG | P38: =VLOOKUP(H38,'RM Used'!A:F,6,0) -> 0.38 | Q38: =P38*N38 -> 0.86757991 | R38: =IFERROR(IF(B38="Reynolds",VLOOKUP(H38,'Yield & Time'!A:U,21,0),VLOOKUP(H38,'Yield & Time'!A:L,12,0)),0) -> 0.89425536 | S38: =R38*J38*E38*AO$1 -> 0.4843287 | T38: =(R38*Z38*J38*E38)/60 -> 0.02384681 | U38: =IF(A37=A38,0,VLOOKUP(A38,'Packing Time'!A:F,6,0)) -> 0.875 | V38: =U38*AO$1 -> 0.2961875 | W38: =(U38*Z38)/60 -> 0.014583333 | X38: =((R38*J38*E38)+U38)*AO$1*AP38 -> 0.85856782 | Y38: =X38*Z38 -> 0.85856782 | Z38: 1 | AA38: =Z38*N38 -> 2.283105 | AB38: =AA38*P38 -> 0.86757991 | AC38: =(((R38*J38*E38)+U38)/60)*Z38*AP38 -> 0.042273157 | AD38: =AC38*60*AO$1 -> 0.85856782 | AE38: =VLOOKUP(H38,'Yield & Time'!A:R,18,0) -> CHLORINE | AF38: =IFERROR(VLOOKUP(AE38,'Chemical Cost'!A:D,4,0),0) -> 0.027756518 | AG38: =AF38*N38/3 -> 0.021123682 | AH38: =AF38*AA38/3 -> 0.021123682 | AI38: =IFERROR((Q38*Z38)+(Z38*X38)+AH38,0) -> 1.7472714 | AJ38: =IFERROR(VLOOKUP(A38,'All Products'!A:F,6,0),0) -> 2.17 | AK38: =AJ38*Z38*J38 -> 1.736 | AL38: 0.8 | AM38: 0.2 | AN38: #N/A | AP38: 1.1 | AQ38: =(((R38*J38*E38)+U38)/60)*AP38 -> 0.042273157 | AR38: =_xlfn.XLOOKUP(F38,'RM Cost'!A:A,'RM Cost'!S:S) -> 0.29914854 | AS38: =_xlfn.XLOOKUP(A38,[3]Sheet1!$B:$B,[3]Sheet1!$B:$B) -> 1180CS | AT38: =_xlfn.XLOOKUP(H38,'Yield & Time'!A:A,'Yield & Time'!O:O) -> Yes
A39: 1180CS | B39: Reynolds | C39: RED CABBAGE N CARROT SLAW 2X1K | D39: KG | E39: 2 | F39: =VLOOKUP(H39,'RM Used'!A:B,2,0) -> 032ACS | G39: =IFERROR(VLOOKUP(F39,'RM Cost'!A:B,2,0),"") -> RM - LRG PROCESSING CARROT X 1000KG | H39: Carrot - Julienne | I39: =VLOOKUP(F39,'RM Used'!B:D,3,0) -> RM-FOOD | J39: 0.2 | K39: =IF(I39="RM-FOOD",J39*E39,"") -> 0.4 | L39: =IFERROR(K39*Z39,0) -> 0.4 | M39: {=_xlfn.IFS(BOM!I39="RM-PACKING","100%",B39="Reynolds",VLOOKUP(H39,'Yield & Time'!A:V,22,0),BOM!B39="Dnata",VLOOKUP(BOM!H39,'Yield & Time'!A:M,13,0),B39="NK",VLOOKUP(H39,'Yield & Time'!A:X,24,0))} -> 0.7533 | N39: =IFERROR(IF(I39="RM-FOOD",(E39*J39)/M39,1),0) -> 0.53099695 | O39: =VLOOKUP(H39,'RM Used'!A:E,5,0) -> KG | P39: =VLOOKUP(H39,'RM Used'!A:F,6,0) -> 0.38 | Q39: =P39*N39 -> 0.20177884 | R39: =IFERROR(IF(B39="Reynolds",VLOOKUP(H39,'Yield & Time'!A:U,21,0),VLOOKUP(H39,'Yield & Time'!A:L,12,0)),0) -> 0.90531915 | S39: =R39*J39*E39*AO$1 -> 0.12258021 | T39: =(R39*Z39*J39*E39)/60 -> 0.006035461 | U39: =IF(A38=A39,0,VLOOKUP(A39,'Packing Time'!A:F,6,0)) -> 0 | V39: =U39*AO$1 -> 0 | W39: =(U39*Z39)/60 -> 0 | X39: =((R39*J39*E39)+U39)*AO$1*AP39 -> 0.13483823 | Y39: =X39*Z39 -> 0.13483823 | Z39: 1 | AA39: =Z39*N39 -> 0.53099695 | AB39: =AA39*P39 -> 0.20177884 | AC39: =(((R39*J39*E39)+U39)/60)*Z39*AP39 -> 0.0066390071 | AD39: =AC39*60*AO$1 -> 0.13483823 | AE39: =VLOOKUP(H39,'Yield & Time'!A:R,18,0) -> CHLORINE | AF39: =IFERROR(VLOOKUP(AE39,'Chemical Cost'!A:D,4,0),0) -> 0.027756518 | AG39: =AF39*N39/3 -> 0.0049128754 | AH39: =AF39*AA39/3 -> 0.0049128754 | AI39: =IFERROR((Q39*Z39)+(Z39*X39)+AH39,0) -> 0.34152995 | AJ39: =IFERROR(VLOOKUP(A39,'All Products'!A:F,6,0),0) -> 2.17 | AK39: =AJ39*Z39*J39 -> 0.434 | AL39: 0.8 | AM39: 0.2 | AN39: #N/A | AP39: 1.1 | AQ39: =(((R39*J39*E39)+U39)/60)*AP39 -> 0.0066390071 | AR39: =_xlfn.XLOOKUP(F39,'RM Cost'!A:A,'RM Cost'!S:S) -> 0 | AS39: =_xlfn.XLOOKUP(A39,[3]Sheet1!$B:$B,[3]Sheet1!$B:$B) -> 1180CS | AT39: =_xlfn.XLOOKUP(H39,'Yield & Time'!A:A,'Yield & Time'!O:O) -> Yes
A40: 1180CS | B40: Reynolds | C40: RED CABBAGE N CARROT SLAW 2X1K | D40: KG | E40: 2 | F40: =VLOOKUP(H40,'RM Used'!A:B,2,0) -> P0001 | G40: =IFERROR(VLOOKUP(F40,'RM Cost'!A:B,2,0),"") -> SOL 30EL # PPLUS 630x1000 BLUE -1 | H40: SOL 30EL # PPLUS 630x1000 BLUE -1 | I40: =VLOOKUP(F40,'RM Used'!B:D,3,0) -> RM-PACKING | J40: 1 | K40: =IF(I40="RM-FOOD",J40*E40,"") | L40: =IFERROR(K40*Z40,0) -> 0 | M40: {=_xlfn.IFS(BOM!I40="RM-PACKING","100%",B40="Reynolds",VLOOKUP(H40,'Yield & Time'!A:V,22,0),BOM!B40="Dnata",VLOOKUP(BOM!H40,'Yield & Time'!A:M,13,0),B40="NK",VLOOKUP(H40,'Yield & Time'!A:X,24,0))} -> 100% | N40: 2 | O40: =VLOOKUP(H40,'RM Used'!A:E,5,0) -> Count | P40: =VLOOKUP(H40,'RM Used'!A:F,6,0) -> 0.08 | Q40: =P40*N40 -> 0.16 | R40: =IFERROR(IF(B40="Reynolds",VLOOKUP(H40,'Yield & Time'!A:U,21,0),VLOOKUP(H40,'Yield & Time'!A:L,12,0)),0) -> 0 | S40: =R40*J40*E40*AO$1 -> 0 | T40: =(R40*Z40*J40*E40)/60 -> 0 | U40: =IF(A39=A40,0,VLOOKUP(A40,'Packing Time'!A:F,6,0)) -> 0 | V40: =U40*AO$1 -> 0 | W40: =(U40*Z40)/60 -> 0 | X40: =((R40*J40*E40)+U40)*AO$1*AP40 -> 0 | Y40: =X40*Z40 -> 0 | Z40: 1 | AA40: =Z40*N40 -> 2 | AB40: =AA40*P40 -> 0.16 | AC40: =(((R40*J40*E40)+U40)/60)*Z40*AP40 -> 0 | AD40: =AC40*60*AO$1 -> 0 | AF40: =IFERROR(VLOOKUP(AE40,'Chemical Cost'!A:D,4,0),0) -> 0 | AG40: =AF40*N40/3 -> 0 | AH40: =AF40*AA40/3 -> 0 | AI40: =IFERROR((Q40*Z40)+(Z40*X40)+AH40,0) -> 0.16 | AJ40: =IFERROR(VLOOKUP(A40,'All Products'!A:F,6,0),0) -> 2.17 | AL40: 0.8 | AM40: 0.2 | AN40: #N/A | AP40: 1.1 | AQ40: =(((R40*J40*E40)+U40)/60)*AP40 -> 0 | AR40: =_xlfn.XLOOKUP(F40,'RM Cost'!A:A,'RM Cost'!S:S) -> 0 | AS40: =_xlfn.XLOOKUP(A40,[3]Sheet1!$B:$B,[3]Sheet1!$B:$B) -> 1180CS | AT40: =_xlfn.XLOOKUP(H40,'Yield & Time'!A:A,'Yield & Time'!F:F) -> #N/A
A41: 1180CS | B41: Reynolds | C41: RED CABBAGE N CARROT SLAW 2X1K | D41: KG | E41: 2 | F41: =VLOOKUP(H41,'RM Used'!A:B,2,0) -> P0016 | G41: =IFERROR(VLOOKUP(F41,'RM Cost'!A:B,2,0),"") -> REY 40 30 BOX | H41: black box | I41: =VLOOKUP(F41,'RM Used'!B:D,3,0) -> RM-PACKING | J41: 1 | K41: =IF(I41="RM-FOOD",J41*E41,"") | L41: =IFERROR(K41*Z41,0) -> 0 | M41: {=_xlfn.IFS(BOM!I41="RM-PACKING","100%",B41="Reynolds",VLOOKUP(H41,'Yield & Time'!A:V,22,0),BOM!B41="Dnata",VLOOKUP(BOM!H41,'Yield & Time'!A:M,13,0),B41="NK",VLOOKUP(H41,'Yield & Time'!A:X,24,0))} -> 100% | N41: =IFERROR(IF(I41="RM-FOOD",(E41*J41)/M41,1),0) -> 1 | O41: =VLOOKUP(H41,'RM Used'!A:E,5,0) -> Count | P41: =VLOOKUP(H41,'RM Used'!A:F,6,0) -> 0.28 | Q41: =P41*N41 -> 0.28 | R41: =IFERROR(IF(B41="Reynolds",VLOOKUP(H41,'Yield & Time'!A:U,21,0),VLOOKUP(H41,'Yield & Time'!A:L,12,0)),0) -> 0 | S41: =R41*J41*E41*AO$1 -> 0 | T41: =(R41*Z41*J41*E41)/60 -> 0 | U41: =IF(A40=A41,0,VLOOKUP(A41,'Packing Time'!A:F,6,0)) -> 0 | V41: =U41*AO$1 -> 0 | W41: =(U41*Z41)/60 -> 0 | X41: =((R41*J41*E41)+U41)*AO$1*AP41 -> 0 | Y41: =X41*Z41 -> 0 | Z41: 1 | AA41: =Z41*N41 -> 1 | AB41: =AA41*P41 -> 0.28 | AC41: =(((R41*J41*E41)+U41)/60)*Z41*AP41 -> 0 | AD41: =AC41*60*AO$1 -> 0 | AF41: =IFERROR(VLOOKUP(AE41,'Chemical Cost'!A:D,4,0),0) -> 0 | AG41: =AF41*N41/3 -> 0 | AH41: =AF41*AA41/3 -> 0 | AI41: =IFERROR((Q41*Z41)+(Z41*X41)+AH41,0) -> 0.28 | AJ41: =IFERROR(VLOOKUP(A41,'All Products'!A:F,6,0),0) -> 2.17 | AL41: 0.8 | AM41: 0.2 | AN41: #N/A | AP41: 1.1 | AQ41: =(((R41*J41*E41)+U41)/60)*AP41 -> 0 | AR41: =_xlfn.XLOOKUP(F41,'RM Cost'!A:A,'RM Cost'!S:S) -> 0 | AS41: =_xlfn.XLOOKUP(A41,[3]Sheet1!$B:$B,[3]Sheet1!$B:$B) -> 1180CS | AT41: =_xlfn.XLOOKUP(H41,'Yield & Time'!A:A,'Yield & Time'!F:F) -> #N/A
A42: 1174CS | B42: Reynolds | C42: PREP CARROTS GRATED 4 X 1KG | D42: KG | E42: 4 | F42: =VLOOKUP(H42,'RM Used'!A:B,2,0) -> 032ACS | G42: =IFERROR(VLOOKUP(F42,'RM Cost'!A:B,2,0),"") -> RM - LRG PROCESSING CARROT X 1000KG | H42: Carrot - Julienne | I42: =VLOOKUP(F42,'RM Used'!B:D,3,0) -> RM-FOOD | J42: 1 | K42: =IF(I42="RM-FOOD",J42*E42,"") -> 4 | L42: =IFERROR(K42*Z42,0) -> 4 | M42: {=_xlfn.IFS(BOM!I42="RM-PACKING","100%",B42="Reynolds",VLOOKUP(H42,'Yield & Time'!A:V,22,0),BOM!B42="Dnata",VLOOKUP(BOM!H42,'Yield & Time'!A:M,13,0),B42="NK",VLOOKUP(H42,'Yield & Time'!A:X,24,0))} -> 0.7533 | N42: =IFERROR(IF(I42="RM-FOOD",(E42*J42)/M42,1),0) -> 5.3099695 | O42: =VLOOKUP(H42,'RM Used'!A:E,5,0) -> KG | P42: =VLOOKUP(H42,'RM Used'!A:F,6,0) -> 0.38 | Q42: =P42*N42 -> 2.0177884 | R42: =IFERROR(IF(B42="Reynolds",VLOOKUP(H42,'Yield & Time'!A:U,21,0),VLOOKUP(H42,'Yield & Time'!A:L,12,0)),0) -> 0.90531915 | S42: =R42*J42*E42*AO$1 -> 1.2258021 | T42: =(R42*Z42*J42*E42)/60 -> 0.06035461 | U42: =IF(A41=A42,0,VLOOKUP(A42,'Packing Time'!A:F,6,0)) -> 1.75 | V42: =U42*AO$1 -> 0.592375 | W42: =(U42*Z42)/60 -> 0.029166667 | X42: =((R42*J42*E42)+U42)*AO$1*AP42 -> 1.9999948 | Y42: =X42*Z42 -> 1.9999948 | Z42: 1 | AA42: =Z42*N42 -> 5.3099695 | AB42: =AA42*P42 -> 2.0177884 | AC42: =(((R42*J42*E42)+U42)/60)*Z42*AP42 -> 0.098473404 | AD42: =AC42*60*AO$1 -> 1.9999948 | AE42: =VLOOKUP(H42,'Yield & Time'!A:R,18,0) -> CHLORINE | AF42: =IFERROR(VLOOKUP(AE42,'Chemical Cost'!A:D,4,0),0) -> 0.027756518 | AG42: =AF42*N42/3 -> 0.049128754 | AH42: =AF42*AA42/3 -> 0.049128754 | AI42: =IFERROR((Q42*Z42)+(Z42*X42)+AH42,0) -> 4.066912 | AJ42: =IFERROR(VLOOKUP(A42,'All Products'!A:F,6,0),0) -> 6.36 | AK42: =AJ42*Z42*J42 -> 6.36 | AM42: 1 | AN42: #N/A | AP42: 1.1 | AQ42: =(((R42*J42*E42)+U42)/60)*AP42 -> 0.098473404 | AR42: =_xlfn.XLOOKUP(F42,'RM Cost'!A:A,'RM Cost'!S:S) -> 0 | AS42: =_xlfn.XLOOKUP(A42,[3]Sheet1!$B:$B,[3]Sheet1!$B:$B) -> 1174CS | AT42: =_xlfn.XLOOKUP(H42,'Yield & Time'!A:A,'Yield & Time'!O:O) -> Yes
A43: 1174CS | B43: Reynolds | C43: PREP CARROTS GRATED 4 X 1KG | D43: KG | E43: 4 | F43: =VLOOKUP(H43,'RM Used'!A:B,2,0) -> P0002 | G43: =IFERROR(VLOOKUP(F43,'RM Cost'!A:B,2,0),"") -> SOL 30EL # PPLUS 630x1000 BLUE -4 | H43: SOL 30EL # PPLUS 630x1000 BLUE -4 | I43: =VLOOKUP(F43,'RM Used'!B:D,3,0) -> RM-PACKING | J43: 1 | K43: =IF(I43="RM-FOOD",J43*E43,"") | L43: =IFERROR(K43*Z43,0) -> 0 | M43: {=_xlfn.IFS(BOM!I43="RM-PACKING","100%",B43="Reynolds",VLOOKUP(H43,'Yield & Time'!A:V,22,0),BOM!B43="Dnata",VLOOKUP(BOM!H43,'Yield & Time'!A:M,13,0),B43="NK",VLOOKUP(H43,'Yield & Time'!A:X,24,0))} -> 100% | N43: =IFERROR(IF(I43="RM-FOOD",(E43*J43)/M43,1),0) -> 1 | O43: =VLOOKUP(H43,'RM Used'!A:E,5,0) -> Count | P43: =VLOOKUP(H43,'RM Used'!A:F,6,0) -> 0.32 | Q43: =P43*N43 -> 0.32 | R43: =IFERROR(IF(B43="Reynolds",VLOOKUP(H43,'Yield & Time'!A:U,21,0),VLOOKUP(H43,'Yield & Time'!A:L,12,0)),0) -> 0 | S43: =R43*J43*E43*AO$1 -> 0 | T43: =(R43*Z43*J43*E43)/60 -> 0 | U43: =IF(A42=A43,0,VLOOKUP(A43,'Packing Time'!A:F,6,0)) -> 0 | V43: =U43*AO$1 -> 0 | W43: =(U43*Z43)/60 -> 0 | X43: =((R43*J43*E43)+U43)*AO$1*AP43 -> 0 | Y43: =X43*Z43 -> 0 | Z43: 1 | AA43: =Z43*N43 -> 1 | AB43: =AA43*P43 -> 0.32 | AC43: =(((R43*J43*E43)+U43)/60)*Z43*AP43 -> 0 | AD43: =AC43*60*AO$1 -> 0 | AF43: =IFERROR(VLOOKUP(AE43,'Chemical Cost'!A:D,4,0),0) -> 0 | AG43: =AF43*N43/3 -> 0 | AH43: =AF43*AA43/3 -> 0 | AI43: =IFERROR((Q43*Z43)+(Z43*X43)+AH43,0) -> 0.32 | AJ43: =IFERROR(VLOOKUP(A43,'All Products'!A:F,6,0),0) -> 6.36 | AM43: 1 | AN43: #N/A | AP43: 1.1 | AQ43: =(((R43*J43*E43)+U43)/60)*AP43 -> 0 | AR43: =_xlfn.XLOOKUP(F43,'RM Cost'!A:A,'RM Cost'!S:S) -> 0 | AS43: =_xlfn.XLOOKUP(A43,[3]Sheet1!$B:$B,[3]Sheet1!$B:$B) -> 1174CS | AT43: =_xlfn.XLOOKUP(H43,'Yield & Time'!A:A,'Yield & Time'!F:F) -> #N/A
A44: 1174CS | B44: Reynolds | C44: PREP CARROTS GRATED 4 X 1KG | D44: KG | E44: 4 | F44: =VLOOKUP(H44,'RM Used'!A:B,2,0) -> P0016 | G44: =IFERROR(VLOOKUP(F44,'RM Cost'!A:B,2,0),"") -> REY 40 30 BOX | H44: black box | I44: =VLOOKUP(F44,'RM Used'!B:D,3,0) -> RM-PACKING | J44: 1 | K44: =IF(I44="RM-FOOD",J44*E44,"") | L44: =IFERROR(K44*Z44,0) -> 0 | M44: {=_xlfn.IFS(BOM!I44="RM-PACKING","100%",B44="Reynolds",VLOOKUP(H44,'Yield & Time'!A:V,22,0),BOM!B44="Dnata",VLOOKUP(BOM!H44,'Yield & Time'!A:M,13,0),B44="NK",VLOOKUP(H44,'Yield & Time'!A:X,24,0))} -> 100% | N44: =IFERROR(IF(I44="RM-FOOD",(E44*J44)/M44,1),0) -> 1 | O44: =VLOOKUP(H44,'RM Used'!A:E,5,0) -> Count | P44: =VLOOKUP(H44,'RM Used'!A:F,6,0) -> 0.28 | Q44: =P44*N44 -> 0.28 | R44: =IFERROR(IF(B44="Reynolds",VLOOKUP(H44,'Yield & Time'!A:U,21,0),VLOOKUP(H44,'Yield & Time'!A:L,12,0)),0) -> 0 | S44: =R44*J44*E44*AO$1 -> 0 | T44: =(R44*Z44*J44*E44)/60 -> 0 | U44: =IF(A43=A44,0,VLOOKUP(A44,'Packing Time'!A:F,6,0)) -> 0 | V44: =U44*AO$1 -> 0 | W44: =(U44*Z44)/60 -> 0 | X44: =((R44*J44*E44)+U44)*AO$1*AP44 -> 0 | Y44: =X44*Z44 -> 0 | Z44: 1 | AA44: =Z44*N44 -> 1 | AB44: =AA44*P44 -> 0.28 | AC44: =(((R44*J44*E44)+U44)/60)*Z44*AP44 -> 0 | AD44: =AC44*60*AO$1 -> 0 | AF44: =IFERROR(VLOOKUP(AE44,'Chemical Cost'!A:D,4,0),0) -> 0 | AG44: =AF44*N44/3 -> 0 | AH44: =AF44*AA44/3 -> 0 | AI44: =IFERROR((Q44*Z44)+(Z44*X44)+AH44,0) -> 0.28 | AJ44: =IFERROR(VLOOKUP(A44,'All Products'!A:F,6,0),0) -> 6.36 | AM44: 1 | AN44: #N/A | AP44: 1.1 | AQ44: =(((R44*J44*E44)+U44)/60)*AP44 -> 0 | AR44: =_xlfn.XLOOKUP(F44,'RM Cost'!A:A,'RM Cost'!S:S) -> 0 | AS44: =_xlfn.XLOOKUP(A44,[3]Sheet1!$B:$B,[3]Sheet1!$B:$B) -> 1174CS | AT44: =_xlfn.XLOOKUP(H44,'Yield & Time'!A:A,'Yield & Time'!F:F) -> #N/A
A45: 502ACS | B45: Reynolds | C45: NHS PREP STEW PACK 2.5KG | D45: KG | E45: 2.5 | F45: =VLOOKUP(H45,'RM Used'!A:B,2,0) -> 032ACS | G45: =IFERROR(VLOOKUP(F45,'RM Cost'!A:B,2,0),"") -> RM - LRG PROCESSING CARROT X 1000KG | H45: Carrot - Peeled & Diced 25mm | I45: =VLOOKUP(F45,'RM Used'!B:D,3,0) -> RM-FOOD | J45: 0.25 | K45: =IF(I45="RM-FOOD",J45*E45,"") -> 0.625 | L45: =IFERROR(K45*Z45,0) -> 0.625 | M45: {=_xlfn.IFS(BOM!I45="RM-PACKING","100%",B45="Reynolds",VLOOKUP(H45,'Yield & Time'!A:V,22,0),BOM!B45="Dnata",VLOOKUP(BOM!H45,'Yield & Time'!A:M,13,0),B45="NK",VLOOKUP(H45,'Yield & Time'!A:X,24,0))} -> 0.71506674 | N45: =IFERROR(IF(I45="RM-FOOD",(E45*J45)/M45,1),0) -> 0.87404429 | O45: =VLOOKUP(H45,'RM Used'!A:E,5,0) -> KG | P45: =VLOOKUP(H45,'RM Used'!A:F,6,0) -> 0.38 | Q45: =P45*N45 -> 0.33213683 | R45: =IFERROR(IF(B45="Reynolds",VLOOKUP(H45,'Yield & Time'!A:U,21,0),VLOOKUP(H45,'Yield & Time'!A:L,12,0)),0) -> 1.2475449 | S45: =R45*J45*E45*AO$1 -> 0.26393372 | T45: =(R45*Z45*J45*E45)/60 -> 0.01299526 | U45: =IF(A44=A45,0,VLOOKUP(A45,'Packing Time'!A:F,6,0)) -> 0.875 | V45: =U45*AO$1 -> 0.2961875 | W45: =(U45*Z45)/60 -> 0.014583333 | X45: =((R45*J45*E45)+U45)*AO$1*AP45 -> 0.89619396 | Y45: =X45*Z45 -> 0.89619396 | Z45: 1 | AA45: =Z45*N45 -> 0.87404429 | AB45: =AA45*P45 -> 0.33213683 | AC45: =(((R45*J45*E45)+U45)/60)*Z45*AP45 -> 0.044125749 | AD45: =AC45*60*AO$1 -> 0.89619396 | AF45: =IFERROR(VLOOKUP(AE45,'Chemical Cost'!A:D,4,0),0) -> 0 | AG45: =AF45*N45/3 -> 0 | AH45: =AF45*AA45/3 -> 0 | AI45: =IFERROR((Q45*Z45)+(Z45*X45)+AH45,0) -> 1.2283308 | AJ45: =IFERROR(VLOOKUP(A45,'All Products'!A:F,6,0),0) -> 8.09 | AK45: =AJ45*Z45*J45 -> 2.0225 | AL45: 1 | AN45: #N/A | AP45: 1.6 | AQ45: =(((R45*J45*E45)+U45)/60)*AP45 -> 0.044125749 | AR45: =_xlfn.XLOOKUP(F45,'RM Cost'!A:A,'RM Cost'!S:S) -> 0 | AS45: =_xlfn.XLOOKUP(A45,[3]Sheet1!$B:$B,[3]Sheet1!$B:$B) -> #N/A
A46: 502ACS | B46: Reynolds | C46: NHS PREP STEW PACK 2.5KG | D46: KG | E46: 2.5 | F46: =VLOOKUP(H46,'RM Used'!A:B,2,0) -> 3277CS | G46: =IFERROR(VLOOKUP(F46,'RM Cost'!A:B,2,0),"") -> RM - SWEDE 12.5KG | H46: Swede - Diced 25MM | I46: =VLOOKUP(F46,'RM Used'!B:D,3,0) -> RM-FOOD | J46: 0.25 | K46: =IF(I46="RM-FOOD",J46*E46,"") -> 0.625 | L46: =IFERROR(K46*Z46,0) -> 0.625 | M46: {=_xlfn.IFS(BOM!I46="RM-PACKING","100%",B46="Reynolds",VLOOKUP(H46,'Yield & Time'!A:V,22,0),BOM!B46="Dnata",VLOOKUP(BOM!H46,'Yield & Time'!A:M,13,0),B46="NK",VLOOKUP(H46,'Yield & Time'!A:X,24,0))} -> 0.82357724 | N46: =IFERROR(IF(I46="RM-FOOD",(E46*J46)/M46,1),0) -> 0.7588845 | O46: =VLOOKUP(H46,'RM Used'!A:E,5,0) -> KG | P46: =VLOOKUP(H46,'RM Used'!A:F,6,0) -> 0.52 | Q46: =P46*N46 -> 0.39461994 | R46: =IFERROR(IF(B46="Reynolds",VLOOKUP(H46,'Yield & Time'!A:U,21,0),VLOOKUP(H46,'Yield & Time'!A:L,12,0)),0) -> 1.9442895 | S46: =R46*J46*E46*AO$1 -> 0.41133874 | T46: =(R46*Z46*J46*E46)/60 -> 0.020253015 | U46: =IF(A45=A46,0,VLOOKUP(A46,'Packing Time'!A:F,6,0)) -> 0 | V46: =U46*AO$1 -> 0 | W46: =(U46*Z46)/60 -> 0 | X46: =((R46*J46*E46)+U46)*AO$1*AP46 -> 0.65814198 | Y46: =X46*Z46 -> 0.65814198 | Z46: 1 | AA46: =Z46*N46 -> 0.7588845 | AB46: =AA46*P46 -> 0.39461994 | AC46: =(((R46*J46*E46)+U46)/60)*Z46*AP46 -> 0.032404824 | AD46: =AC46*60*AO$1 -> 0.65814198 | AF46: =IFERROR(VLOOKUP(AE46,'Chemical Cost'!A:D,4,0),0) -> 0 | AG46: =AF46*N46/3 -> 0 | AH46: =AF46*AA46/3 -> 0 | AI46: =IFERROR((Q46*Z46)+(Z46*X46)+AH46,0) -> 1.0527619 | AJ46: =IFERROR(VLOOKUP(A46,'All Products'!A:F,6,0),0) -> 8.09 | AK46: =AJ46*Z46*J46 -> 2.0225 | AL46: 1 | AN46: #N/A | AP46: 1.6 | AQ46: =(((R46*J46*E46)+U46)/60)*AP46 -> 0.032404824 | AR46: =_xlfn.XLOOKUP(F46,'RM Cost'!A:A,'RM Cost'!S:S) -> 0 | AS46: =_xlfn.XLOOKUP(A46,[3]Sheet1!$B:$B,[3]Sheet1!$B:$B) -> #N/A
A47: 502ACS | B47: Reynolds | C47: NHS PREP STEW PACK 2.5KG | D47: KG | E47: 2.5 | F47: =VLOOKUP(H47,'RM Used'!A:B,2,0) -> 3288CS | G47: =IFERROR(VLOOKUP(F47,'RM Cost'!A:B,2,0),"") -> RM - TURNIPS X5KG | H47: Turnip - Diced 25MM | I47: =VLOOKUP(F47,'RM Used'!B:D,3,0) -> RM-FOOD | J47: 0.25 | K47: =IF(I47="RM-FOOD",J47*E47,"") -> 0.625 | L47: =IFERROR(K47*Z47,0) -> 0.625 | M47: {=_xlfn.IFS(BOM!I47="RM-PACKING","100%",B47="Reynolds",VLOOKUP(H47,'Yield & Time'!A:V,22,0),BOM!B47="Dnata",VLOOKUP(BOM!H47,'Yield & Time'!A:M,13,0),B47="NK",VLOOKUP(H47,'Yield & Time'!A:X,24,0))} -> 0.7629542 | N47: =IFERROR(IF(I47="RM-FOOD",(E47*J47)/M47,1),0) -> 0.81918416 | O47: =VLOOKUP(H47,'RM Used'!A:E,5,0) -> KG | P47: =VLOOKUP(H47,'RM Used'!A:F,6,0) -> 0.68 | Q47: =P47*N47 -> 0.55704523 | R47: =IFERROR(IF(B47="Reynolds",VLOOKUP(H47,'Yield & Time'!A:U,21,0),VLOOKUP(H47,'Yield & Time'!A:L,12,0)),0) -> 2.3746748 | S47: =R47*J47*E47*AO$1 -> 0.50239214 | T47: =(R47*Z47*J47*E47)/60 -> 0.024736196 | U47: =IF(A46=A47,0,VLOOKUP(A47,'Packing Time'!A:F,6,0)) -> 0 | V47: =U47*AO$1 -> 0 | W47: =(U47*Z47)/60 -> 0 | X47: =((R47*J47*E47)+U47)*AO$1*AP47 -> 0.80382742 | Y47: =X47*Z47 -> 0.80382742 | Z47: 1 | AA47: =Z47*N47 -> 0.81918416 | AB47: =AA47*P47 -> 0.55704523 | AC47: =(((R47*J47*E47)+U47)/60)*Z47*AP47 -> 0.039577913 | AD47: =AC47*60*AO$1 -> 0.80382742 | AF47: =IFERROR(VLOOKUP(AE47,'Chemical Cost'!A:D,4,0),0) -> 0 | AG47: =AF47*N47/3 -> 0 | AH47: =AF47*AA47/3 -> 0 | AI47: =IFERROR((Q47*Z47)+(Z47*X47)+AH47,0) -> 1.3608726 | AJ47: =IFERROR(VLOOKUP(A47,'All Products'!A:F,6,0),0) -> 8.09 | AK47: =AJ47*Z47*J47 -> 2.0225 | AL47: 1 | AN47: #N/A | AP47: 1.6 | AQ47: =(((R47*J47*E47)+U47)/60)*AP47 -> 0.039577913 | AR47: =_xlfn.XLOOKUP(F47,'RM Cost'!A:A,'RM Cost'!S:S) -> 0 | AS47: =_xlfn.XLOOKUP(A47,[3]Sheet1!$B:$B,[3]Sheet1!$B:$B) -> #N/A
A48: 502ACS | B48: Reynolds | C48: NHS PREP STEW PACK 2.5KG | D48: KG | E48: 2.5 | F48: =VLOOKUP(H48,'RM Used'!A:B,2,0) -> 3191CS | G48: =IFERROR(VLOOKUP(F48,'RM Cost'!A:B,2,0),"") -> RM - PARSNIPS 10KG | H48: Parsnip - Diced 25MM | I48: =VLOOKUP(F48,'RM Used'!B:D,3,0) -> RM-FOOD | J48: 0.25 | K48: =IF(I48="RM-FOOD",J48*E48,"") -> 0.625 | L48: =IFERROR(K48*Z48,0) -> 0.625 | M48: {=_xlfn.IFS(BOM!I48="RM-PACKING","100%",B48="Reynolds",VLOOKUP(H48,'Yield & Time'!A:V,22,0),BOM!B48="Dnata",VLOOKUP(BOM!H48,'Yield & Time'!A:M,13,0),B48="NK",VLOOKUP(H48,'Yield & Time'!A:X,24,0))} -> 0.55242718 | N48: =IFERROR(IF(I48="RM-FOOD",(E48*J48)/M48,1),0) -> 1.1313708 | O48: =VLOOKUP(H48,'RM Used'!A:E,5,0) -> KG | P48: =VLOOKUP(H48,'RM Used'!A:F,6,0) -> 0.76 | Q48: =P48*N48 -> 0.85984183 | R48: =IFERROR(IF(B48="Reynolds",VLOOKUP(H48,'Yield & Time'!A:U,21,0),VLOOKUP(H48,'Yield & Time'!A:L,12,0)),0) -> 7.7801406 | S48: =R48*J48*E48*AO$1 -> 1.645986 | T48: =(R48*Z48*J48*E48)/60 -> 0.081043131 | U48: =IF(A47=A48,0,VLOOKUP(A48,'Packing Time'!A:F,6,0)) -> 0 | V48: =U48*AO$1 -> 0 | W48: =(U48*Z48)/60 -> 0 | X48: =((R48*J48*E48)+U48)*AO$1*AP48 -> 2.6335776 | Y48: =X48*Z48 -> 2.6335776 | Z48: 1 | AA48: =Z48*N48 -> 1.1313708 | AB48: =AA48*P48 -> 0.85984183 | AC48: =(((R48*J48*E48)+U48)/60)*Z48*AP48 -> 0.12966901 | AD48: =AC48*60*AO$1 -> 2.6335776 | AE48: =VLOOKUP(H48,'Yield & Time'!A:R,18,0) -> SODIUM METABISULPHITE | AF48: =IFERROR(VLOOKUP(AE48,'Chemical Cost'!A:D,4,0),0) -> 0.0097586225 | AG48: =AF48*N48/3 -> 0.003680207 | AH48: =AF48*AA48/3 -> 0.003680207 | AI48: =IFERROR((Q48*Z48)+(Z48*X48)+AH48,0) -> 3.4970996 | AJ48: =IFERROR(VLOOKUP(A48,'All Products'!A:F,6,0),0) -> 8.09 | AK48: =AJ48*Z48*J48 -> 2.0225 | AL48: 1 | AN48: #N/A | AP48: 1.6 | AQ48: =(((R48*J48*E48)+U48)/60)*AP48 -> 0.12966901 | AR48: =_xlfn.XLOOKUP(F48,'RM Cost'!A:A,'RM Cost'!S:S) -> 0 | AS48: =_xlfn.XLOOKUP(A48,[3]Sheet1!$B:$B,[3]Sheet1!$B:$B) -> #N/A
A49: 502ACS | B49: Reynolds | C49: NHS PREP STEW PACK 2.5KG | D49: KG | E49: 2.5 | F49: =VLOOKUP(H49,'RM Used'!A:B,2,0) -> P0020 | G49: =IFERROR(VLOOKUP(F49,'RM Cost'!A:B,2,0),"") -> PALE BLUE BAG 430X430MM | H49: BLUE TINT BAGS ON A ROLL - SMALL | I49: =VLOOKUP(F49,'RM Used'!B:D,3,0) -> RM-PACKING | J49: 1 | K49: =IF(I49="RM-FOOD",J49*E49,"") | L49: =IFERROR(K49*Z49,0) -> 0 | M49: {=_xlfn.IFS(BOM!I49="RM-PACKING","100%",B49="Reynolds",VLOOKUP(H49,'Yield & Time'!A:V,22,0),BOM!B49="Dnata",VLOOKUP(BOM!H49,'Yield & Time'!A:M,13,0),B49="NK",VLOOKUP(H49,'Yield & Time'!A:X,24,0))} -> 100% | N49: =IFERROR(IF(I49="RM-FOOD",(E49*J49)/M49,1),0) -> 1 | O49: =VLOOKUP(H49,'RM Used'!A:E,5,0) -> Count | P49: =VLOOKUP(H49,'RM Used'!A:F,6,0) -> 0.09 | Q49: =P49*N49 -> 0.09 | R49: =IFERROR(IF(B49="Reynolds",VLOOKUP(H49,'Yield & Time'!A:U,21,0),VLOOKUP(H49,'Yield & Time'!A:L,12,0)),0) -> 0 | S49: =R49*J49*E49*AO$1 -> 0 | T49: =(R49*Z49*J49*E49)/60 -> 0 | U49: =IF(A48=A49,0,VLOOKUP(A49,'Packing Time'!A:F,6,0)) -> 0 | V49: =U49*AO$1 -> 0 | W49: =(U49*Z49)/60 -> 0 | X49: =((R49*J49*E49)+U49)*AO$1*AP49 -> 0 | Y49: =X49*Z49 -> 0 | Z49: 1 | AA49: =Z49*N49 -> 1 | AB49: =AA49*P49 -> 0.09 | AC49: =(((R49*J49*E49)+U49)/60)*Z49*AP49 -> 0 | AD49: =AC49*60*AO$1 -> 0 | AF49: =IFERROR(VLOOKUP(AE49,'Chemical Cost'!A:D,4,0),0) -> 0 | AG49: =AF49*N49/3 -> 0 | AH49: =AF49*AA49/3 -> 0 | AI49: =IFERROR((Q49*Z49)+(Z49*X49)+AH49,0) -> 0.09 | AJ49: =IFERROR(VLOOKUP(A49,'All Products'!A:F,6,0),0) -> 8.09 | AL49: 1 | AN49: #N/A | AP49: 1.6 | AQ49: =(((R49*J49*E49)+U49)/60)*AP49 -> 0 | AR49: =_xlfn.XLOOKUP(F49,'RM Cost'!A:A,'RM Cost'!S:S) -> 0 | AS49: =_xlfn.XLOOKUP(A49,[3]Sheet1!$B:$B,[3]Sheet1!$B:$B) -> #N/A
A50: 502ACS | B50: Reynolds | C50: NHS PREP STEW PACK 2.5KG | D50: KG | E50: 2.5 | F50: =VLOOKUP(H50,'RM Used'!A:B,2,0) -> P0016 | G50: =IFERROR(VLOOKUP(F50,'RM Cost'!A:B,2,0),"") -> REY 40 30 BOX | H50: black box | I50: =VLOOKUP(F50,'RM Used'!B:D,3,0) -> RM-PACKING | J50: 1 | K50: =IF(I50="RM-FOOD",J50*E50,"") | L50: =IFERROR(K50*Z50,0) -> 0 | M50: {=_xlfn.IFS(BOM!I50="RM-PACKING","100%",B50="Reynolds",VLOOKUP(H50,'Yield & Time'!A:V,22,0),BOM!B50="Dnata",VLOOKUP(BOM!H50,'Yield & Time'!A:M,13,0),B50="NK",VLOOKUP(H50,'Yield & Time'!A:X,24,0))} -> 100% | N50: =IFERROR(IF(I50="RM-FOOD",(E50*J50)/M50,1),0) -> 1 | O50: =VLOOKUP(H50,'RM Used'!A:E,5,0) -> Count | P50: =VLOOKUP(H50,'RM Used'!A:F,6,0) -> 0.28 | Q50: =P50*N50 -> 0.28 | R50: =IFERROR(IF(B50="Reynolds",VLOOKUP(H50,'Yield & Time'!A:U,21,0),VLOOKUP(H50,'Yield & Time'!A:L,12,0)),0) -> 0 | S50: =R50*J50*E50*AO$1 -> 0 | T50: =(R50*Z50*J50*E50)/60 -> 0 | U50: =IF(A49=A50,0,VLOOKUP(A50,'Packing Time'!A:F,6,0)) -> 0 | V50: =U50*AO$1 -> 0 | W50: =(U50*Z50)/60 -> 0 | X50: =((R50*J50*E50)+U50)*AO$1*AP50 -> 0 | Y50: =X50*Z50 -> 0 | Z50: 1 | AA50: =Z50*N50 -> 1 | AB50: =AA50*P50 -> 0.28 | AC50: =(((R50*J50*E50)+U50)/60)*Z50*AP50 -> 0 | AD50: =AC50*60*AO$1 -> 0 | AF50: =IFERROR(VLOOKUP(AE50,'Chemical Cost'!A:D,4,0),0) -> 0 | AG50: =AF50*N50/3 -> 0 | AH50: =AF50*AA50/3 -> 0 | AI50: =IFERROR((Q50*Z50)+(Z50*X50)+AH50,0) -> 0.28 | AJ50: =IFERROR(VLOOKUP(A50,'All Products'!A:F,6,0),0) -> 8.09 | AL50: 1 | AN50: #N/A | AP50: 1.6 | AQ50: =(((R50*J50*E50)+U50)/60)*AP50 -> 0 | AR50: =_xlfn.XLOOKUP(F50,'RM Cost'!A:A,'RM Cost'!S:S) -> 0 | AS50: =_xlfn.XLOOKUP(A50,[3]Sheet1!$B:$B,[3]Sheet1!$B:$B) -> #N/A
A51: 730ACS | B51: Reynolds | C51: CARROT MOOLI CHAYOTE MIX 1x2KG | D51: KG | E51: 2 | F51: =VLOOKUP(H51,'RM Used'!A:B,2,0) -> 3450CS | G51: =IFERROR(VLOOKUP(F51,'RM Cost'!A:B,2,0),"") -> CHAYOTE (CHOW CHOW) AVE X25 | H51: Chayote - Shredded | I51: =VLOOKUP(F51,'RM Used'!B:D,3,0) -> RM-FOOD | J51: 0.33 | K51: =IF(I51="RM-FOOD",J51*E51,"") -> 0.66 | L51: =IFERROR(K51*Z51,0) -> 0.66 | M51: {=_xlfn.IFS(BOM!I51="RM-PACKING","100%",B51="Reynolds",VLOOKUP(H51,'Yield & Time'!A:V,22,0),BOM!B51="Dnata",VLOOKUP(BOM!H51,'Yield & Time'!A:M,13,0),B51="NK",VLOOKUP(H51,'Yield & Time'!A:X,24,0))} -> 0.741 | N51: =IFERROR(IF(I51="RM-FOOD",(E51*J51)/M51,1),0) -> 0.89068826 | O51: =VLOOKUP(H51,'RM Used'!A:E,5,0) -> KG | P51: =VLOOKUP(H51,'RM Used'!A:F,6,0) -> 2.32 | Q51: =P51*N51 -> 2.0663968 | R51: =IFERROR(IF(B51="Reynolds",VLOOKUP(H51,'Yield & Time'!A:U,21,0),VLOOKUP(H51,'Yield & Time'!A:L,12,0)),0) -> 8.8606838 | S51: =R51*J51*E51*AO$1 -> 1.9795654 | T51: =(R51*Z51*J51*E51)/60 -> 0.097467521 | U51: =IF(A50=A51,0,VLOOKUP(A51,'Packing Time'!A:F,6,0)) -> 1.44 | V51: =U51*AO$1 -> 0.48744 | W51: =(U51*Z51)/60 -> 0.024 | X51: =((R51*J51*E51)+U51)*AO$1*AP51 -> 3.9472086 | Y51: =X51*Z51 -> 3.9472086 | Z51: 1 | AA51: =Z51*N51 -> 0.89068826 | AB51: =AA51*P51 -> 2.0663968 | AC51: =(((R51*J51*E51)+U51)/60)*Z51*AP51 -> 0.19434803 | AD51: =AC51*60*AO$1 -> 3.9472086 | AE51: =VLOOKUP(H51,'Yield & Time'!A:R,18,0) -> CHLORINE | AF51: =IFERROR(VLOOKUP(AE51,'Chemical Cost'!A:D,4,0),0) -> 0.027756518 | AG51: =AF51*N51/3 -> 0.0082408016 | AH51: =AF51*AA51/3 -> 0.0082408016 | AI51: =IFERROR((Q51*Z51)+(Z51*X51)+AH51,0) -> 6.0218461 | AJ51: =IFERROR(VLOOKUP(A51,'All Products'!A:F,6,0),0) -> 6.22 | AK51: =AJ51*Z51*J51 -> 2.0526 | AL51: 0.5 | AM51: 0.5 | AN51: #N/A | AP51: 1.6 | AQ51: =(((R51*J51*E51)+U51)/60)*AP51 -> 0.19434803 | AR51: =_xlfn.XLOOKUP(F51,'RM Cost'!A:A,'RM Cost'!S:S) -> 0 | AS51: =_xlfn.XLOOKUP(A51,[3]Sheet1!$B:$B,[3]Sheet1!$B:$B) -> #N/A
A52: 730ACS | B52: Reynolds | C52: CARROT MOOLI CHAYOTE MIX 1x2KG | D52: KG | E52: 2 | F52: =VLOOKUP(H52,'RM Used'!A:B,2,0) -> 3342CS | G52: =IFERROR(VLOOKUP(F52,'RM Cost'!A:B,2,0),"") -> RM - ORI MOOLI X 15 EA | H52: Mooli - shredded | I52: =VLOOKUP(F52,'RM Used'!B:D,3,0) -> RM-FOOD | J52: 0.33 | K52: =IF(I52="RM-FOOD",J52*E52,"") -> 0.66 | L52: =IFERROR(K52*Z52,0) -> 0.66 | M52: {=_xlfn.IFS(BOM!I52="RM-PACKING","100%",B52="Reynolds",VLOOKUP(H52,'Yield & Time'!A:V,22,0),BOM!B52="Dnata",VLOOKUP(BOM!H52,'Yield & Time'!A:M,13,0),B52="NK",VLOOKUP(H52,'Yield & Time'!A:X,24,0))} -> 0.77616 | N52: =IFERROR(IF(I52="RM-FOOD",(E52*J52)/M52,1),0) -> 0.85034014 | O52: =VLOOKUP(H52,'RM Used'!A:E,5,0) -> KG | P52: =VLOOKUP(H52,'RM Used'!A:F,6,0) -> 1.23 | Q52: =P52*N52 -> 1.0459184 | R52: =IFERROR(IF(B52="Reynolds",VLOOKUP(H52,'Yield & Time'!A:U,21,0),VLOOKUP(H52,'Yield & Time'!A:L,12,0)),0) -> 1.4605442 | S52: =R52*J52*E52*AO$1 -> 0.32630018 | T52: =(R52*Z52*J52*E52)/60 -> 0.016065986 | U52: =IF(A51=A52,0,VLOOKUP(A52,'Packing Time'!A:F,6,0)) -> 0 | V52: =U52*AO$1 -> 0 | W52: =(U52*Z52)/60 -> 0 | X52: =((R52*J52*E52)+U52)*AO$1*AP52 -> 0.52208029 | Y52: =X52*Z52 -> 0.52208029 | Z52: 1 | AA52: =Z52*N52 -> 0.85034014 | AB52: =AA52*P52 -> 1.0459184 | AC52: =(((R52*J52*E52)+U52)/60)*Z52*AP52 -> 0.025705578 | AD52: =AC52*60*AO$1 -> 0.52208029 | AE52: =VLOOKUP(H52,'Yield & Time'!A:R,18,0) -> CHLORINE | AF52: =IFERROR(VLOOKUP(AE52,'Chemical Cost'!A:D,4,0),0) -> 0.027756518 | AG52: =AF52*N52/3 -> 0.0078674938 | AH52: =AF52*AA52/3 -> 0.0078674938 | AI52: =IFERROR((Q52*Z52)+(Z52*X52)+AH52,0) -> 1.5758662 | AJ52: =IFERROR(VLOOKUP(A52,'All Products'!A:F,6,0),0) -> 6.22 | AK52: =AJ52*Z52*J52 -> 2.0526 | AL52: 0.5 | AM52: 0.5 | AN52: #N/A | AP52: 1.6 | AQ52: =(((R52*J52*E52)+U52)/60)*AP52 -> 0.025705578 | AR52: =_xlfn.XLOOKUP(F52,'RM Cost'!A:A,'RM Cost'!S:S) -> 0 | AS52: =_xlfn.XLOOKUP(A52,[3]Sheet1!$B:$B,[3]Sheet1!$B:$B) -> #N/A
A53: 730ACS | B53: Reynolds | C53: CARROT MOOLI CHAYOTE MIX 1x2KG | D53: KG | E53: 2 | F53: =VLOOKUP(H53,'RM Used'!A:B,2,0) -> 032ACS | G53: =IFERROR(VLOOKUP(F53,'RM Cost'!A:B,2,0),"") -> RM - LRG PROCESSING CARROT X 1000KG | H53: Carrot - Julienne | I53: =VLOOKUP(F53,'RM Used'!B:D,3,0) -> RM-FOOD | J53: 0.33 | K53: =IF(I53="RM-FOOD",J53*E53,"") -> 0.66 | L53: =IFERROR(K53*Z53,0) -> 0.66 | M53: {=_xlfn.IFS(BOM!I53="RM-PACKING","100%",B53="Reynolds",VLOOKUP(H53,'Yield & Time'!A:V,22,0),BOM!B53="Dnata",VLOOKUP(BOM!H53,'Yield & Time'!A:M,13,0),B53="NK",VLOOKUP(H53,'Yield & Time'!A:X,24,0))} -> 0.7533 | N53: =IFERROR(IF(I53="RM-FOOD",(E53*J53)/M53,1),0) -> 0.87614496 | O53: =VLOOKUP(H53,'RM Used'!A:E,5,0) -> KG | P53: =VLOOKUP(H53,'RM Used'!A:F,6,0) -> 0.38 | Q53: =P53*N53 -> 0.33293509 | R53: =IFERROR(IF(B53="Reynolds",VLOOKUP(H53,'Yield & Time'!A:U,21,0),VLOOKUP(H53,'Yield & Time'!A:L,12,0)),0) -> 0.90531915 | S53: =R53*J53*E53*AO$1 -> 0.20225735 | T53: =(R53*Z53*J53*E53)/60 -> 0.0099585106 | U53: =IF(A52=A53,0,VLOOKUP(A53,'Packing Time'!A:F,6,0)) -> 0 | V53: =U53*AO$1 -> 0 | W53: =(U53*Z53)/60 -> 0 | X53: =((R53*J53*E53)+U53)*AO$1*AP53 -> 0.32361176 | Y53: =X53*Z53 -> 0.32361176 | Z53: 1 | AA53: =Z53*N53 -> 0.87614496 | AB53: =AA53*P53 -> 0.33293509 | AC53: =(((R53*J53*E53)+U53)/60)*Z53*AP53 -> 0.015933617 | AD53: =AC53*60*AO$1 -> 0.32361176 | AE53: =VLOOKUP(H53,'Yield & Time'!A:R,18,0) -> CHLORINE | AF53: =IFERROR(VLOOKUP(AE53,'Chemical Cost'!A:D,4,0),0) -> 0.027756518 | AG53: =AF53*N53/3 -> 0.0081062445 | AH53: =AF53*AA53/3 -> 0.0081062445 | AI53: =IFERROR((Q53*Z53)+(Z53*X53)+AH53,0) -> 0.66465309 | AJ53: =IFERROR(VLOOKUP(A53,'All Products'!A:F,6,0),0) -> 6.22 | AK53: =AJ53*Z53*J53 -> 2.0526 | AL53: 0.5 | AM53: 0.5 | AN53: #N/A | AP53: 1.6 | AQ53: =(((R53*J53*E53)+U53)/60)*AP53 -> 0.015933617 | AR53: =_xlfn.XLOOKUP(F53,'RM Cost'!A:A,'RM Cost'!S:S) -> 0 | AS53: =_xlfn.XLOOKUP(A53,[3]Sheet1!$B:$B,[3]Sheet1!$B:$B) -> #N/A
A54: 730ACS | B54: Reynolds | C54: CARROT MOOLI CHAYOTE MIX 1x2KG | D54: KG | E54: 2 | F54: =VLOOKUP(H54,'RM Used'!A:B,2,0) -> P0020 | G54: =IFERROR(VLOOKUP(F54,'RM Cost'!A:B,2,0),"") -> PALE BLUE BAG 430X430MM | H54: BLUE TINT BAGS ON A ROLL - SMALL | I54: =VLOOKUP(F54,'RM Used'!B:D,3,0) -> RM-PACKING | J54: 1 | K54: =IF(I54="RM-FOOD",J54*E54,"") | L54: =IFERROR(K54*Z54,0) -> 0 | M54: {=_xlfn.IFS(BOM!I54="RM-PACKING","100%",B54="Reynolds",VLOOKUP(H54,'Yield & Time'!A:V,22,0),BOM!B54="Dnata",VLOOKUP(BOM!H54,'Yield & Time'!A:M,13,0),B54="NK",VLOOKUP(H54,'Yield & Time'!A:X,24,0))} -> 100% | N54: 2 | O54: =VLOOKUP(H54,'RM Used'!A:E,5,0) -> Count | P54: =VLOOKUP(H54,'RM Used'!A:F,6,0) -> 0.09 | Q54: =P54*N54 -> 0.18 | R54: =IFERROR(IF(B54="Reynolds",VLOOKUP(H54,'Yield & Time'!A:U,21,0),VLOOKUP(H54,'Yield & Time'!A:L,12,0)),0) -> 0 | S54: =R54*J54*E54*AO$1 -> 0 | T54: =(R54*Z54*J54*E54)/60 -> 0 | U54: =IF(A53=A54,0,VLOOKUP(A54,'Packing Time'!A:F,6,0)) -> 0 | V54: =U54*AO$1 -> 0 | W54: =(U54*Z54)/60 -> 0 | X54: =((R54*J54*E54)+U54)*AO$1*AP54 -> 0 | Y54: =X54*Z54 -> 0 | Z54: 1 | AA54: =Z54*N54 -> 2 | AB54: =AA54*P54 -> 0.18 | AC54: =(((R54*J54*E54)+U54)/60)*Z54*AP54 -> 0 | AD54: =AC54*60*AO$1 -> 0 | AF54: =IFERROR(VLOOKUP(AE54,'Chemical Cost'!A:D,4,0),0) -> 0 | AG54: =AF54*N54/3 -> 0 | AH54: =AF54*AA54/3 -> 0 | AI54: =IFERROR((Q54*Z54)+(Z54*X54)+AH54,0) -> 0.18 | AJ54: =IFERROR(VLOOKUP(A54,'All Products'!A:F,6,0),0) -> 6.22 | AL54: 0.5 | AM54: 0.5 | AN54: #N/A | AP54: 1.6 | AQ54: =(((R54*J54*E54)+U54)/60)*AP54 -> 0 | AR54: =_xlfn.XLOOKUP(F54,'RM Cost'!A:A,'RM Cost'!S:S) -> 0 | AS54: =_xlfn.XLOOKUP(A54,[3]Sheet1!$B:$B,[3]Sheet1!$B:$B) -> #N/A
A55: 730ACS | B55: Reynolds | C55: CARROT MOOLI CHAYOTE MIX 1x2KG | D55: KG | E55: 2 | F55: =VLOOKUP(H55,'RM Used'!A:B,2,0) -> P0016 | G55: =IFERROR(VLOOKUP(F55,'RM Cost'!A:B,2,0),"") -> REY 40 30 BOX | H55: black box | I55: =VLOOKUP(F55,'RM Used'!B:D,3,0) -> RM-PACKING | J55: 1 | K55: =IF(I55="RM-FOOD",J55*E55,"") | L55: =IFERROR(K55*Z55,0) -> 0 | M55: {=_xlfn.IFS(BOM!I55="RM-PACKING","100%",B55="Reynolds",VLOOKUP(H55,'Yield & Time'!A:V,22,0),BOM!B55="Dnata",VLOOKUP(BOM!H55,'Yield & Time'!A:M,13,0),B55="NK",VLOOKUP(H55,'Yield & Time'!A:X,24,0))} -> 100% | N55: =IFERROR(IF(I55="RM-FOOD",(E55*J55)/M55,1),0) -> 1 | O55: =VLOOKUP(H55,'RM Used'!A:E,5,0) -> Count | P55: =VLOOKUP(H55,'RM Used'!A:F,6,0) -> 0.28 | Q55: =P55*N55 -> 0.28 | R55: =IFERROR(IF(B55="Reynolds",VLOOKUP(H55,'Yield & Time'!A:U,21,0),VLOOKUP(H55,'Yield & Time'!A:L,12,0)),0) -> 0 | S55: =R55*J55*E55*AO$1 -> 0 | T55: =(R55*Z55*J55*E55)/60 -> 0 | U55: =IF(A54=A55,0,VLOOKUP(A55,'Packing Time'!A:F,6,0)) -> 0 | V55: =U55*AO$1 -> 0 | W55: =(U55*Z55)/60 -> 0 | X55: =((R55*J55*E55)+U55)*AO$1*AP55 -> 0 | Y55: =X55*Z55 -> 0 | Z55: 1 | AA55: =Z55*N55 -> 1 | AB55: =AA55*P55 -> 0.28 | AC55: =(((R55*J55*E55)+U55)/60)*Z55*AP55 -> 0 | AD55: =AC55*60*AO$1 -> 0 | AF55: =IFERROR(VLOOKUP(AE55,'Chemical Cost'!A:D,4,0),0) -> 0 | AG55: =AF55*N55/3 -> 0 | AH55: =AF55*AA55/3 -> 0 | AI55: =IFERROR((Q55*Z55)+(Z55*X55)+AH55,0) -> 0.28 | AJ55: =IFERROR(VLOOKUP(A55,'All Products'!A:F,6,0),0) -> 6.22 | AL55: 0.5 | AM55: 0.5 | AN55: #N/A | AP55: 1.6 | AQ55: =(((R55*J55*E55)+U55)/60)*AP55 -> 0 | AR55: =_xlfn.XLOOKUP(F55,'RM Cost'!A:A,'RM Cost'!S:S) -> 0 | AS55: =_xlfn.XLOOKUP(A55,[3]Sheet1!$B:$B,[3]Sheet1!$B:$B) -> #N/A
A56: 280ACS | B56: Reynolds | C56: NHS PREP SLICED CARROT 2.5KG | D56: KG | E56: 2.5 | F56: =VLOOKUP(H56,'RM Used'!A:B,2,0) -> 032ACS | G56: =IFERROR(VLOOKUP(F56,'RM Cost'!A:B,2,0),"") -> RM - LRG PROCESSING CARROT X 1000KG | H56: Carrot - Sliced | I56: =VLOOKUP(F56,'RM Used'!B:D,3,0) -> RM-FOOD | J56: 1 | K56: =IF(I56="RM-FOOD",J56*E56,"") -> 2.5 | L56: =IFERROR(K56*Z56,0) -> 2.5 | M56: {=_xlfn.IFS(BOM!I56="RM-PACKING","100%",B56="Reynolds",VLOOKUP(H56,'Yield & Time'!A:V,22,0),BOM!B56="Dnata",VLOOKUP(BOM!H56,'Yield & Time'!A:M,13,0),B56="NK",VLOOKUP(H56,'Yield & Time'!A:X,24,0))} -> 0.71850998 | N56: =IFERROR(IF(I56="RM-FOOD",(E56*J56)/M56,1),0) -> 3.4794228 | O56: =VLOOKUP(H56,'RM Used'!A:E,5,0) -> KG | P56: =VLOOKUP(H56,'RM Used'!A:F,6,0) -> 0.38 | Q56: =P56*N56 -> 1.3221807 | R56: =IFERROR(IF(B56="Reynolds",VLOOKUP(H56,'Yield & Time'!A:U,21,0),VLOOKUP(H56,'Yield & Time'!A:L,12,0)),0) -> 1.7110958 | S56: =R56*J56*E56*AO$1 -> 1.4480148 | T56: =(R56*Z56*J56*E56)/60 -> 0.071295658 | U56: =IF(A55=A56,0,VLOOKUP(A56,'Packing Time'!A:F,6,0)) -> 0.875 | V56: =U56*AO$1 -> 0.2961875 | W56: =(U56*Z56)/60 -> 0.014583333 | X56: =((R56*J56*E56)+U56)*AO$1*AP56 -> 2.7907237 | Y56: =X56*Z56 -> 2.7907237 | Z56: 1 | AA56: =Z56*N56 -> 3.4794228 | AB56: =AA56*P56 -> 1.3221807 | AC56: =(((R56*J56*E56)+U56)/60)*Z56*AP56 -> 0.13740639 | AD56: =AC56*60*AO$1 -> 2.7907237 | AE56: =VLOOKUP(H56,'Yield & Time'!A:R,18,0) -> CHLORINE | AF56: =IFERROR(VLOOKUP(AE56,'Chemical Cost'!A:D,4,0),0) -> 0.027756518 | AG56: =AF56*N56/3 -> 0.03219222 | AH56: =AF56*AA56/3 -> 0.03219222 | AI56: =IFERROR((Q56*Z56)+(Z56*X56)+AH56,0) -> 4.1450966 | AJ56: =IFERROR(VLOOKUP(A56,'All Products'!A:F,6,0),0) -> 4.04 | AK56: =AJ56*Z56*J56 -> 4.04 | AL56: 1 | AN56: #N/A | AP56: 1.6 | AQ56: =(((R56*J56*E56)+U56)/60)*AP56 -> 0.13740639 | AR56: =_xlfn.XLOOKUP(F56,'RM Cost'!A:A,'RM Cost'!S:S) -> 0 | AS56: =_xlfn.XLOOKUP(A56,[3]Sheet1!$B:$B,[3]Sheet1!$B:$B) -> #N/A
A57: 280ACS | B57: Reynolds | C57: NHS PREP SLICED CARROT 2.5KG | D57: KG | E57: 2.5 | F57: =VLOOKUP(H57,'RM Used'!A:B,2,0) -> P0020 | G57: =IFERROR(VLOOKUP(F57,'RM Cost'!A:B,2,0),"") -> PALE BLUE BAG 430X430MM | H57: BLUE TINT BAGS ON A ROLL - SMALL | I57: =VLOOKUP(F57,'RM Used'!B:D,3,0) -> RM-PACKING | J57: 1 | K57: =IF(I57="RM-FOOD",J57*E57,"") | L57: =IFERROR(K57*Z57,0) -> 0 | M57: {=_xlfn.IFS(BOM!I57="RM-PACKING","100%",B57="Reynolds",VLOOKUP(H57,'Yield & Time'!A:V,22,0),BOM!B57="Dnata",VLOOKUP(BOM!H57,'Yield & Time'!A:M,13,0),B57="NK",VLOOKUP(H57,'Yield & Time'!A:X,24,0))} -> 100% | N57: =IFERROR(IF(I57="RM-FOOD",(E57*J57)/M57,1),0) -> 1 | O57: =VLOOKUP(H57,'RM Used'!A:E,5,0) -> Count | P57: =VLOOKUP(H57,'RM Used'!A:F,6,0) -> 0.09 | Q57: =P57*N57 -> 0.09 | R57: =IFERROR(IF(B57="Reynolds",VLOOKUP(H57,'Yield & Time'!A:U,21,0),VLOOKUP(H57,'Yield & Time'!A:L,12,0)),0) -> 0 | S57: =R57*J57*E57*AO$1 -> 0 | T57: =(R57*Z57*J57*E57)/60 -> 0 | U57: =IF(A56=A57,0,VLOOKUP(A57,'Packing Time'!A:F,6,0)) -> 0 | V57: =U57*AO$1 -> 0 | W57: =(U57*Z57)/60 -> 0 | X57: =((R57*J57*E57)+U57)*AO$1*AP57 -> 0 | Y57: =X57*Z57 -> 0 | Z57: 1 | AA57: =Z57*N57 -> 1 | AB57: =AA57*P57 -> 0.09 | AC57: =(((R57*J57*E57)+U57)/60)*Z57*AP57 -> 0 | AD57: =AC57*60*AO$1 -> 0 | AF57: =IFERROR(VLOOKUP(AE57,'Chemical Cost'!A:D,4,0),0) -> 0 | AG57: =AF57*N57/3 -> 0 | AH57: =AF57*AA57/3 -> 0 | AI57: =IFERROR((Q57*Z57)+(Z57*X57)+AH57,0) -> 0.09 | AJ57: =IFERROR(VLOOKUP(A57,'All Products'!A:F,6,0),0) -> 4.04 | AL57: 1 | AN57: #N/A | AP57: 1.6 | AQ57: =(((R57*J57*E57)+U57)/60)*AP57 -> 0 | AR57: =_xlfn.XLOOKUP(F57,'RM Cost'!A:A,'RM Cost'!S:S) -> 0 | AS57: =_xlfn.XLOOKUP(A57,[3]Sheet1!$B:$B,[3]Sheet1!$B:$B) -> #N/A
A58: 280ACS | B58: Reynolds | C58: NHS PREP SLICED CARROT 2.5KG | D58: KG | E58: 2.5 | F58: =VLOOKUP(H58,'RM Used'!A:B,2,0) -> P0016 | G58: =IFERROR(VLOOKUP(F58,'RM Cost'!A:B,2,0),"") -> REY 40 30 BOX | H58: black box | I58: =VLOOKUP(F58,'RM Used'!B:D,3,0) -> RM-PACKING | J58: 1 | K58: =IF(I58="RM-FOOD",J58*E58,"") | L58: =IFERROR(K58*Z58,0) -> 0 | M58: {=_xlfn.IFS(BOM!I58="RM-PACKING","100%",B58="Reynolds",VLOOKUP(H58,'Yield & Time'!A:V,22,0),BOM!B58="Dnata",VLOOKUP(BOM!H58,'Yield & Time'!A:M,13,0),B58="NK",VLOOKUP(H58,'Yield & Time'!A:X,24,0))} -> 100% | N58: =IFERROR(IF(I58="RM-FOOD",(E58*J58)/M58,1),0) -> 1 | O58: =VLOOKUP(H58,'RM Used'!A:E,5,0) -> Count | P58: =VLOOKUP(H58,'RM Used'!A:F,6,0) -> 0.28 | Q58: =P58*N58 -> 0.28 | R58: =IFERROR(IF(B58="Reynolds",VLOOKUP(H58,'Yield & Time'!A:U,21,0),VLOOKUP(H58,'Yield & Time'!A:L,12,0)),0) -> 0 | S58: =R58*J58*E58*AO$1 -> 0 | T58: =(R58*Z58*J58*E58)/60 -> 0 | U58: =IF(A57=A58,0,VLOOKUP(A58,'Packing Time'!A:F,6,0)) -> 0 | V58: =U58*AO$1 -> 0 | W58: =(U58*Z58)/60 -> 0 | X58: =((R58*J58*E58)+U58)*AO$1*AP58 -> 0 | Y58: =X58*Z58 -> 0 | Z58: 1 | AA58: =Z58*N58 -> 1 | AB58: =AA58*P58 -> 0.28 | AC58: =(((R58*J58*E58)+U58)/60)*Z58*AP58 -> 0 | AD58: =AC58*60*AO$1 -> 0 | AF58: =IFERROR(VLOOKUP(AE58,'Chemical Cost'!A:D,4,0),0) -> 0 | AG58: =AF58*N58/3 -> 0 | AH58: =AF58*AA58/3 -> 0 | AI58: =IFERROR((Q58*Z58)+(Z58*X58)+AH58,0) -> 0.28 | AJ58: =IFERROR(VLOOKUP(A58,'All Products'!A:F,6,0),0) -> 4.04 | AL58: 1 | AN58: #N/A | AP58: 1.6 | AQ58: =(((R58*J58*E58)+U58)/60)*AP58 -> 0 | AR58: =_xlfn.XLOOKUP(F58,'RM Cost'!A:A,'RM Cost'!S:S) -> 0 | AS58: =_xlfn.XLOOKUP(A58,[3]Sheet1!$B:$B,[3]Sheet1!$B:$B) -> #N/A
A59: 490ACS | B59: Reynolds | C59: NHS CARROTS GRATED 1 X 1KG | D59: KG | E59: 1 | F59: =VLOOKUP(H59,'RM Used'!A:B,2,0) -> 032ACS | G59: =IFERROR(VLOOKUP(F59,'RM Cost'!A:B,2,0),"") -> RM - LRG PROCESSING CARROT X 1000KG | H59: Carrot - Julienne | I59: =VLOOKUP(F59,'RM Used'!B:D,3,0) -> RM-FOOD | J59: 1 | K59: =IF(I59="RM-FOOD",J59*E59,"") -> 1 | L59: =IFERROR(K59*Z59,0) -> 1 | M59: {=_xlfn.IFS(BOM!I59="RM-PACKING","100%",B59="Reynolds",VLOOKUP(H59,'Yield & Time'!A:V,22,0),BOM!B59="Dnata",VLOOKUP(BOM!H59,'Yield & Time'!A:M,13,0),B59="NK",VLOOKUP(H59,'Yield & Time'!A:X,24,0))} -> 0.7533 | N59: =IFERROR(IF(I59="RM-FOOD",(E59*J59)/M59,1),0) -> 1.3274924 | O59: =VLOOKUP(H59,'RM Used'!A:E,5,0) -> KG | P59: =VLOOKUP(H59,'RM Used'!A:F,6,0) -> 0.38 | Q59: =P59*N59 -> 0.5044471 | R59: =IFERROR(IF(B59="Reynolds",VLOOKUP(H59,'Yield & Time'!A:U,21,0),VLOOKUP(H59,'Yield & Time'!A:L,12,0)),0) -> 0.90531915 | S59: =R59*J59*E59*AO$1 -> 0.30645053 | T59: =(R59*Z59*J59*E59)/60 -> 0.015088652 | U59: =IF(A58=A59,0,VLOOKUP(A59,'Packing Time'!A:F,6,0)) -> 0.55 | V59: =U59*AO$1 -> 0.186175 | W59: =(U59*Z59)/60 -> 0.0091666667 | X59: =((R59*J59*E59)+U59)*AO$1*AP59 -> 0.78820085 | Y59: =X59*Z59 -> 0.78820085 | Z59: 1 | AA59: =Z59*N59 -> 1.3274924 | AB59: =AA59*P59 -> 0.5044471 | AC59: =(((R59*J59*E59)+U59)/60)*Z59*AP59 -> 0.038808511 | AD59: =AC59*60*AO$1 -> 0.78820085 | AE59: =VLOOKUP(H59,'Yield & Time'!A:R,18,0) -> CHLORINE | AF59: =IFERROR(VLOOKUP(AE59,'Chemical Cost'!A:D,4,0),0) -> 0.027756518 | AG59: =AF59*N59/3 -> 0.012282189 | AH59: =AF59*AA59/3 -> 0.012282189 | AI59: =IFERROR((Q59*Z59)+(Z59*X59)+AH59,0) -> 1.3049301 | AJ59: =IFERROR(VLOOKUP(A59,'All Products'!A:F,6,0),0) -> 1.77 | AK59: =AJ59*Z59*J59 -> 1.77 | AM59: 1 | AN59: #N/A | AP59: 1.6 | AQ59: =(((R59*J59*E59)+U59)/60)*AP59 -> 0.038808511 | AR59: =_xlfn.XLOOKUP(F59,'RM Cost'!A:A,'RM Cost'!S:S) -> 0 | AS59: =_xlfn.XLOOKUP(A59,[3]Sheet1!$B:$B,[3]Sheet1!$B:$B) -> #N/A
A60: 490ACS | B60: Reynolds | C60: NHS CARROTS GRATED 1 X 1KG | D60: KG | E60: 1 | F60: =VLOOKUP(H60,'RM Used'!A:B,2,0) -> P0001 | G60: =IFERROR(VLOOKUP(F60,'RM Cost'!A:B,2,0),"") -> SOL 30EL # PPLUS 630x1000 BLUE -1 | H60: SOL 30EL # PPLUS 630x1000 BLUE -1 | I60: =VLOOKUP(F60,'RM Used'!B:D,3,0) -> RM-PACKING | J60: 1 | K60: =IF(I60="RM-FOOD",J60*E60,"") | L60: =IFERROR(K60*Z60,0) -> 0 | M60: {=_xlfn.IFS(BOM!I60="RM-PACKING","100%",B60="Reynolds",VLOOKUP(H60,'Yield & Time'!A:V,22,0),BOM!B60="Dnata",VLOOKUP(BOM!H60,'Yield & Time'!A:M,13,0),B60="NK",VLOOKUP(H60,'Yield & Time'!A:X,24,0))} -> 100% | N60: =IFERROR(IF(I60="RM-FOOD",(E60*J60)/M60,1),0) -> 1 | O60: =VLOOKUP(H60,'RM Used'!A:E,5,0) -> Count | P60: =VLOOKUP(H60,'RM Used'!A:F,6,0) -> 0.08 | Q60: =P60*N60 -> 0.08 | R60: =IFERROR(IF(B60="Reynolds",VLOOKUP(H60,'Yield & Time'!A:U,21,0),VLOOKUP(H60,'Yield & Time'!A:L,12,0)),0) -> 0 | S60: =R60*J60*E60*AO$1 -> 0 | T60: =(R60*Z60*J60*E60)/60 -> 0 | U60: =IF(A59=A60,0,VLOOKUP(A60,'Packing Time'!A:F,6,0)) -> 0 | V60: =U60*AO$1 -> 0 | W60: =(U60*Z60)/60 -> 0 | X60: =((R60*J60*E60)+U60)*AO$1*AP60 -> 0 | Y60: =X60*Z60 -> 0 | Z60: 1 | AA60: =Z60*N60 -> 1 | AB60: =AA60*P60 -> 0.08 | AC60: =(((R60*J60*E60)+U60)/60)*Z60*AP60 -> 0 | AD60: =AC60*60*AO$1 -> 0 | AF60: =IFERROR(VLOOKUP(AE60,'Chemical Cost'!A:D,4,0),0) -> 0 | AG60: =AF60*N60/3 -> 0 | AH60: =AF60*AA60/3 -> 0 | AI60: =IFERROR((Q60*Z60)+(Z60*X60)+AH60,0) -> 0.08 | AJ60: =IFERROR(VLOOKUP(A60,'All Products'!A:F,6,0),0) -> 1.77 | AM60: 1 | AN60: #N/A | AP60: 1.6 | AQ60: =(((R60*J60*E60)+U60)/60)*AP60 -> 0 | AR60: =_xlfn.XLOOKUP(F60,'RM Cost'!A:A,'RM Cost'!S:S) -> 0 | AS60: =_xlfn.XLOOKUP(A60,[3]Sheet1!$B:$B,[3]Sheet1!$B:$B) -> #N/A
A61: 490ACS | B61: Reynolds | C61: NHS CARROTS GRATED 1 X 1KG | D61: KG | E61: 1 | F61: =VLOOKUP(H61,'RM Used'!A:B,2,0) -> P0016 | G61: =IFERROR(VLOOKUP(F61,'RM Cost'!A:B,2,0),"") -> REY 40 30 BOX | H61: black box | I61: =VLOOKUP(F61,'RM Used'!B:D,3,0) -> RM-PACKING | J61: 1 | K61: =IF(I61="RM-FOOD",J61*E61,"") | L61: =IFERROR(K61*Z61,0) -> 0 | M61: {=_xlfn.IFS(BOM!I61="RM-PACKING","100%",B61="Reynolds",VLOOKUP(H61,'Yield & Time'!A:V,22,0),BOM!B61="Dnata",VLOOKUP(BOM!H61,'Yield & Time'!A:M,13,0),B61="NK",VLOOKUP(H61,'Yield & Time'!A:X,24,0))} -> 100% | N61: =IFERROR(IF(I61="RM-FOOD",(E61*J61)/M61,1),0) -> 1 | O61: =VLOOKUP(H61,'RM Used'!A:E,5,0) -> Count | P61: =VLOOKUP(H61,'RM Used'!A:F,6,0) -> 0.28 | Q61: =P61*N61 -> 0.28 | R61: =IFERROR(IF(B61="Reynolds",VLOOKUP(H61,'Yield & Time'!A:U,21,0),VLOOKUP(H61,'Yield & Time'!A:L,12,0)),0) -> 0 | S61: =R61*J61*E61*AO$1 -> 0 | T61: =(R61*Z61*J61*E61)/60 -> 0 | U61: =IF(A60=A61,0,VLOOKUP(A61,'Packing Time'!A:F,6,0)) -> 0 | V61: =U61*AO$1 -> 0 | W61: =(U61*Z61)/60 -> 0 | X61: =((R61*J61*E61)+U61)*AO$1*AP61 -> 0 | Y61: =X61*Z61 -> 0 | Z61: 1 | AA61: =Z61*N61 -> 1 | AB61: =AA61*P61 -> 0.28 | AC61: =(((R61*J61*E61)+U61)/60)*Z61*AP61 -> 0 | AD61: =AC61*60*AO$1 -> 0 | AF61: =IFERROR(VLOOKUP(AE61,'Chemical Cost'!A:D,4,0),0) -> 0 | AG61: =AF61*N61/3 -> 0 | AH61: =AF61*AA61/3 -> 0 | AI61: =IFERROR((Q61*Z61)+(Z61*X61)+AH61,0) -> 0.28 | AJ61: =IFERROR(VLOOKUP(A61,'All Products'!A:F,6,0),0) -> 1.77 | AM61: 1 | AN61: #N/A | AP61: 1.6 | AQ61: =(((R61*J61*E61)+U61)/60)*AP61 -> 0 | AR61: =_xlfn.XLOOKUP(F61,'RM Cost'!A:A,'RM Cost'!S:S) -> 0 | AS61: =_xlfn.XLOOKUP(A61,[3]Sheet1!$B:$B,[3]Sheet1!$B:$B) -> #N/A
A62: 281ACS | B62: Reynolds | C62: NHS DICED CARROT 10MM 2.5KG | D62: KG | E62: 2.5 | F62: =VLOOKUP(H62,'RM Used'!A:B,2,0) -> 032ACS | G62: =IFERROR(VLOOKUP(F62,'RM Cost'!A:B,2,0),"") -> RM - LRG PROCESSING CARROT X 1000KG | H62: Carrot - Peeled & Diced 10 mm | I62: =VLOOKUP(F62,'RM Used'!B:D,3,0) -> RM-FOOD | J62: 1 | K62: =IF(I62="RM-FOOD",J62*E62,"") -> 2.5 | L62: =IFERROR(K62*Z62,0) -> 2.5 | M62: {=_xlfn.IFS(BOM!I62="RM-PACKING","100%",B62="Reynolds",VLOOKUP(H62,'Yield & Time'!A:V,22,0),BOM!B62="Dnata",VLOOKUP(BOM!H62,'Yield & Time'!A:M,13,0),B62="NK",VLOOKUP(H62,'Yield & Time'!A:X,24,0))} -> 0.71222564 | N62: =IFERROR(IF(I62="RM-FOOD",(E62*J62)/M62,1),0) -> 3.5101236 | O62: =VLOOKUP(H62,'RM Used'!A:E,5,0) -> KG | P62: =VLOOKUP(H62,'RM Used'!A:F,6,0) -> 0.38 | Q62: =P62*N62 -> 1.333847 | R62: =IFERROR(IF(B62="Reynolds",VLOOKUP(H62,'Yield & Time'!A:U,21,0),VLOOKUP(H62,'Yield & Time'!A:L,12,0)),0) -> 1.2525214 | S62: =R62*J62*E62*AO$1 -> 1.0599463 | T62: =(R62*Z62*J62*E62)/60 -> 0.052188393 | U62: =IF(A61=A62,0,VLOOKUP(A62,'Packing Time'!A:F,6,0)) -> 0.875 | V62: =U62*AO$1 -> 0.2961875 | W62: =(U62*Z62)/60 -> 0.014583333 | X62: =((R62*J62*E62)+U62)*AO$1*AP62 -> 2.169814 | Y62: =X62*Z62 -> 2.169814 | Z62: 1 | AA62: =Z62*N62 -> 3.5101236 | AB62: =AA62*P62 -> 1.333847 | AC62: =(((R62*J62*E62)+U62)/60)*Z62*AP62 -> 0.10683476 | AD62: =AC62*60*AO$1 -> 2.169814 | AF62: =IFERROR(VLOOKUP(AE62,'Chemical Cost'!A:D,4,0),0) -> 0 | AG62: =AF62*N62/3 -> 0 | AH62: =AF62*AA62/3 -> 0 | AI62: =IFERROR((Q62*Z62)+(Z62*X62)+AH62,0) -> 3.503661 | AJ62: =IFERROR(VLOOKUP(A62,'All Products'!A:F,6,0),0) -> 4.02 | AK62: =AJ62*Z62*J62 -> 4.02 | AL62: 1 | AN62: #N/A | AP62: 1.6 | AQ62: =(((R62*J62*E62)+U62)/60)*AP62 -> 0.10683476 | AR62: =_xlfn.XLOOKUP(F62,'RM Cost'!A:A,'RM Cost'!S:S) -> 0 | AS62: =_xlfn.XLOOKUP(A62,[3]Sheet1!$B:$B,[3]Sheet1!$B:$B) -> #N/A
A63: 281ACS | B63: Reynolds | C63: NHS DICED CARROT 10MM 2.5KG | D63: KG | E63: 2.5 | F63: =VLOOKUP(H63,'RM Used'!A:B,2,0) -> P0020 | G63: =IFERROR(VLOOKUP(F63,'RM Cost'!A:B,2,0),"") -> PALE BLUE BAG 430X430MM | H63: BLUE TINT BAGS ON A ROLL - SMALL | I63: =VLOOKUP(F63,'RM Used'!B:D,3,0) -> RM-PACKING | J63: 1 | K63: =IF(I63="RM-FOOD",J63*E63,"") | L63: =IFERROR(K63*Z63,0) -> 0 | M63: {=_xlfn.IFS(BOM!I63="RM-PACKING","100%",B63="Reynolds",VLOOKUP(H63,'Yield & Time'!A:V,22,0),BOM!B63="Dnata",VLOOKUP(BOM!H63,'Yield & Time'!A:M,13,0),B63="NK",VLOOKUP(H63,'Yield & Time'!A:X,24,0))} -> 100% | N63: =IFERROR(IF(I63="RM-FOOD",(E63*J63)/M63,1),0) -> 1 | O63: =VLOOKUP(H63,'RM Used'!A:E,5,0) -> Count | P63: =VLOOKUP(H63,'RM Used'!A:F,6,0) -> 0.09 | Q63: =P63*N63 -> 0.09 | R63: =IFERROR(IF(B63="Reynolds",VLOOKUP(H63,'Yield & Time'!A:U,21,0),VLOOKUP(H63,'Yield & Time'!A:L,12,0)),0) -> 0 | S63: =R63*J63*E63*AO$1 -> 0 | T63: =(R63*Z63*J63*E63)/60 -> 0 | U63: =IF(A62=A63,0,VLOOKUP(A63,'Packing Time'!A:F,6,0)) -> 0 | V63: =U63*AO$1 -> 0 | W63: =(U63*Z63)/60 -> 0 | X63: =((R63*J63*E63)+U63)*AO$1*AP63 -> 0 | Y63: =X63*Z63 -> 0 | Z63: 1 | AA63: =Z63*N63 -> 1 | AB63: =AA63*P63 -> 0.09 | AC63: =(((R63*J63*E63)+U63)/60)*Z63*AP63 -> 0 | AD63: =AC63*60*AO$1 -> 0 | AF63: =IFERROR(VLOOKUP(AE63,'Chemical Cost'!A:D,4,0),0) -> 0 | AG63: =AF63*N63/3 -> 0 | AH63: =AF63*AA63/3 -> 0 | AI63: =IFERROR((Q63*Z63)+(Z63*X63)+AH63,0) -> 0.09 | AJ63: =IFERROR(VLOOKUP(A63,'All Products'!A:F,6,0),0) -> 4.02 | AL63: 1 | AN63: #N/A | AP63: 1.6 | AQ63: =(((R63*J63*E63)+U63)/60)*AP63 -> 0 | AR63: =_xlfn.XLOOKUP(F63,'RM Cost'!A:A,'RM Cost'!S:S) -> 0 | AS63: =_xlfn.XLOOKUP(A63,[3]Sheet1!$B:$B,[3]Sheet1!$B:$B) -> #N/A
A64: 281ACS | B64: Reynolds | C64: NHS DICED CARROT 10MM 2.5KG | D64: KG | E64: 2.5 | F64: =VLOOKUP(H64,'RM Used'!A:B,2,0) -> P0016 | G64: =IFERROR(VLOOKUP(F64,'RM Cost'!A:B,2,0),"") -> REY 40 30 BOX | H64: black box | I64: =VLOOKUP(F64,'RM Used'!B:D,3,0) -> RM-PACKING | J64: 1 | K64: =IF(I64="RM-FOOD",J64*E64,"") | L64: =IFERROR(K64*Z64,0) -> 0 | M64: {=_xlfn.IFS(BOM!I64="RM-PACKING","100%",B64="Reynolds",VLOOKUP(H64,'Yield & Time'!A:V,22,0),BOM!B64="Dnata",VLOOKUP(BOM!H64,'Yield & Time'!A:M,13,0),B64="NK",VLOOKUP(H64,'Yield & Time'!A:X,24,0))} -> 100% | N64: =IFERROR(IF(I64="RM-FOOD",(E64*J64)/M64,1),0) -> 1 | O64: =VLOOKUP(H64,'RM Used'!A:E,5,0) -> Count | P64: =VLOOKUP(H64,'RM Used'!A:F,6,0) -> 0.28 | Q64: =P64*N64 -> 0.28 | R64: =IFERROR(IF(B64="Reynolds",VLOOKUP(H64,'Yield & Time'!A:U,21,0),VLOOKUP(H64,'Yield & Time'!A:L,12,0)),0) -> 0 | S64: =R64*J64*E64*AO$1 -> 0 | T64: =(R64*Z64*J64*E64)/60 -> 0 | U64: =IF(A63=A64,0,VLOOKUP(A64,'Packing Time'!A:F,6,0)) -> 0 | V64: =U64*AO$1 -> 0 | W64: =(U64*Z64)/60 -> 0 | X64: =((R64*J64*E64)+U64)*AO$1*AP64 -> 0 | Y64: =X64*Z64 -> 0 | Z64: 1 | AA64: =Z64*N64 -> 1 | AB64: =AA64*P64 -> 0.28 | AC64: =(((R64*J64*E64)+U64)/60)*Z64*AP64 -> 0 | AD64: =AC64*60*AO$1 -> 0 | AF64: =IFERROR(VLOOKUP(AE64,'Chemical Cost'!A:D,4,0),0) -> 0 | AG64: =AF64*N64/3 -> 0 | AH64: =AF64*AA64/3 -> 0 | AI64: =IFERROR((Q64*Z64)+(Z64*X64)+AH64,0) -> 0.28 | AJ64: =IFERROR(VLOOKUP(A64,'All Products'!A:F,6,0),0) -> 4.02 | AL64: 1 | AN64: #N/A | AP64: 1.6 | AQ64: =(((R64*J64*E64)+U64)/60)*AP64 -> 0 | AR64: =_xlfn.XLOOKUP(F64,'RM Cost'!A:A,'RM Cost'!S:S) -> 0 | AS64: =_xlfn.XLOOKUP(A64,[3]Sheet1!$B:$B,[3]Sheet1!$B:$B) -> #N/A
A65: 1256CS | B65: Reynolds | C65: PRP DRY C/SLAW MX REDONION 4X1 | D65: KG | E65: 4 | F65: =VLOOKUP(H65,'RM Used'!A:B,2,0) -> S3997CS | G65: =IFERROR(VLOOKUP(F65,'RM Cost'!A:B,2,0),"") -> RM - DECORE WHITE CABBAGE 1/3 1200KG | H65: Cabbage White - Sliced | I65: =VLOOKUP(F65,'RM Used'!B:D,3,0) -> RM-FOOD | J65: 0.7 | K65: =IF(I65="RM-FOOD",J65*E65,"") -> 2.8 | L65: =IFERROR(K65*Z65,0) -> 2.8 | M65: {=_xlfn.IFS(BOM!I65="RM-PACKING","100%",B65="Reynolds",VLOOKUP(H65,'Yield & Time'!A:V,22,0),BOM!B65="Dnata",VLOOKUP(BOM!H65,'Yield & Time'!A:M,13,0),B65="NK",VLOOKUP(H65,'Yield & Time'!A:X,24,0))} -> 0.77222322 | N65: =IFERROR(IF(I65="RM-FOOD",(E65*J65)/M65,1),0) -> 3.6258946 | O65: =VLOOKUP(H65,'RM Used'!A:E,5,0) -> KG | P65: =VLOOKUP(H65,'RM Used'!A:F,6,0) -> 0.34 | Q65: =P65*N65 -> 1.2328042 | R65: =IFERROR(IF(B65="Reynolds",VLOOKUP(H65,'Yield & Time'!A:U,21,0),VLOOKUP(H65,'Yield & Time'!A:L,12,0)),0) -> 0.82773481 | S65: =R65*J65*E65*AO$1 -> 0.78452705 | T65: =(R65*Z65*J65*E65)/60 -> 0.038627624 | U65: =IF(A64=A65,0,VLOOKUP(A65,'Packing Time'!A:F,6,0)) -> 2.58 | V65: =U65*AO$1 -> 0.87333 | W65: =(U65*Z65)/60 -> 0.043 | X65: =((R65*J65*E65)+U65)*AO$1*AP65 -> 2.3209999 | Y65: =X65*Z65 -> 2.3209999 | Z65: 1 | AA65: =Z65*N65 -> 3.6258946 | AB65: =AA65*P65 -> 1.2328042 | AC65: =(((R65*J65*E65)+U65)/60)*Z65*AP65 -> 0.11427867 | AD65: =AC65*60*AO$1 -> 2.3209999 | AE65: =VLOOKUP(H65,'Yield & Time'!A:R,18,0) -> CHLORINE | AF65: =IFERROR(VLOOKUP(AE65,'Chemical Cost'!A:D,4,0),0) -> 0.027756518 | AG65: =AF65*N65/3 -> 0.033547403 | AH65: =AF65*AA65/3 -> 0.033547403 | AI65: =IFERROR((Q65*Z65)+(Z65*X65)+AH65,0) -> 3.5873514 | AJ65: =IFERROR(VLOOKUP(A65,'All Products'!A:F,6,0),0) -> 5.73 | AK65: =AJ65*Z65*J65 -> 4.011 | AL65: 0.8 | AM65: 0.2 | AN65: #N/A | AP65: 1.4 | AQ65: =(((R65*J65*E65)+U65)/60)*AP65 -> 0.11427867 | AR65: =_xlfn.XLOOKUP(F65,'RM Cost'!A:A,'RM Cost'!S:S) -> 0.29914854 | AS65: =_xlfn.XLOOKUP(A65,[3]Sheet1!$B:$B,[3]Sheet1!$B:$B) -> 1256CS | AT65: =_xlfn.XLOOKUP(H65,'Yield & Time'!A:A,'Yield & Time'!O:O) -> Yes
